Workbook
Name ccEtq: OFFSET(Calculos!$CZ$6,0,0,ccN,1)
Name ccLbl: OFFSET(Calculos!$AK$10,0,0,ccN,1)
Name ccN: MAX(1,COUNTA(Calculos!$AK$10:$AK$20))
Name ccP: OFFSET(Calculos!$DB$6,0,0,ccN,1)
Name ccPpto: OFFSET(Calculos!$AM$10,0,0,ccN,1)
Name ccR: OFFSET(Calculos!$DA$6,0,0,ccN,1)
Name ccReal: OFFSET(Calculos!$AL$10,0,0,ccN,1)
Name ccVar: OFFSET(Calculos!$DC$6,0,0,ccN,1)
Name cuentaLbl: OFFSET(Calculos!$F$7,0,0,cuentaN,1)
Name cuentaN: MAX(1,COUNTA(Calculos!$F$7:$F$47))
Name cuentaPpto: OFFSET(Calculos!$H$7,0,0,cuentaN,1)
Name cuentaReal: OFFSET(Calculos!$G$7,0,0,cuentaN,1)
Name linTabLbl: OFFSET(Calculos!$O$6,0,0,linTabN,1)
Name linTabN: MAX(1,COUNTA(Calculos!$O$6:$O$16))
Name pCorte: Seguimiento!$L$6
Name pIPC: 'PPTO 2027'!$G$7
Name pMesCorte: Seguimiento!$K$6
Name pMetaGastosIngresos: Calculos!$DI$8
Name pMetaMargenBruto: Calculos!$DI$5
Name pMetaMargenEbitda: Calculos!$DI$6
Name pMetaMargenNeto: Calculos!$DI$7
Name pSalario: 'PPTO 2027'!$G$8
Name pTasaRenta: 'PPTO 2027'!$G$59
Name rSegResumen: Seguimiento!$B$8:$F$21
Name SegmentaciónDeDatos_LíneaTab: #N/A

Sheet Guía
K7: 1 · PEGA TU REAL 2026
K8: Ve a la hoja PPTO 2027: es tu estado de resultados completo. Despliega los meses con el botón + del esquema; las celdas lila de Ene 26 a Dic 26 son tu real: reemplaza las cifras de ejemplo por las tuyas, cuenta por cuenta. Para agregar una cuenta, inserta una fila dentro de su bloque. Si el año no ha cerrado, usa real hasta el último cierre y un estimado para los meses que faltan. No incluyas el impuesto de renta: se calcula con la tasa de los supuestos.
K10: 2 · DEFINE LOS SUPUESTOS, EN LA MISMA HOJA
K11: Arriba solo hay dos supuestos generales: IPC y aumento salarial (las cuentas indexadas y la nómina los toman solas). El resto va implícito en la columna Crec. 2027 de cada cuenta: ventas (volumen × precio), costo de mercancía, deuda, una campaña o un recorte. La tasa de renta está en la fila Impuesto de renta. El presupuesto de cada mes es el mismo mes del 2026 por su crecimiento: conserva la estacionalidad.
K13: 3 · SENSIBILIZA SIN SALIR DE LA HOJA
K14: Todo se recalcula al instante. A la derecha de cada cuenta, subtotal y margen ves la variación del año y de cada trimestre (en pesos y en %), con barras, la tendencia mes a mes y el peso sobre los ingresos. Verde = mejora, rojo = empeora: en ingresos y utilidades, subir es verde; en costos y gastos, subir es rojo.
K16: 4 · LEE EL TABLERO
K17: Las pestañas cambian la línea del P&G en la tarjeta y en el gráfico mes a mes. La cascada muestra qué bloque explica el salto de utilidad y el Estado de resultados completo aparece como imagen vinculada. Las tablas de cuentas y centros de costo son tablas dinámicas: se actualizan al abrir el archivo o con Datos > Actualizar todo.
K19: 5 · HAZLE SEGUIMIENTO AL AÑO
K20: En la hoja Seguimiento pega tu real 2027 mes a mes (hoy trae cifras sintéticas de ejemplo) y elige el mes de corte. Verás el acumulado real contra el presupuesto de ese mismo periodo, por cuenta y por bloque del P&G, con semáforo. El resumen también sale en el tablero.
K22: LÍNEAS QUE RECONOCE EL TABLERO
K23: Ingresos operacionales, Costo de ventas, Gastos de administración, Gastos de ventas, Gastos financieros, Otros ingresos no operacionales y Otros gastos no operacionales. Usa esos nombres exactos en la columna Línea. Los centros de costo son libres. Si agregas o quitas cuentas, hazlo igual en la tabla de Seguimiento.
... K29: Hecho por Mauricio Escobar · arquitecto de decisiones financieras. Empresa y datos de ejemplo, ficticios.

Sheet Tablero

Sheet PPTO 2027
B2: PRESUPUESTO 2027 · ESTADO DE RESULTADOS REAL 2026 Y PRESUPUESTO 2027
B3: Celdas lila = editables: real 2026 mes a mes y el crecimiento 2027 de cada cuenta. Ppto 2027 = mismo mes del 2026 × (1 + crecimiento). Todo se recalcula al instante. Millones de pesos · datos de ejemplo.
B4: ← Volver al tablero
B6: SUPUESTOS GENERALES 2027
B7: Inflación (IPC) 2027 | G7: 0.04 | I7: Aplica a arriendos, servicios, honorarios y gastos indexados.
B8: Aumento salarial 2027 | G8: 0.07 | I8: Aplica a toda la nómina.
B9: El resto del crecimiento (volumen, precio, costo unitario, deuda) va implícito en la columna Crec. 2027 de cada cuenta: cámbialo ahí para sensibilizar.
I11: REAL | V11: PPTO | AJ11: SENSIBILIZACIÓN · 2027 contra 2026
B12: Cuenta | C12: Línea | D12: Tipo | E12: Centro de costo | F12: Driver | G12: Crec. 2027 | I12: Ene 26 | J12: Feb 26 | K12: Mar 26 | L12: Abr 26 | M12: May 26 | N12: Jun 26 | O12: Jul 26 | P12: Ago 26 | Q12: Sep 26 | R12: Oct 26 | S12: Nov 26 | T12: Dic 26 | U12: 2026 | V12: Ene 27 | W12: Feb 27 | X12: Mar 27 | Y12: Abr 27 | Z12: May 27 | AA12: Jun 27 | AB12: Jul 27 | AC12: Ago 27 | AD12: Sep 27 | AE12: Oct 27 | AF12: Nov 27 | AG12: Dic 27 | AH12: 2027 | AJ12: Var $ | AK12: Var % | AL12: Var $ Q1 | AM12: Var $ Q2 | AN12: Var $ Q3 | AO12: Var $ Q4 | AP12: Var % Q1 | AQ12: Var % Q2 | AR12: Var % Q3 | AS12: Var % Q4 | AT12: Tendencia 2027 | AU12: Peso 2026 | AV12: Peso 2027 | AW12: Δ peso pp
B13: INGRESOS OPERACIONALES
B14: Venta de mercancía nacional | C14: Ingresos operacionales | D14: Ingreso | E14: Comercial | F14: Ventas | G14: 0.113 | I14: 640000000 | J14: 680000000 | K14: 760000000 | L14: 760000000 | M14: 800000000 | N14: 800000000 | O14: 800000000 | P14: 840000000 | Q14: 800000000 | R14: 840000000 | S14: 920000000 | T14: 960000000 | U14: =SUM(I14:T14) -> 9600000000 | V14: =I14*(1+$G14) -> 712320000 | W14: =J14*(1+$G14) -> 756840000 | X14: =K14*(1+$G14) -> 845880000 | Y14: =L14*(1+$G14) -> 845880000 | Z14: =M14*(1+$G14) -> 890400000 | AA14: =N14*(1+$G14) -> 890400000 | AB14: =O14*(1+$G14) -> 890400000 | AC14: =P14*(1+$G14) -> 934920000 | ... AG14: =T14*(1+$G14) -> 1068480000 | AH14: =SUM(V14:AG14) -> 10684800000 | AJ14: =AH14-U14 -> 1084800000 | AK14: =IFERROR(AJ14/ABS(U14),"") -> 0.113 | AL14: =SUM(V14:X14)-SUM(I14:K14) -> 235040000 | AM14: =SUM(Y14:AA14)-SUM(L14:N14) -> 266680000 | AN14: =SUM(AB14:AD14)-SUM(O14:Q14) -> 275720000 | AO14: =SUM(AE14:AG14)-SUM(R14:T14) -> 307360000 | AP14: =IFERROR(AL14/ABS(SUM(I14:K14)),"") -> 0.113 | AQ14: =IFERROR(AM14/ABS(SUM(L14:N14)),"") -> 0.113 | AR14: =IFERROR(AN14/ABS(SUM(O14:Q14)),"") -> 0.113 | AS14: =IFERROR(AO14/ABS(SUM(R14:T14)),"") -> 0.113 | AU14: =IFERROR(U14/$U$17,0) -> 0.8 | AV14: =IFERROR(AH14/$AH$17,0) -> 0.78239093 | AW14: =(AV14-AU14)*100 -> -1.7609068
B15: Ventas canal digital | C15: Ingresos operacionales | D15: Ingreso | E15: Comercial | F15: Ventas | G15: 0.28 | I15: 120000000 | J15: 127500000 | K15: 142500000 | L15: 142500000 | M15: 150000000 | N15: 150000000 | O15: 150000000 | P15: 157500000 | Q15: 150000000 | R15: 157500000 | S15: 172500000 | T15: 180000000 | U15: =SUM(I15:T15) -> 1800000000 | V15: =I15*(1+$G15) -> 153600000 | W15: =J15*(1+$G15) -> 163200000 | X15: =K15*(1+$G15) -> 182400000 | Y15: =L15*(1+$G15) -> 182400000 | Z15: =M15*(1+$G15) -> 192000000 | AA15: =N15*(1+$G15) -> 192000000 | AB15: =O15*(1+$G15) -> 192000000 | AC15: =P15*(1+$G15) -> 201600000 | ... AG15: =T15*(1+$G15) -> 230400000 | AH15: =SUM(V15:AG15) -> 2304000000 | AJ15: =AH15-U15 -> 504000000 | AK15: =IFERROR(AJ15/ABS(U15),"") -> 0.28 | AL15: =SUM(V15:X15)-SUM(I15:K15) -> 109200000 | AM15: =SUM(Y15:AA15)-SUM(L15:N15) -> 123900000 | AN15: =SUM(AB15:AD15)-SUM(O15:Q15) -> 128100000 | AO15: =SUM(AE15:AG15)-SUM(R15:T15) -> 142800000 | AP15: =IFERROR(AL15/ABS(SUM(I15:K15)),"") -> 0.28 | AQ15: =IFERROR(AM15/ABS(SUM(L15:N15)),"") -> 0.28 | AR15: =IFERROR(AN15/ABS(SUM(O15:Q15)),"") -> 0.28 | AS15: =IFERROR(AO15/ABS(SUM(R15:T15)),"") -> 0.28 | AU15: =IFERROR(U15/$U$17,0) -> 0.15 | AV15: =IFERROR(AH15/$AH$17,0) -> 0.16870963 | AW15: =(AV15-AU15)*100 -> 1.8709635
B16: Servicios de instalación | C16: Ingresos operacionales | D16: Ingreso | E16: Comercial | F16: Ventas | G16: 0.113 | I16: 40000000 | J16: 42500000 | K16: 47500000 | L16: 47500000 | M16: 50000000 | N16: 50000000 | O16: 50000000 | P16: 52500000 | Q16: 50000000 | R16: 52500000 | S16: 57500000 | T16: 60000000 | U16: =SUM(I16:T16) -> 600000000 | V16: =I16*(1+$G16) -> 44520000 | W16: =J16*(1+$G16) -> 47302500 | X16: =K16*(1+$G16) -> 52867500 | Y16: =L16*(1+$G16) -> 52867500 | Z16: =M16*(1+$G16) -> 55650000 | AA16: =N16*(1+$G16) -> 55650000 | AB16: =O16*(1+$G16) -> 55650000 | AC16: =P16*(1+$G16) -> 58432500 | ... AG16: =T16*(1+$G16) -> 66780000 | AH16: =SUM(V16:AG16) -> 667800000 | AJ16: =AH16-U16 -> 67800000 | AK16: =IFERROR(AJ16/ABS(U16),"") -> 0.113 | AL16: =SUM(V16:X16)-SUM(I16:K16) -> 14690000 | AM16: =SUM(Y16:AA16)-SUM(L16:N16) -> 16667500 | AN16: =SUM(AB16:AD16)-SUM(O16:Q16) -> 17232500 | AO16: =SUM(AE16:AG16)-SUM(R16:T16) -> 19210000 | AP16: =IFERROR(AL16/ABS(SUM(I16:K16)),"") -> 0.113 | AQ16: =IFERROR(AM16/ABS(SUM(L16:N16)),"") -> 0.113 | AR16: =IFERROR(AN16/ABS(SUM(O16:Q16)),"") -> 0.113 | AS16: =IFERROR(AO16/ABS(SUM(R16:T16)),"") -> 0.113 | AU16: =IFERROR(U16/$U$17,0) -> 0.05 | AV16: =IFERROR(AH16/$AH$17,0) -> 0.048899433 | AW16: =(AV16-AU16)*100 -> -0.11005668
B17: Total ingresos operacionales | D17: Ingreso | I17: =SUM(I14:I16) -> 800000000 | J17: =SUM(J14:J16) -> 850000000 | K17: =SUM(K14:K16) -> 950000000 | L17: =SUM(L14:L16) -> 950000000 | M17: =SUM(M14:M16) -> 1000000000 | N17: =SUM(N14:N16) -> 1000000000 | O17: =SUM(O14:O16) -> 1000000000 | P17: =SUM(P14:P16) -> 1050000000 | ... T17: =SUM(T14:T16) -> 1200000000 | U17: =SUM(I17:T17) -> 12000000000 | V17: =SUM(V14:V16) -> 910440000 | W17: =SUM(W14:W16) -> 967342500 | X17: =SUM(X14:X16) -> 1081147500 | Y17: =SUM(Y14:Y16) -> 1081147500 | Z17: =SUM(Z14:Z16) -> 1138050000 | AA17: =SUM(AA14:AA16) -> 1138050000 | AB17: =SUM(AB14:AB16) -> 1138050000 | AC17: =SUM(AC14:AC16) -> 1194952500 | ... AG17: =SUM(AG14:AG16) -> 1365660000 | AH17: =SUM(V17:AG17) -> 13656600000 | AJ17: =AH17-U17 -> 1656600000 | AK17: =IFERROR(AJ17/ABS(U17),"") -> 0.13805 | AL17: =SUM(V17:X17)-SUM(I17:K17) -> 358930000 | AM17: =SUM(Y17:AA17)-SUM(L17:N17) -> 407247500 | AN17: =SUM(AB17:AD17)-SUM(O17:Q17) -> 421052500 | AO17: =SUM(AE17:AG17)-SUM(R17:T17) -> 469370000 | AP17: =IFERROR(AL17/ABS(SUM(I17:K17)),"") -> 0.13805 | AQ17: =IFERROR(AM17/ABS(SUM(L17:N17)),"") -> 0.13805 | AR17: =IFERROR(AN17/ABS(SUM(O17:Q17)),"") -> 0.13805 | AS17: =IFERROR(AO17/ABS(SUM(R17:T17)),"") -> 0.13805 | AU17: =IFERROR(U17/$U$17,0) -> 1 | AV17: =IFERROR(AH17/$AH$17,0) -> 1 | AW17: =(AV17-AU17)*100 -> 0
B18: COSTO DE VENTAS
B19: Costo de mercancía vendida | C19: Costo de ventas | D19: Costo | E19: Operaciones | F19: Costo variable | G19: 0.1183 | I19: 466700000 | J19: 495800000 | K19: 554200000 | L19: 554200000 | M19: 583300000 | N19: 583300000 | O19: 583300000 | P19: 612500000 | Q19: 583300000 | R19: 612500000 | S19: 670800000 | T19: 700100000 | U19: =SUM(I19:T19) -> 7000000000 | V19: =I19*(1+$G19) -> 5.2191061e+08 | W19: =J19*(1+$G19) -> 554453140 | X19: =K19*(1+$G19) -> 619761860 | Y19: =L19*(1+$G19) -> 619761860 | Z19: =M19*(1+$G19) -> 652304390 | AA19: =N19*(1+$G19) -> 652304390 | AB19: =O19*(1+$G19) -> 652304390 | AC19: =P19*(1+$G19) -> 684958750 | ... AG19: =T19*(1+$G19) -> 782921830 | AH19: =SUM(V19:AG19) -> 7828100000 | AJ19: =AH19-U19 -> 828100000 | AK19: =IFERROR(AJ19/ABS(U19),"") -> 0.1183 | AL19: =SUM(V19:X19)-SUM(I19:K19) -> 179425610 | AM19: =SUM(Y19:AA19)-SUM(L19:N19) -> 203570640 | AN19: =SUM(AB19:AD19)-SUM(O19:Q19) -> 210467530 | AO19: =SUM(AE19:AG19)-SUM(R19:T19) -> 234636220 | AP19: =IFERROR(AL19/ABS(SUM(I19:K19)),"") -> 0.1183 | AQ19: =IFERROR(AM19/ABS(SUM(L19:N19)),"") -> 0.1183 | AR19: =IFERROR(AN19/ABS(SUM(O19:Q19)),"") -> 0.1183 | AS19: =IFERROR(AO19/ABS(SUM(R19:T19)),"") -> 0.1183 | AU19: =IFERROR(U19/$U$17,0) -> 0.58333333 | AV19: =IFERROR(AH19/$AH$17,0) -> 0.57321002 | AW19: =(AV19-AU19)*100 -> -1.012331
B20: Fletes de compra | C20: Costo de ventas | D20: Costo | E20: Operaciones | F20: Costo variable | G20: 0.1183 | I20: 32000000 | J20: 34000000 | K20: 38000000 | L20: 38000000 | M20: 40000000 | N20: 40000000 | O20: 40000000 | P20: 42000000 | Q20: 40000000 | R20: 42000000 | S20: 46000000 | T20: 48000000 | U20: =SUM(I20:T20) -> 480000000 | V20: =I20*(1+$G20) -> 35785600 | W20: =J20*(1+$G20) -> 38022200 | X20: =K20*(1+$G20) -> 42495400 | Y20: =L20*(1+$G20) -> 42495400 | Z20: =M20*(1+$G20) -> 44732000 | AA20: =N20*(1+$G20) -> 44732000 | AB20: =O20*(1+$G20) -> 44732000 | AC20: =P20*(1+$G20) -> 46968600 | ... AG20: =T20*(1+$G20) -> 53678400 | AH20: =SUM(V20:AG20) -> 536784000 | AJ20: =AH20-U20 -> 56784000 | AK20: =IFERROR(AJ20/ABS(U20),"") -> 0.1183 | AL20: =SUM(V20:X20)-SUM(I20:K20) -> 12303200 | AM20: =SUM(Y20:AA20)-SUM(L20:N20) -> 13959400 | AN20: =SUM(AB20:AD20)-SUM(O20:Q20) -> 14432600 | AO20: =SUM(AE20:AG20)-SUM(R20:T20) -> 16088800 | AP20: =IFERROR(AL20/ABS(SUM(I20:K20)),"") -> 0.1183 | AQ20: =IFERROR(AM20/ABS(SUM(L20:N20)),"") -> 0.1183 | AR20: =IFERROR(AN20/ABS(SUM(O20:Q20)),"") -> 0.1183 | AS20: =IFERROR(AO20/ABS(SUM(R20:T20)),"") -> 0.1183 | AU20: =IFERROR(U20/$U$17,0) -> 0.04 | AV20: =IFERROR(AH20/$AH$17,0) -> 0.03930583 | AW20: =(AV20-AU20)*100 -> -0.069416985
B21: Mermas y averías | C21: Costo de ventas | D21: Costo | E21: Operaciones | F21: Costo variable | G21: 0.1183 | I21: 10000000 | J21: 10600000 | K21: 11900000 | L21: 11900000 | M21: 12500000 | N21: 12500000 | O21: 12500000 | P21: 13100000 | Q21: 12500000 | R21: 13100000 | S21: 14400000 | T21: 15000000 | U21: =SUM(I21:T21) -> 150000000 | V21: =I21*(1+$G21) -> 11183000 | W21: =J21*(1+$G21) -> 11853980 | X21: =K21*(1+$G21) -> 13307770 | Y21: =L21*(1+$G21) -> 13307770 | Z21: =M21*(1+$G21) -> 13978750 | AA21: =N21*(1+$G21) -> 13978750 | AB21: =O21*(1+$G21) -> 13978750 | AC21: =P21*(1+$G21) -> 14649730 | ... AG21: =T21*(1+$G21) -> 16774500 | AH21: =SUM(V21:AG21) -> 167745000 | AJ21: =AH21-U21 -> 17745000 | AK21: =IFERROR(AJ21/ABS(U21),"") -> 0.1183 | AL21: =SUM(V21:X21)-SUM(I21:K21) -> 3844750 | AM21: =SUM(Y21:AA21)-SUM(L21:N21) -> 4365270 | AN21: =SUM(AB21:AD21)-SUM(O21:Q21) -> 4507230 | AO21: =SUM(AE21:AG21)-SUM(R21:T21) -> 5027750 | AP21: =IFERROR(AL21/ABS(SUM(I21:K21)),"") -> 0.1183 | AQ21: =IFERROR(AM21/ABS(SUM(L21:N21)),"") -> 0.1183 | AR21: =IFERROR(AN21/ABS(SUM(O21:Q21)),"") -> 0.1183 | AS21: =IFERROR(AO21/ABS(SUM(R21:T21)),"") -> 0.1183 | AU21: =IFERROR(U21/$U$17,0) -> 0.0125 | AV21: =IFERROR(AH21/$AH$17,0) -> 0.012283072 | AW21: =(AV21-AU21)*100 -> -0.021692808
B22: Total costo de ventas | D22: Costo | I22: =SUM(I19:I21) -> 508700000 | J22: =SUM(J19:J21) -> 540400000 | K22: =SUM(K19:K21) -> 604100000 | L22: =SUM(L19:L21) -> 604100000 | M22: =SUM(M19:M21) -> 635800000 | N22: =SUM(N19:N21) -> 635800000 | O22: =SUM(O19:O21) -> 635800000 | P22: =SUM(P19:P21) -> 667600000 | ... T22: =SUM(T19:T21) -> 763100000 | U22: =SUM(I22:T22) -> 7630000000 | V22: =SUM(V19:V21) -> 568879210 | W22: =SUM(W19:W21) -> 604329320 | X22: =SUM(X19:X21) -> 675565030 | Y22: =SUM(Y19:Y21) -> 675565030 | Z22: =SUM(Z19:Z21) -> 711015140 | AA22: =SUM(AA19:AA21) -> 711015140 | AB22: =SUM(AB19:AB21) -> 711015140 | AC22: =SUM(AC19:AC21) -> 746577080 | ... AG22: =SUM(AG19:AG21) -> 853374730 | AH22: =SUM(V22:AG22) -> 8532629000 | AJ22: =AH22-U22 -> 902629000 | AK22: =IFERROR(AJ22/ABS(U22),"") -> 0.1183 | AL22: =SUM(V22:X22)-SUM(I22:K22) -> 195573560 | AM22: =SUM(Y22:AA22)-SUM(L22:N22) -> 221895310 | AN22: =SUM(AB22:AD22)-SUM(O22:Q22) -> 229407360 | AO22: =SUM(AE22:AG22)-SUM(R22:T22) -> 255752770 | AP22: =IFERROR(AL22/ABS(SUM(I22:K22)),"") -> 0.1183 | AQ22: =IFERROR(AM22/ABS(SUM(L22:N22)),"") -> 0.1183 | AR22: =IFERROR(AN22/ABS(SUM(O22:Q22)),"") -> 0.1183 | AS22: =IFERROR(AO22/ABS(SUM(R22:T22)),"") -> 0.1183 | AU22: =IFERROR(U22/$U$17,0) -> 0.63583333 | AV22: =IFERROR(AH22/$AH$17,0) -> 0.62479893 | AW22: =(AV22-AU22)*100 -> -1.1034408
B23: Utilidad bruta | D23: T | I23: =I17-I22 -> 291300000 | J23: =J17-J22 -> 309600000 | K23: =K17-K22 -> 345900000 | L23: =L17-L22 -> 345900000 | M23: =M17-M22 -> 364200000 | N23: =N17-N22 -> 364200000 | O23: =O17-O22 -> 364200000 | P23: =P17-P22 -> 382400000 | ... T23: =T17-T22 -> 436900000 | U23: =SUM(I23:T23) -> 4370000000 | V23: =V17-V22 -> 341560790 | W23: =W17-W22 -> 363013180 | X23: =X17-X22 -> 405582470 | Y23: =Y17-Y22 -> 405582470 | Z23: =Z17-Z22 -> 427034860 | AA23: =AA17-AA22 -> 427034860 | AB23: =AB17-AB22 -> 427034860 | AC23: =AC17-AC22 -> 448375420 | ... AG23: =AG17-AG22 -> 512285270 | AH23: =SUM(V23:AG23) -> 5123971000 | AJ23: =AH23-U23 -> 753971000 | AK23: =IFERROR(AJ23/ABS(U23),"") -> 0.17253341 | AL23: =SUM(V23:X23)-SUM(I23:K23) -> 163356440 | AM23: =SUM(Y23:AA23)-SUM(L23:N23) -> 185352190 | AN23: =SUM(AB23:AD23)-SUM(O23:Q23) -> 191645140 | AO23: =SUM(AE23:AG23)-SUM(R23:T23) -> 213617230 | AP23: =IFERROR(AL23/ABS(SUM(I23:K23)),"") -> 0.17253532 | AQ23: =IFERROR(AM23/ABS(SUM(L23:N23)),"") -> 0.17253299 | AR23: =IFERROR(AN23/ABS(SUM(O23:Q23)),"") -> 0.17252893 | AS23: =IFERROR(AO23/ABS(SUM(R23:T23)),"") -> 0.17253633 | AU23: =IFERROR(U23/$U$17,0) -> 0.36416667 | AV23: =IFERROR(AH23/$AH$17,0) -> 0.37520107 | AW23: =(AV23-AU23)*100 -> 1.1034408
B24: Margen bruto | D24: M | I24: =IFERROR(I23/I17,0) -> 0.364125 | J24: =IFERROR(J23/J17,0) -> 0.36423529 | K24: =IFERROR(K23/K17,0) -> 0.36410526 | L24: =IFERROR(L23/L17,0) -> 0.36410526 | M24: =IFERROR(M23/M17,0) -> 0.3642 | N24: =IFERROR(N23/N17,0) -> 0.3642 | O24: =IFERROR(O23/O17,0) -> 0.3642 | P24: =IFERROR(P23/P17,0) -> 0.36419048 | ... AH24: =IFERROR(AH23/AH17,0) -> 0.37520107 | AK24: =(AH24-U24)*100 -> 1.1034408 | AP24: =(IFERROR(SUM(V23:X23)/SUM(V17:X17),0)-IFERROR(SUM(I23:K23)/SUM(I17:K17),0))*100 -> 1.1034631 | AQ24: =(IFERROR(SUM(Y23:AA23)/SUM(Y17:AA17),0)-IFERROR(SUM(L23:N23)/SUM(L17:N17),0))*100 -> 1.1034359 | AR24: =(IFERROR(SUM(AB23:AD23)/SUM(AB17:AD17),0)-IFERROR(SUM(O23:Q23)/SUM(O17:Q17),0))*100 -> 1.1033887 | AS24: =(IFERROR(SUM(AE23:AG23)/SUM(AE17:AG17),0)-IFERROR(SUM(R23:T23)/SUM(R17:T17),0))*100 -> 1.1034749
B26: GASTOS DE ADMINISTRACIÓN
B27: Nómina administrativa | C27: Gastos de administración | D27: Gasto | E27: Administración | F27: Nómina | G27: =pSalario -> 0.07 | I27: 50000000 | J27: 50000000 | K27: 50000000 | L27: 50000000 | M27: 50000000 | N27: 50000000 | O27: 50000000 | P27: 50000000 | Q27: 50000000 | R27: 50000000 | S27: 50000000 | T27: 50000000 | U27: =SUM(I27:T27) -> 600000000 | V27: =I27*(1+$G27) -> 53500000 | W27: =J27*(1+$G27) -> 53500000 | X27: =K27*(1+$G27) -> 53500000 | Y27: =L27*(1+$G27) -> 53500000 | Z27: =M27*(1+$G27) -> 53500000 | AA27: =N27*(1+$G27) -> 53500000 | AB27: =O27*(1+$G27) -> 53500000 | AC27: =P27*(1+$G27) -> 53500000 | ... AG27: =T27*(1+$G27) -> 53500000 | AH27: =SUM(V27:AG27) -> 642000000 | AJ27: =AH27-U27 -> 42000000 | AK27: =IFERROR(AJ27/ABS(U27),"") -> 0.07 | AL27: =SUM(V27:X27)-SUM(I27:K27) -> 10500000 | AM27: =SUM(Y27:AA27)-SUM(L27:N27) -> 10500000 | AN27: =SUM(AB27:AD27)-SUM(O27:Q27) -> 10500000 | AO27: =SUM(AE27:AG27)-SUM(R27:T27) -> 10500000 | AP27: =IFERROR(AL27/ABS(SUM(I27:K27)),"") -> 0.07 | AQ27: =IFERROR(AM27/ABS(SUM(L27:N27)),"") -> 0.07 | AR27: =IFERROR(AN27/ABS(SUM(O27:Q27)),"") -> 0.07 | AS27: =IFERROR(AO27/ABS(SUM(R27:T27)),"") -> 0.07 | AU27: =IFERROR(U27/$U$17,0) -> 0.05 | AV27: =IFERROR(AH27/$AH$17,0) -> 0.047010237 | AW27: =(AV27-AU27)*100 -> -0.29897632
B28: Arrendamiento de oficinas | C28: Gastos de administración | D28: Gasto | E28: Administración | F28: IPC | G28: =pIPC -> 0.04 | I28: 15000000 | J28: 15000000 | K28: 15000000 | L28: 15000000 | M28: 15000000 | N28: 15000000 | O28: 15000000 | P28: 15000000 | Q28: 15000000 | R28: 15000000 | S28: 15000000 | T28: 15000000 | U28: =SUM(I28:T28) -> 180000000 | V28: =I28*(1+$G28) -> 15600000 | W28: =J28*(1+$G28) -> 15600000 | X28: =K28*(1+$G28) -> 15600000 | Y28: =L28*(1+$G28) -> 15600000 | Z28: =M28*(1+$G28) -> 15600000 | AA28: =N28*(1+$G28) -> 15600000 | AB28: =O28*(1+$G28) -> 15600000 | AC28: =P28*(1+$G28) -> 15600000 | ... AG28: =T28*(1+$G28) -> 15600000 | AH28: =SUM(V28:AG28) -> 187200000 | AJ28: =AH28-U28 -> 7200000 | AK28: =IFERROR(AJ28/ABS(U28),"") -> 0.04 | AL28: =SUM(V28:X28)-SUM(I28:K28) -> 1800000 | AM28: =SUM(Y28:AA28)-SUM(L28:N28) -> 1800000 | AN28: =SUM(AB28:AD28)-SUM(O28:Q28) -> 1800000 | AO28: =SUM(AE28:AG28)-SUM(R28:T28) -> 1800000 | AP28: =IFERROR(AL28/ABS(SUM(I28:K28)),"") -> 0.04 | AQ28: =IFERROR(AM28/ABS(SUM(L28:N28)),"") -> 0.04 | AR28: =IFERROR(AN28/ABS(SUM(O28:Q28)),"") -> 0.04 | AS28: =IFERROR(AO28/ABS(SUM(R28:T28)),"") -> 0.04 | AU28: =IFERROR(U28/$U$17,0) -> 0.015 | AV28: =IFERROR(AH28/$AH$17,0) -> 0.013707658 | AW28: =(AV28-AU28)*100 -> -0.12923422
B29: Servicios públicos | C29: Gastos de administración | D29: Gasto | E29: Administración | F29: IPC | G29: =pIPC -> 0.04 | I29: 7000000 | J29: 7000000 | K29: 7000000 | L29: 7000000 | M29: 7000000 | N29: 7000000 | O29: 7000000 | P29: 7000000 | Q29: 7000000 | R29: 7000000 | S29: 7000000 | T29: 7000000 | U29: =SUM(I29:T29) -> 84000000 | V29: =I29*(1+$G29) -> 7280000 | W29: =J29*(1+$G29) -> 7280000 | X29: =K29*(1+$G29) -> 7280000 | Y29: =L29*(1+$G29) -> 7280000 | Z29: =M29*(1+$G29) -> 7280000 | AA29: =N29*(1+$G29) -> 7280000 | AB29: =O29*(1+$G29) -> 7280000 | AC29: =P29*(1+$G29) -> 7280000 | ... AG29: =T29*(1+$G29) -> 7280000 | AH29: =SUM(V29:AG29) -> 87360000 | AJ29: =AH29-U29 -> 3360000 | AK29: =IFERROR(AJ29/ABS(U29),"") -> 0.04 | AL29: =SUM(V29:X29)-SUM(I29:K29) -> 840000 | AM29: =SUM(Y29:AA29)-SUM(L29:N29) -> 840000 | AN29: =SUM(AB29:AD29)-SUM(O29:Q29) -> 840000 | AO29: =SUM(AE29:AG29)-SUM(R29:T29) -> 840000 | AP29: =IFERROR(AL29/ABS(SUM(I29:K29)),"") -> 0.04 | AQ29: =IFERROR(AM29/ABS(SUM(L29:N29)),"") -> 0.04 | AR29: =IFERROR(AN29/ABS(SUM(O29:Q29)),"") -> 0.04 | AS29: =IFERROR(AO29/ABS(SUM(R29:T29)),"") -> 0.04 | AU29: =IFERROR(U29/$U$17,0) -> 0.007 | AV29: =IFERROR(AH29/$AH$17,0) -> 0.006396907 | AW29: =(AV29-AU29)*100 -> -0.060309301
B30: Honorarios profesionales | C30: Gastos de administración | D30: Gasto | E30: Administración | F30: IPC | G30: -0.22 | I30: 10000000 | J30: 10000000 | K30: 10000000 | L30: 10000000 | M30: 10000000 | N30: 10000000 | O30: 10000000 | P30: 10000000 | Q30: 10000000 | R30: 10000000 | S30: 10000000 | T30: 10000000 | U30: =SUM(I30:T30) -> 120000000 | V30: =I30*(1+$G30) -> 7800000 | W30: =J30*(1+$G30) -> 7800000 | X30: =K30*(1+$G30) -> 7800000 | Y30: =L30*(1+$G30) -> 7800000 | Z30: =M30*(1+$G30) -> 7800000 | AA30: =N30*(1+$G30) -> 7800000 | AB30: =O30*(1+$G30) -> 7800000 | AC30: =P30*(1+$G30) -> 7800000 | ... AG30: =T30*(1+$G30) -> 7800000 | AH30: =SUM(V30:AG30) -> 93600000 | AJ30: =AH30-U30 -> -26400000 | AK30: =IFERROR(AJ30/ABS(U30),"") -> -0.22 | AL30: =SUM(V30:X30)-SUM(I30:K30) -> -6600000 | AM30: =SUM(Y30:AA30)-SUM(L30:N30) -> -6600000 | AN30: =SUM(AB30:AD30)-SUM(O30:Q30) -> -6600000 | AO30: =SUM(AE30:AG30)-SUM(R30:T30) -> -6600000 | AP30: =IFERROR(AL30/ABS(SUM(I30:K30)),"") -> -0.22 | AQ30: =IFERROR(AM30/ABS(SUM(L30:N30)),"") -> -0.22 | AR30: =IFERROR(AN30/ABS(SUM(O30:Q30)),"") -> -0.22 | AS30: =IFERROR(AO30/ABS(SUM(R30:T30)),"") -> -0.22 | AU30: =IFERROR(U30/$U$17,0) -> 0.01 | AV30: =IFERROR(AH30/$AH$17,0) -> 0.0068538289 | AW30: =(AV30-AU30)*100 -> -0.31461711
B31: Tecnología y software | C31: Gastos de administración | D31: Gasto | E31: Administración | F31: IPC | G31: =pIPC -> 0.04 | I31: 8000000 | J31: 8000000 | K31: 8000000 | L31: 8000000 | M31: 8000000 | N31: 8000000 | O31: 8000000 | P31: 8000000 | Q31: 8000000 | R31: 8000000 | S31: 8000000 | T31: 8000000 | U31: =SUM(I31:T31) -> 96000000 | V31: =I31*(1+$G31) -> 8320000 | W31: =J31*(1+$G31) -> 8320000 | X31: =K31*(1+$G31) -> 8320000 | Y31: =L31*(1+$G31) -> 8320000 | Z31: =M31*(1+$G31) -> 8320000 | AA31: =N31*(1+$G31) -> 8320000 | AB31: =O31*(1+$G31) -> 8320000 | AC31: =P31*(1+$G31) -> 8320000 | ... AG31: =T31*(1+$G31) -> 8320000 | AH31: =SUM(V31:AG31) -> 99840000 | AJ31: =AH31-U31 -> 3840000 | AK31: =IFERROR(AJ31/ABS(U31),"") -> 0.04 | AL31: =SUM(V31:X31)-SUM(I31:K31) -> 960000 | AM31: =SUM(Y31:AA31)-SUM(L31:N31) -> 960000 | AN31: =SUM(AB31:AD31)-SUM(O31:Q31) -> 960000 | AO31: =SUM(AE31:AG31)-SUM(R31:T31) -> 960000 | AP31: =IFERROR(AL31/ABS(SUM(I31:K31)),"") -> 0.04 | AQ31: =IFERROR(AM31/ABS(SUM(L31:N31)),"") -> 0.04 | AR31: =IFERROR(AN31/ABS(SUM(O31:Q31)),"") -> 0.04 | AS31: =IFERROR(AO31/ABS(SUM(R31:T31)),"") -> 0.04 | AU31: =IFERROR(U31/$U$17,0) -> 0.008 | AV31: =IFERROR(AH31/$AH$17,0) -> 0.0073107508 | AW31: =(AV31-AU31)*100 -> -0.068924915
B32: Depreciación y amortización | C32: Gastos de administración | D32: Gasto | E32: Administración | F32: Fijo | G32: 0 | I32: 15000000 | J32: 15000000 | K32: 15000000 | L32: 15000000 | M32: 15000000 | N32: 15000000 | O32: 15000000 | P32: 15000000 | Q32: 15000000 | R32: 15000000 | S32: 15000000 | T32: 15000000 | U32: =SUM(I32:T32) -> 180000000 | V32: =I32*(1+$G32) -> 15000000 | W32: =J32*(1+$G32) -> 15000000 | X32: =K32*(1+$G32) -> 15000000 | Y32: =L32*(1+$G32) -> 15000000 | Z32: =M32*(1+$G32) -> 15000000 | AA32: =N32*(1+$G32) -> 15000000 | AB32: =O32*(1+$G32) -> 15000000 | AC32: =P32*(1+$G32) -> 15000000 | ... AG32: =T32*(1+$G32) -> 15000000 | AH32: =SUM(V32:AG32) -> 180000000 | AJ32: =AH32-U32 -> 0 | AK32: =IFERROR(AJ32/ABS(U32),"") -> 0 | AL32: =SUM(V32:X32)-SUM(I32:K32) -> 0 | AM32: =SUM(Y32:AA32)-SUM(L32:N32) -> 0 | AN32: =SUM(AB32:AD32)-SUM(O32:Q32) -> 0 | AO32: =SUM(AE32:AG32)-SUM(R32:T32) -> 0 | AP32: =IFERROR(AL32/ABS(SUM(I32:K32)),"") -> 0 | AQ32: =IFERROR(AM32/ABS(SUM(L32:N32)),"") -> 0 | AR32: =IFERROR(AN32/ABS(SUM(O32:Q32)),"") -> 0 | AS32: =IFERROR(AO32/ABS(SUM(R32:T32)),"") -> 0 | AU32: =IFERROR(U32/$U$17,0) -> 0.015 | AV32: =IFERROR(AH32/$AH$17,0) -> 0.01318044 | AW32: =(AV32-AU32)*100 -> -0.18195598
B33: Total gastos de administración | D33: Gasto | I33: =SUM(I27:I32) -> 105000000 | J33: =SUM(J27:J32) -> 105000000 | K33: =SUM(K27:K32) -> 105000000 | L33: =SUM(L27:L32) -> 105000000 | M33: =SUM(M27:M32) -> 105000000 | N33: =SUM(N27:N32) -> 105000000 | O33: =SUM(O27:O32) -> 105000000 | P33: =SUM(P27:P32) -> 105000000 | ... T33: =SUM(T27:T32) -> 105000000 | U33: =SUM(I33:T33) -> 1260000000 | V33: =SUM(V27:V32) -> 107500000 | W33: =SUM(W27:W32) -> 107500000 | X33: =SUM(X27:X32) -> 107500000 | Y33: =SUM(Y27:Y32) -> 107500000 | Z33: =SUM(Z27:Z32) -> 107500000 | AA33: =SUM(AA27:AA32) -> 107500000 | AB33: =SUM(AB27:AB32) -> 107500000 | AC33: =SUM(AC27:AC32) -> 107500000 | ... AG33: =SUM(AG27:AG32) -> 107500000 | AH33: =SUM(V33:AG33) -> 1290000000 | AJ33: =AH33-U33 -> 30000000 | AK33: =IFERROR(AJ33/ABS(U33),"") -> 0.023809524 | AL33: =SUM(V33:X33)-SUM(I33:K33) -> 7500000 | AM33: =SUM(Y33:AA33)-SUM(L33:N33) -> 7500000 | AN33: =SUM(AB33:AD33)-SUM(O33:Q33) -> 7500000 | AO33: =SUM(AE33:AG33)-SUM(R33:T33) -> 7500000 | AP33: =IFERROR(AL33/ABS(SUM(I33:K33)),"") -> 0.023809524 | AQ33: =IFERROR(AM33/ABS(SUM(L33:N33)),"") -> 0.023809524 | AR33: =IFERROR(AN33/ABS(SUM(O33:Q33)),"") -> 0.023809524 | AS33: =IFERROR(AO33/ABS(SUM(R33:T33)),"") -> 0.023809524 | AU33: =IFERROR(U33/$U$17,0) -> 0.105 | AV33: =IFERROR(AH33/$AH$17,0) -> 0.094459822 | AW33: =(AV33-AU33)*100 -> -1.0540178
B34: GASTOS DE VENTAS
B35: Nómina comercial | C35: Gastos de ventas | D35: Gasto | E35: Comercial | F35: Nómina | G35: =pSalario -> 0.07 | I35: 43300000 | J35: 43300000 | K35: 43300000 | L35: 43300000 | M35: 43300000 | N35: 43300000 | O35: 43300000 | P35: 43300000 | Q35: 43300000 | R35: 43300000 | S35: 43300000 | T35: 43700000 | U35: =SUM(I35:T35) -> 520000000 | V35: =I35*(1+$G35) -> 46331000 | W35: =J35*(1+$G35) -> 46331000 | X35: =K35*(1+$G35) -> 46331000 | Y35: =L35*(1+$G35) -> 46331000 | Z35: =M35*(1+$G35) -> 46331000 | AA35: =N35*(1+$G35) -> 46331000 | AB35: =O35*(1+$G35) -> 46331000 | AC35: =P35*(1+$G35) -> 46331000 | ... AG35: =T35*(1+$G35) -> 46759000 | AH35: =SUM(V35:AG35) -> 556400000 | AJ35: =AH35-U35 -> 36400000 | AK35: =IFERROR(AJ35/ABS(U35),"") -> 0.07 | AL35: =SUM(V35:X35)-SUM(I35:K35) -> 9093000 | AM35: =SUM(Y35:AA35)-SUM(L35:N35) -> 9093000 | AN35: =SUM(AB35:AD35)-SUM(O35:Q35) -> 9093000 | AO35: =SUM(AE35:AG35)-SUM(R35:T35) -> 9121000 | AP35: =IFERROR(AL35/ABS(SUM(I35:K35)),"") -> 0.07 | AQ35: =IFERROR(AM35/ABS(SUM(L35:N35)),"") -> 0.07 | AR35: =IFERROR(AN35/ABS(SUM(O35:Q35)),"") -> 0.07 | AS35: =IFERROR(AO35/ABS(SUM(R35:T35)),"") -> 0.07 | AU35: =IFERROR(U35/$U$17,0) -> 0.043333333 | AV35: =IFERROR(AH35/$AH$17,0) -> 0.040742205 | AW35: =(AV35-AU35)*100 -> -0.25911281
B36: Comisiones de ventas | C36: Gastos de ventas | D36: Gasto | E36: Comercial | F36: Ventas | G36: 0.113 | I36: 24000000 | J36: 25500000 | K36: 28500000 | L36: 28500000 | M36: 30000000 | N36: 30000000 | O36: 30000000 | P36: 31500000 | Q36: 30000000 | R36: 31500000 | S36: 34500000 | T36: 36000000 | U36: =SUM(I36:T36) -> 360000000 | V36: =I36*(1+$G36) -> 26712000 | W36: =J36*(1+$G36) -> 28381500 | X36: =K36*(1+$G36) -> 31720500 | Y36: =L36*(1+$G36) -> 31720500 | Z36: =M36*(1+$G36) -> 33390000 | AA36: =N36*(1+$G36) -> 33390000 | AB36: =O36*(1+$G36) -> 33390000 | AC36: =P36*(1+$G36) -> 35059500 | ... AG36: =T36*(1+$G36) -> 40068000 | AH36: =SUM(V36:AG36) -> 400680000 | AJ36: =AH36-U36 -> 40680000 | AK36: =IFERROR(AJ36/ABS(U36),"") -> 0.113 | AL36: =SUM(V36:X36)-SUM(I36:K36) -> 8814000 | AM36: =SUM(Y36:AA36)-SUM(L36:N36) -> 10000500 | AN36: =SUM(AB36:AD36)-SUM(O36:Q36) -> 10339500 | AO36: =SUM(AE36:AG36)-SUM(R36:T36) -> 11526000 | AP36: =IFERROR(AL36/ABS(SUM(I36:K36)),"") -> 0.113 | AQ36: =IFERROR(AM36/ABS(SUM(L36:N36)),"") -> 0.113 | AR36: =IFERROR(AN36/ABS(SUM(O36:Q36)),"") -> 0.113 | AS36: =IFERROR(AO36/ABS(SUM(R36:T36)),"") -> 0.113 | AU36: =IFERROR(U36/$U$17,0) -> 0.03 | AV36: =IFERROR(AH36/$AH$17,0) -> 0.02933966 | AW36: =(AV36-AU36)*100 -> -0.066034006
B37: Publicidad y mercadeo | C37: Gastos de ventas | D37: Gasto | E37: Comercial | F37: IPC | G37: 0.352 | I37: 20000000 | J37: 20000000 | K37: 20000000 | L37: 20000000 | M37: 20000000 | N37: 20000000 | O37: 20000000 | P37: 20000000 | Q37: 20000000 | R37: 20000000 | S37: 20000000 | T37: 20000000 | U37: =SUM(I37:T37) -> 240000000 | V37: =I37*(1+$G37) -> 27040000 | W37: =J37*(1+$G37) -> 27040000 | X37: =K37*(1+$G37) -> 27040000 | Y37: =L37*(1+$G37) -> 27040000 | Z37: =M37*(1+$G37) -> 27040000 | AA37: =N37*(1+$G37) -> 27040000 | AB37: =O37*(1+$G37) -> 27040000 | AC37: =P37*(1+$G37) -> 27040000 | ... AG37: =T37*(1+$G37) -> 27040000 | AH37: =SUM(V37:AG37) -> 3.2448e+08 | AJ37: =AH37-U37 -> 84480000 | AK37: =IFERROR(AJ37/ABS(U37),"") -> 0.352 | AL37: =SUM(V37:X37)-SUM(I37:K37) -> 21120000 | AM37: =SUM(Y37:AA37)-SUM(L37:N37) -> 21120000 | AN37: =SUM(AB37:AD37)-SUM(O37:Q37) -> 21120000 | AO37: =SUM(AE37:AG37)-SUM(R37:T37) -> 21120000 | AP37: =IFERROR(AL37/ABS(SUM(I37:K37)),"") -> 0.352 | AQ37: =IFERROR(AM37/ABS(SUM(L37:N37)),"") -> 0.352 | AR37: =IFERROR(AN37/ABS(SUM(O37:Q37)),"") -> 0.352 | AS37: =IFERROR(AO37/ABS(SUM(R37:T37)),"") -> 0.352 | AU37: =IFERROR(U37/$U$17,0) -> 0.02 | AV37: =IFERROR(AH37/$AH$17,0) -> 0.02375994 | AW37: =(AV37-AU37)*100 -> 0.37599402
B38: Transporte y distribución | C38: Gastos de ventas | D38: Gasto | E38: Operaciones | F38: Volumen | G38: 0.06 | I38: 20000000 | J38: 21200000 | K38: 23800000 | L38: 23800000 | M38: 25000000 | N38: 25000000 | O38: 25000000 | P38: 26200000 | Q38: 25000000 | R38: 26200000 | S38: 28800000 | T38: 30000000 | U38: =SUM(I38:T38) -> 300000000 | V38: =I38*(1+$G38) -> 21200000 | W38: =J38*(1+$G38) -> 22472000 | X38: =K38*(1+$G38) -> 25228000 | Y38: =L38*(1+$G38) -> 25228000 | Z38: =M38*(1+$G38) -> 26500000 | AA38: =N38*(1+$G38) -> 26500000 | AB38: =O38*(1+$G38) -> 26500000 | AC38: =P38*(1+$G38) -> 27772000 | ... AG38: =T38*(1+$G38) -> 31800000 | AH38: =SUM(V38:AG38) -> 318000000 | AJ38: =AH38-U38 -> 18000000 | AK38: =IFERROR(AJ38/ABS(U38),"") -> 0.06 | AL38: =SUM(V38:X38)-SUM(I38:K38) -> 3900000 | AM38: =SUM(Y38:AA38)-SUM(L38:N38) -> 4428000 | AN38: =SUM(AB38:AD38)-SUM(O38:Q38) -> 4572000 | AO38: =SUM(AE38:AG38)-SUM(R38:T38) -> 5100000 | AP38: =IFERROR(AL38/ABS(SUM(I38:K38)),"") -> 0.06 | AQ38: =IFERROR(AM38/ABS(SUM(L38:N38)),"") -> 0.06 | AR38: =IFERROR(AN38/ABS(SUM(O38:Q38)),"") -> 0.06 | AS38: =IFERROR(AO38/ABS(SUM(R38:T38)),"") -> 0.06 | AU38: =IFERROR(U38/$U$17,0) -> 0.025 | AV38: =IFERROR(AH38/$AH$17,0) -> 0.023285444 | AW38: =(AV38-AU38)*100 -> -0.17145556
B39: Nómina de bodega | C39: Gastos de ventas | D39: Gasto | E39: Operaciones | F39: Nómina | G39: =pSalario -> 0.07 | I39: 31700000 | J39: 31700000 | K39: 31700000 | L39: 31700000 | M39: 31700000 | N39: 31700000 | O39: 31700000 | P39: 31700000 | Q39: 31700000 | R39: 31700000 | S39: 31700000 | T39: 31300000 | U39: =SUM(I39:T39) -> 380000000 | V39: =I39*(1+$G39) -> 33919000 | W39: =J39*(1+$G39) -> 33919000 | X39: =K39*(1+$G39) -> 33919000 | Y39: =L39*(1+$G39) -> 33919000 | Z39: =M39*(1+$G39) -> 33919000 | AA39: =N39*(1+$G39) -> 33919000 | AB39: =O39*(1+$G39) -> 33919000 | AC39: =P39*(1+$G39) -> 33919000 | ... AG39: =T39*(1+$G39) -> 33491000 | AH39: =SUM(V39:AG39) -> 406600000 | AJ39: =AH39-U39 -> 26600000 | AK39: =IFERROR(AJ39/ABS(U39),"") -> 0.07 | AL39: =SUM(V39:X39)-SUM(I39:K39) -> 6657000 | AM39: =SUM(Y39:AA39)-SUM(L39:N39) -> 6657000 | AN39: =SUM(AB39:AD39)-SUM(O39:Q39) -> 6657000 | AO39: =SUM(AE39:AG39)-SUM(R39:T39) -> 6629000 | AP39: =IFERROR(AL39/ABS(SUM(I39:K39)),"") -> 0.07 | AQ39: =IFERROR(AM39/ABS(SUM(L39:N39)),"") -> 0.07 | AR39: =IFERROR(AN39/ABS(SUM(O39:Q39)),"") -> 0.07 | AS39: =IFERROR(AO39/ABS(SUM(R39:T39)),"") -> 0.07 | AU39: =IFERROR(U39/$U$17,0) -> 0.031666667 | AV39: =IFERROR(AH39/$AH$17,0) -> 0.02977315 | AW39: =(AV39-AU39)*100 -> -0.18935167
B40: Arrendamiento de bodega | C40: Gastos de ventas | D40: Gasto | E40: Operaciones | F40: IPC | G40: =pIPC -> 0.04 | I40: 20000000 | J40: 20000000 | K40: 20000000 | L40: 20000000 | M40: 20000000 | N40: 20000000 | O40: 20000000 | P40: 20000000 | Q40: 20000000 | R40: 20000000 | S40: 20000000 | T40: 20000000 | U40: =SUM(I40:T40) -> 240000000 | V40: =I40*(1+$G40) -> 20800000 | W40: =J40*(1+$G40) -> 20800000 | X40: =K40*(1+$G40) -> 20800000 | Y40: =L40*(1+$G40) -> 20800000 | Z40: =M40*(1+$G40) -> 20800000 | AA40: =N40*(1+$G40) -> 20800000 | AB40: =O40*(1+$G40) -> 20800000 | AC40: =P40*(1+$G40) -> 20800000 | ... AG40: =T40*(1+$G40) -> 20800000 | AH40: =SUM(V40:AG40) -> 249600000 | AJ40: =AH40-U40 -> 9600000 | AK40: =IFERROR(AJ40/ABS(U40),"") -> 0.04 | AL40: =SUM(V40:X40)-SUM(I40:K40) -> 2400000 | AM40: =SUM(Y40:AA40)-SUM(L40:N40) -> 2400000 | AN40: =SUM(AB40:AD40)-SUM(O40:Q40) -> 2400000 | AO40: =SUM(AE40:AG40)-SUM(R40:T40) -> 2400000 | AP40: =IFERROR(AL40/ABS(SUM(I40:K40)),"") -> 0.04 | AQ40: =IFERROR(AM40/ABS(SUM(L40:N40)),"") -> 0.04 | AR40: =IFERROR(AN40/ABS(SUM(O40:Q40)),"") -> 0.04 | AS40: =IFERROR(AO40/ABS(SUM(R40:T40)),"") -> 0.04 | AU40: =IFERROR(U40/$U$17,0) -> 0.02 | AV40: =IFERROR(AH40/$AH$17,0) -> 0.018276877 | AW40: =(AV40-AU40)*100 -> -0.17231229
B41: Mantenimiento | C41: Gastos de ventas | D41: Gasto | E41: Operaciones | F41: IPC | G41: =pIPC -> 0.04 | I41: 7500000 | J41: 7500000 | K41: 7500000 | L41: 7500000 | M41: 7500000 | N41: 7500000 | O41: 7500000 | P41: 7500000 | Q41: 7500000 | R41: 7500000 | S41: 7500000 | T41: 7500000 | U41: =SUM(I41:T41) -> 90000000 | V41: =I41*(1+$G41) -> 7800000 | W41: =J41*(1+$G41) -> 7800000 | X41: =K41*(1+$G41) -> 7800000 | Y41: =L41*(1+$G41) -> 7800000 | Z41: =M41*(1+$G41) -> 7800000 | AA41: =N41*(1+$G41) -> 7800000 | AB41: =O41*(1+$G41) -> 7800000 | AC41: =P41*(1+$G41) -> 7800000 | ... AG41: =T41*(1+$G41) -> 7800000 | AH41: =SUM(V41:AG41) -> 93600000 | AJ41: =AH41-U41 -> 3600000 | AK41: =IFERROR(AJ41/ABS(U41),"") -> 0.04 | AL41: =SUM(V41:X41)-SUM(I41:K41) -> 900000 | AM41: =SUM(Y41:AA41)-SUM(L41:N41) -> 900000 | AN41: =SUM(AB41:AD41)-SUM(O41:Q41) -> 900000 | AO41: =SUM(AE41:AG41)-SUM(R41:T41) -> 900000 | AP41: =IFERROR(AL41/ABS(SUM(I41:K41)),"") -> 0.04 | AQ41: =IFERROR(AM41/ABS(SUM(L41:N41)),"") -> 0.04 | AR41: =IFERROR(AN41/ABS(SUM(O41:Q41)),"") -> 0.04 | AS41: =IFERROR(AO41/ABS(SUM(R41:T41)),"") -> 0.04 | AU41: =IFERROR(U41/$U$17,0) -> 0.0075 | AV41: =IFERROR(AH41/$AH$17,0) -> 0.0068538289 | AW41: =(AV41-AU41)*100 -> -0.064617108
B42: Total gastos de ventas | D42: Gasto | I42: =SUM(I35:I41) -> 166500000 | J42: =SUM(J35:J41) -> 169200000 | K42: =SUM(K35:K41) -> 174800000 | L42: =SUM(L35:L41) -> 174800000 | M42: =SUM(M35:M41) -> 177500000 | N42: =SUM(N35:N41) -> 177500000 | O42: =SUM(O35:O41) -> 177500000 | P42: =SUM(P35:P41) -> 180200000 | ... T42: =SUM(T35:T41) -> 188500000 | U42: =SUM(I42:T42) -> 2130000000 | V42: =SUM(V35:V41) -> 183802000 | W42: =SUM(W35:W41) -> 186743500 | X42: =SUM(X35:X41) -> 192838500 | Y42: =SUM(Y35:Y41) -> 192838500 | Z42: =SUM(Z35:Z41) -> 195780000 | AA42: =SUM(AA35:AA41) -> 195780000 | AB42: =SUM(AB35:AB41) -> 195780000 | AC42: =SUM(AC35:AC41) -> 198721500 | ... AG42: =SUM(AG35:AG41) -> 207758000 | AH42: =SUM(V42:AG42) -> 2349360000 | AJ42: =AH42-U42 -> 219360000 | AK42: =IFERROR(AJ42/ABS(U42),"") -> 0.10298592 | AL42: =SUM(V42:X42)-SUM(I42:K42) -> 52884000 | AM42: =SUM(Y42:AA42)-SUM(L42:N42) -> 54598500 | AN42: =SUM(AB42:AD42)-SUM(O42:Q42) -> 55081500 | AO42: =SUM(AE42:AG42)-SUM(R42:T42) -> 56796000 | AP42: =IFERROR(AL42/ABS(SUM(I42:K42)),"") -> 0.10359256 | AQ42: =IFERROR(AM42/ABS(SUM(L42:N42)),"") -> 0.10305493 | AR42: =IFERROR(AN42/ABS(SUM(O42:Q42)),"") -> 0.1029176 | AS42: =IFERROR(AO42/ABS(SUM(R42:T42)),"") -> 0.10242741 | AU42: =IFERROR(U42/$U$17,0) -> 0.1775 | AV42: =IFERROR(AH42/$AH$17,0) -> 0.17203111 | AW42: =(AV42-AU42)*100 -> -0.54688942
B43: Utilidad operacional (EBIT) | D43: T | I43: =I23-I33-I42 -> 19800000 | J43: =J23-J33-J42 -> 35400000 | K43: =K23-K33-K42 -> 66100000 | L43: =L23-L33-L42 -> 66100000 | M43: =M23-M33-M42 -> 81700000 | N43: =N23-N33-N42 -> 81700000 | O43: =O23-O33-O42 -> 81700000 | P43: =P23-P33-P42 -> 97200000 | ... T43: =T23-T33-T42 -> 143400000 | U43: =SUM(I43:T43) -> 980000000 | V43: =V23-V33-V42 -> 50258790 | W43: =W23-W33-W42 -> 68769680 | X43: =X23-X33-X42 -> 105243970 | Y43: =Y23-Y33-Y42 -> 105243970 | Z43: =Z23-Z33-Z42 -> 123754860 | AA43: =AA23-AA33-AA42 -> 123754860 | AB43: =AB23-AB33-AB42 -> 123754860 | AC43: =AC23-AC33-AC42 -> 142153920 | ... AG43: =AG23-AG33-AG42 -> 197027270 | AH43: =SUM(V43:AG43) -> 1484611000 | AJ43: =AH43-U43 -> 504611000 | AK43: =IFERROR(AJ43/ABS(U43),"") -> 0.51490918 | AL43: =SUM(V43:X43)-SUM(I43:K43) -> 102972440 | AM43: =SUM(Y43:AA43)-SUM(L43:N43) -> 123253690 | AN43: =SUM(AB43:AD43)-SUM(O43:Q43) -> 129063640 | AO43: =SUM(AE43:AG43)-SUM(R43:T43) -> 149321230 | AP43: =IFERROR(AL43/ABS(SUM(I43:K43)),"") -> 0.84890717 | AQ43: =IFERROR(AM43/ABS(SUM(L43:N43)),"") -> 0.53705312 | AR43: =IFERROR(AN43/ABS(SUM(O43:Q43)),"") -> 0.49525572 | AS43: =IFERROR(AO43/ABS(SUM(R43:T43)),"") -> 0.40510372 | AU43: =IFERROR(U43/$U$17,0) -> 0.081666667 | AV43: =IFERROR(AH43/$AH$17,0) -> 0.10871015 | AW43: =(AV43-AU43)*100 -> 2.7043481
B44: Margen operacional | D44: M | I44: =IFERROR(I43/I17,0) -> 0.02475 | J44: =IFERROR(J43/J17,0) -> 0.041647059 | K44: =IFERROR(K43/K17,0) -> 0.069578947 | L44: =IFERROR(L43/L17,0) -> 0.069578947 | M44: =IFERROR(M43/M17,0) -> 0.0817 | N44: =IFERROR(N43/N17,0) -> 0.0817 | O44: =IFERROR(O43/O17,0) -> 0.0817 | P44: =IFERROR(P43/P17,0) -> 0.092571429 | ... AH44: =IFERROR(AH43/AH17,0) -> 0.10871015 | AK44: =(AH44-U44)*100 -> 2.7043481 | AP44: =(IFERROR(SUM(V43:X43)/SUM(V17:X17),0)-IFERROR(SUM(I43:K43)/SUM(I17:K17),0))*100 -> 2.9141269 | AQ44: =(IFERROR(SUM(Y43:AA43)/SUM(Y17:AA17),0)-IFERROR(SUM(L43:N43)/SUM(L17:N17),0))*100 -> 2.7275682 | AR44: =(IFERROR(SUM(AB43:AD43)/SUM(AB17:AD17),0)-IFERROR(SUM(O43:Q43)/SUM(O17:Q17),0))*100 -> 2.6818324 | AS44: =(IFERROR(SUM(AE43:AG43)/SUM(AE17:AG17),0)-IFERROR(SUM(R43:T43)/SUM(R17:T17),0))*100 -> 2.54398
B45: EBITDA | D45: T | I45: =I43+I32 -> 34800000 | J45: =J43+J32 -> 50400000 | K45: =K43+K32 -> 81100000 | L45: =L43+L32 -> 81100000 | M45: =M43+M32 -> 96700000 | N45: =N43+N32 -> 96700000 | O45: =O43+O32 -> 96700000 | P45: =P43+P32 -> 112200000 | ... T45: =T43+T32 -> 158400000 | U45: =SUM(I45:T45) -> 1160000000 | V45: =V43+V32 -> 65258790 | W45: =W43+W32 -> 83769680 | X45: =X43+X32 -> 120243970 | Y45: =Y43+Y32 -> 120243970 | Z45: =Z43+Z32 -> 138754860 | AA45: =AA43+AA32 -> 138754860 | AB45: =AB43+AB32 -> 138754860 | AC45: =AC43+AC32 -> 157153920 | ... AG45: =AG43+AG32 -> 212027270 | AH45: =SUM(V45:AG45) -> 1664611000 | AJ45: =AH45-U45 -> 504611000 | AK45: =IFERROR(AJ45/ABS(U45),"") -> 0.43500948 | AL45: =SUM(V45:X45)-SUM(I45:K45) -> 102972440 | AM45: =SUM(Y45:AA45)-SUM(L45:N45) -> 123253690 | AN45: =SUM(AB45:AD45)-SUM(O45:Q45) -> 129063640 | AO45: =SUM(AE45:AG45)-SUM(R45:T45) -> 149321230 | AP45: =IFERROR(AL45/ABS(SUM(I45:K45)),"") -> 0.61919687 | AQ45: =IFERROR(AM45/ABS(SUM(L45:N45)),"") -> 0.44901162 | AR45: =IFERROR(AN45/ABS(SUM(O45:Q45)),"") -> 0.42232866 | AS45: =IFERROR(AO45/ABS(SUM(R45:T45)),"") -> 0.36102812 | AU45: =IFERROR(U45/$U$17,0) -> 0.096666667 | AV45: =IFERROR(AH45/$AH$17,0) -> 0.12189059 | AW45: =(AV45-AU45)*100 -> 2.5223921
B46: Margen EBITDA | D46: M | I46: =IFERROR(I45/I17,0) -> 0.0435 | J46: =IFERROR(J45/J17,0) -> 0.059294118 | K46: =IFERROR(K45/K17,0) -> 0.085368421 | L46: =IFERROR(L45/L17,0) -> 0.085368421 | M46: =IFERROR(M45/M17,0) -> 0.0967 | N46: =IFERROR(N45/N17,0) -> 0.0967 | O46: =IFERROR(O45/O17,0) -> 0.0967 | P46: =IFERROR(P45/P17,0) -> 0.10685714 | ... AH46: =IFERROR(AH45/AH17,0) -> 0.12189059 | AK46: =(AH46-U46)*100 -> 2.5223921 | AP46: =(IFERROR(SUM(V45:X45)/SUM(V17:X17),0)-IFERROR(SUM(I45:K45)/SUM(I17:K17),0))*100 -> 2.7041777 | AQ46: =(IFERROR(SUM(Y45:AA45)/SUM(Y17:AA17),0)-IFERROR(SUM(L45:N45)/SUM(L17:N17),0))*100 -> 2.5425282 | AR46: =(IFERROR(SUM(AB45:AD45)/SUM(AB17:AD17),0)-IFERROR(SUM(O45:Q45)/SUM(O17:Q17),0))*100 -> 2.5028593 | AS46: =(IFERROR(SUM(AE45:AG45)/SUM(AE17:AG17),0)-IFERROR(SUM(R45:T45)/SUM(R17:T17),0))*100 -> 2.3834306
B48: GASTOS FINANCIEROS
B49: Intereses financieros | C49: Gastos financieros | D49: Gasto | E49: Corporativo | F49: Financiero | G49: -0.1 | I49: 21700000 | J49: 21700000 | K49: 21700000 | L49: 21700000 | M49: 21700000 | N49: 21700000 | O49: 21700000 | P49: 21700000 | Q49: 21700000 | R49: 21700000 | S49: 21700000 | T49: 21300000 | U49: =SUM(I49:T49) -> 260000000 | V49: =I49*(1+$G49) -> 19530000 | W49: =J49*(1+$G49) -> 19530000 | X49: =K49*(1+$G49) -> 19530000 | Y49: =L49*(1+$G49) -> 19530000 | Z49: =M49*(1+$G49) -> 19530000 | AA49: =N49*(1+$G49) -> 19530000 | AB49: =O49*(1+$G49) -> 19530000 | AC49: =P49*(1+$G49) -> 19530000 | ... AG49: =T49*(1+$G49) -> 19170000 | AH49: =SUM(V49:AG49) -> 234000000 | AJ49: =AH49-U49 -> -26000000 | AK49: =IFERROR(AJ49/ABS(U49),"") -> -0.1 | AL49: =SUM(V49:X49)-SUM(I49:K49) -> -6510000 | AM49: =SUM(Y49:AA49)-SUM(L49:N49) -> -6510000 | AN49: =SUM(AB49:AD49)-SUM(O49:Q49) -> -6510000 | AO49: =SUM(AE49:AG49)-SUM(R49:T49) -> -6470000 | AP49: =IFERROR(AL49/ABS(SUM(I49:K49)),"") -> -0.1 | AQ49: =IFERROR(AM49/ABS(SUM(L49:N49)),"") -> -0.1 | AR49: =IFERROR(AN49/ABS(SUM(O49:Q49)),"") -> -0.1 | AS49: =IFERROR(AO49/ABS(SUM(R49:T49)),"") -> -0.1 | AU49: =IFERROR(U49/$U$17,0) -> 0.021666667 | AV49: =IFERROR(AH49/$AH$17,0) -> 0.017134572 | AW49: =(AV49-AU49)*100 -> -0.45320944
B50: Comisiones bancarias | C50: Gastos financieros | D50: Gasto | E50: Corporativo | F50: IPC | G50: =pIPC -> 0.04 | I50: 4000000 | J50: 4000000 | K50: 4000000 | L50: 4000000 | M50: 4000000 | N50: 4000000 | O50: 4000000 | P50: 4000000 | Q50: 4000000 | R50: 4000000 | S50: 4000000 | T50: 4000000 | U50: =SUM(I50:T50) -> 48000000 | V50: =I50*(1+$G50) -> 4160000 | W50: =J50*(1+$G50) -> 4160000 | X50: =K50*(1+$G50) -> 4160000 | Y50: =L50*(1+$G50) -> 4160000 | Z50: =M50*(1+$G50) -> 4160000 | AA50: =N50*(1+$G50) -> 4160000 | AB50: =O50*(1+$G50) -> 4160000 | AC50: =P50*(1+$G50) -> 4160000 | ... AG50: =T50*(1+$G50) -> 4160000 | AH50: =SUM(V50:AG50) -> 49920000 | AJ50: =AH50-U50 -> 1920000 | AK50: =IFERROR(AJ50/ABS(U50),"") -> 0.04 | AL50: =SUM(V50:X50)-SUM(I50:K50) -> 480000 | AM50: =SUM(Y50:AA50)-SUM(L50:N50) -> 480000 | AN50: =SUM(AB50:AD50)-SUM(O50:Q50) -> 480000 | AO50: =SUM(AE50:AG50)-SUM(R50:T50) -> 480000 | AP50: =IFERROR(AL50/ABS(SUM(I50:K50)),"") -> 0.04 | AQ50: =IFERROR(AM50/ABS(SUM(L50:N50)),"") -> 0.04 | AR50: =IFERROR(AN50/ABS(SUM(O50:Q50)),"") -> 0.04 | AS50: =IFERROR(AO50/ABS(SUM(R50:T50)),"") -> 0.04 | AU50: =IFERROR(U50/$U$17,0) -> 0.004 | AV50: =IFERROR(AH50/$AH$17,0) -> 0.0036553754 | AW50: =(AV50-AU50)*100 -> -0.034462458
B51: Total gastos financieros | D51: Gasto | I51: =SUM(I49:I50) -> 25700000 | J51: =SUM(J49:J50) -> 25700000 | K51: =SUM(K49:K50) -> 25700000 | L51: =SUM(L49:L50) -> 25700000 | M51: =SUM(M49:M50) -> 25700000 | N51: =SUM(N49:N50) -> 25700000 | O51: =SUM(O49:O50) -> 25700000 | P51: =SUM(P49:P50) -> 25700000 | ... T51: =SUM(T49:T50) -> 25300000 | U51: =SUM(I51:T51) -> 308000000 | V51: =SUM(V49:V50) -> 23690000 | W51: =SUM(W49:W50) -> 23690000 | X51: =SUM(X49:X50) -> 23690000 | Y51: =SUM(Y49:Y50) -> 23690000 | Z51: =SUM(Z49:Z50) -> 23690000 | AA51: =SUM(AA49:AA50) -> 23690000 | AB51: =SUM(AB49:AB50) -> 23690000 | AC51: =SUM(AC49:AC50) -> 23690000 | ... AG51: =SUM(AG49:AG50) -> 23330000 | AH51: =SUM(V51:AG51) -> 283920000 | AJ51: =AH51-U51 -> -24080000 | AK51: =IFERROR(AJ51/ABS(U51),"") -> -0.078181818 | AL51: =SUM(V51:X51)-SUM(I51:K51) -> -6030000 | AM51: =SUM(Y51:AA51)-SUM(L51:N51) -> -6030000 | AN51: =SUM(AB51:AD51)-SUM(O51:Q51) -> -6030000 | AO51: =SUM(AE51:AG51)-SUM(R51:T51) -> -5990000 | AP51: =IFERROR(AL51/ABS(SUM(I51:K51)),"") -> -0.078210117 | AQ51: =IFERROR(AM51/ABS(SUM(L51:N51)),"") -> -0.078210117 | AR51: =IFERROR(AN51/ABS(SUM(O51:Q51)),"") -> -0.078210117 | AS51: =IFERROR(AO51/ABS(SUM(R51:T51)),"") -> -0.07809648 | AU51: =IFERROR(U51/$U$17,0) -> 0.025666667 | AV51: =IFERROR(AH51/$AH$17,0) -> 0.020789948 | AW51: =(AV51-AU51)*100 -> -0.48767189
B52: OTROS INGRESOS NO OPERACIONALES
B53: Ingresos por arrendamientos | C53: Otros ingresos no operacionales | D53: Ingreso | E53: Corporativo | F53: IPC | G53: =pIPC -> 0.04 | I53: 5000000 | J53: 5000000 | K53: 5000000 | L53: 5000000 | M53: 5000000 | N53: 5000000 | O53: 5000000 | P53: 5000000 | Q53: 5000000 | R53: 5000000 | S53: 5000000 | T53: 5000000 | U53: =SUM(I53:T53) -> 60000000 | V53: =I53*(1+$G53) -> 5200000 | W53: =J53*(1+$G53) -> 5200000 | X53: =K53*(1+$G53) -> 5200000 | Y53: =L53*(1+$G53) -> 5200000 | Z53: =M53*(1+$G53) -> 5200000 | AA53: =N53*(1+$G53) -> 5200000 | AB53: =O53*(1+$G53) -> 5200000 | AC53: =P53*(1+$G53) -> 5200000 | ... AG53: =T53*(1+$G53) -> 5200000 | AH53: =SUM(V53:AG53) -> 62400000 | AJ53: =AH53-U53 -> 2400000 | AK53: =IFERROR(AJ53/ABS(U53),"") -> 0.04 | AL53: =SUM(V53:X53)-SUM(I53:K53) -> 600000 | AM53: =SUM(Y53:AA53)-SUM(L53:N53) -> 600000 | AN53: =SUM(AB53:AD53)-SUM(O53:Q53) -> 600000 | AO53: =SUM(AE53:AG53)-SUM(R53:T53) -> 600000 | AP53: =IFERROR(AL53/ABS(SUM(I53:K53)),"") -> 0.04 | AQ53: =IFERROR(AM53/ABS(SUM(L53:N53)),"") -> 0.04 | AR53: =IFERROR(AN53/ABS(SUM(O53:Q53)),"") -> 0.04 | AS53: =IFERROR(AO53/ABS(SUM(R53:T53)),"") -> 0.04 | AU53: =IFERROR(U53/$U$17,0) -> 0.005 | AV53: =IFERROR(AH53/$AH$17,0) -> 0.0045692193 | AW53: =(AV53-AU53)*100 -> -0.043078072
B54: Total otros ingresos no operacionales | D54: Ingreso | I54: =SUM(I53:I53) -> 5000000 | J54: =SUM(J53:J53) -> 5000000 | K54: =SUM(K53:K53) -> 5000000 | L54: =SUM(L53:L53) -> 5000000 | M54: =SUM(M53:M53) -> 5000000 | N54: =SUM(N53:N53) -> 5000000 | O54: =SUM(O53:O53) -> 5000000 | P54: =SUM(P53:P53) -> 5000000 | ... T54: =SUM(T53:T53) -> 5000000 | U54: =SUM(I54:T54) -> 60000000 | V54: =SUM(V53:V53) -> 5200000 | W54: =SUM(W53:W53) -> 5200000 | X54: =SUM(X53:X53) -> 5200000 | Y54: =SUM(Y53:Y53) -> 5200000 | Z54: =SUM(Z53:Z53) -> 5200000 | AA54: =SUM(AA53:AA53) -> 5200000 | AB54: =SUM(AB53:AB53) -> 5200000 | AC54: =SUM(AC53:AC53) -> 5200000 | ... AG54: =SUM(AG53:AG53) -> 5200000 | AH54: =SUM(V54:AG54) -> 62400000 | AJ54: =AH54-U54 -> 2400000 | AK54: =IFERROR(AJ54/ABS(U54),"") -> 0.04 | AL54: =SUM(V54:X54)-SUM(I54:K54) -> 600000 | AM54: =SUM(Y54:AA54)-SUM(L54:N54) -> 600000 | AN54: =SUM(AB54:AD54)-SUM(O54:Q54) -> 600000 | AO54: =SUM(AE54:AG54)-SUM(R54:T54) -> 600000 | AP54: =IFERROR(AL54/ABS(SUM(I54:K54)),"") -> 0.04 | AQ54: =IFERROR(AM54/ABS(SUM(L54:N54)),"") -> 0.04 | AR54: =IFERROR(AN54/ABS(SUM(O54:Q54)),"") -> 0.04 | AS54: =IFERROR(AO54/ABS(SUM(R54:T54)),"") -> 0.04 | AU54: =IFERROR(U54/$U$17,0) -> 0.005 | AV54: =IFERROR(AH54/$AH$17,0) -> 0.0045692193 | AW54: =(AV54-AU54)*100 -> -0.043078072
B55: OTROS GASTOS NO OPERACIONALES
B56: Gastos extraordinarios | C56: Otros gastos no operacionales | D56: Gasto | E56: Corporativo | F56: Fijo | G56: 0 | I56: 3300000 | J56: 3300000 | K56: 3300000 | L56: 3300000 | M56: 3300000 | N56: 3300000 | O56: 3300000 | P56: 3300000 | Q56: 3300000 | R56: 3300000 | S56: 3300000 | T56: 3700000 | U56: =SUM(I56:T56) -> 40000000 | V56: =I56*(1+$G56) -> 3300000 | W56: =J56*(1+$G56) -> 3300000 | X56: =K56*(1+$G56) -> 3300000 | Y56: =L56*(1+$G56) -> 3300000 | Z56: =M56*(1+$G56) -> 3300000 | AA56: =N56*(1+$G56) -> 3300000 | AB56: =O56*(1+$G56) -> 3300000 | AC56: =P56*(1+$G56) -> 3300000 | ... AG56: =T56*(1+$G56) -> 3700000 | AH56: =SUM(V56:AG56) -> 40000000 | AJ56: =AH56-U56 -> 0 | AK56: =IFERROR(AJ56/ABS(U56),"") -> 0 | AL56: =SUM(V56:X56)-SUM(I56:K56) -> 0 | AM56: =SUM(Y56:AA56)-SUM(L56:N56) -> 0 | AN56: =SUM(AB56:AD56)-SUM(O56:Q56) -> 0 | AO56: =SUM(AE56:AG56)-SUM(R56:T56) -> 0 | AP56: =IFERROR(AL56/ABS(SUM(I56:K56)),"") -> 0 | AQ56: =IFERROR(AM56/ABS(SUM(L56:N56)),"") -> 0 | AR56: =IFERROR(AN56/ABS(SUM(O56:Q56)),"") -> 0 | AS56: =IFERROR(AO56/ABS(SUM(R56:T56)),"") -> 0 | AU56: =IFERROR(U56/$U$17,0) -> 0.0033333333 | AV56: =IFERROR(AH56/$AH$17,0) -> 0.0029289867 | AW56: =(AV56-AU56)*100 -> -0.040434662
B57: Total otros gastos no operacionales | D57: Gasto | I57: =SUM(I56:I56) -> 3300000 | J57: =SUM(J56:J56) -> 3300000 | K57: =SUM(K56:K56) -> 3300000 | L57: =SUM(L56:L56) -> 3300000 | M57: =SUM(M56:M56) -> 3300000 | N57: =SUM(N56:N56) -> 3300000 | O57: =SUM(O56:O56) -> 3300000 | P57: =SUM(P56:P56) -> 3300000 | ... T57: =SUM(T56:T56) -> 3700000 | U57: =SUM(I57:T57) -> 40000000 | V57: =SUM(V56:V56) -> 3300000 | W57: =SUM(W56:W56) -> 3300000 | X57: =SUM(X56:X56) -> 3300000 | Y57: =SUM(Y56:Y56) -> 3300000 | Z57: =SUM(Z56:Z56) -> 3300000 | AA57: =SUM(AA56:AA56) -> 3300000 | AB57: =SUM(AB56:AB56) -> 3300000 | AC57: =SUM(AC56:AC56) -> 3300000 | ... AG57: =SUM(AG56:AG56) -> 3700000 | AH57: =SUM(V57:AG57) -> 40000000 | AJ57: =AH57-U57 -> 0 | AK57: =IFERROR(AJ57/ABS(U57),"") -> 0 | AL57: =SUM(V57:X57)-SUM(I57:K57) -> 0 | AM57: =SUM(Y57:AA57)-SUM(L57:N57) -> 0 | AN57: =SUM(AB57:AD57)-SUM(O57:Q57) -> 0 | AO57: =SUM(AE57:AG57)-SUM(R57:T57) -> 0 | AP57: =IFERROR(AL57/ABS(SUM(I57:K57)),"") -> 0 | AQ57: =IFERROR(AM57/ABS(SUM(L57:N57)),"") -> 0 | AR57: =IFERROR(AN57/ABS(SUM(O57:Q57)),"") -> 0 | AS57: =IFERROR(AO57/ABS(SUM(R57:T57)),"") -> 0 | AU57: =IFERROR(U57/$U$17,0) -> 0.0033333333 | AV57: =IFERROR(AH57/$AH$17,0) -> 0.0029289867 | AW57: =(AV57-AU57)*100 -> -0.040434662
B58: Utilidad antes de impuestos | D58: T | I58: =I43-I51+I54-I57 -> -4200000 | J58: =J43-J51+J54-J57 -> 11400000 | K58: =K43-K51+K54-K57 -> 42100000 | L58: =L43-L51+L54-L57 -> 42100000 | M58: =M43-M51+M54-M57 -> 57700000 | N58: =N43-N51+N54-N57 -> 57700000 | O58: =O43-O51+O54-O57 -> 57700000 | P58: =P43-P51+P54-P57 -> 73200000 | ... T58: =T43-T51+T54-T57 -> 119400000 | U58: =SUM(I58:T58) -> 692000000 | V58: =V43-V51+V54-V57 -> 28468790 | W58: =W43-W51+W54-W57 -> 46979680 | X58: =X43-X51+X54-X57 -> 83453970 | Y58: =Y43-Y51+Y54-Y57 -> 83453970 | Z58: =Z43-Z51+Z54-Z57 -> 101964860 | AA58: =AA43-AA51+AA54-AA57 -> 101964860 | AB58: =AB43-AB51+AB54-AB57 -> 101964860 | AC58: =AC43-AC51+AC54-AC57 -> 120363920 | ... AG58: =AG43-AG51+AG54-AG57 -> 175197270 | AH58: =SUM(V58:AG58) -> 1223091000 | AJ58: =AH58-U58 -> 531091000 | AK58: =IFERROR(AJ58/ABS(U58),"") -> 0.76747254 | AL58: =SUM(V58:X58)-SUM(I58:K58) -> 109602440 | AM58: =SUM(Y58:AA58)-SUM(L58:N58) -> 129883690 | AN58: =SUM(AB58:AD58)-SUM(O58:Q58) -> 135693640 | AO58: =SUM(AE58:AG58)-SUM(R58:T58) -> 155911230 | AP58: =IFERROR(AL58/ABS(SUM(I58:K58)),"") -> 2.2231732 | AQ58: =IFERROR(AM58/ABS(SUM(L58:N58)),"") -> 0.82465835 | AR58: =IFERROR(AN58/ABS(SUM(O58:Q58)),"") -> 0.71947847 | AS58: =IFERROR(AO58/ABS(SUM(R58:T58)),"") -> 0.5256616 | AU58: =IFERROR(U58/$U$17,0) -> 0.057666667 | AV58: =IFERROR(AH58/$AH$17,0) -> 0.089560432 | AW58: =(AV58-AU58)*100 -> 3.1893766
B59: Impuesto de renta | D59: Gasto | F59: Tasa de renta | G59: 0.35 | I59: =I58*_xlfn.SINGLE(pTasaRenta) -> -1470000 | J59: =J58*_xlfn.SINGLE(pTasaRenta) -> 3990000 | K59: =K58*_xlfn.SINGLE(pTasaRenta) -> 14735000 | L59: =L58*_xlfn.SINGLE(pTasaRenta) -> 14735000 | M59: =M58*_xlfn.SINGLE(pTasaRenta) -> 20195000 | N59: =N58*_xlfn.SINGLE(pTasaRenta) -> 20195000 | O59: =O58*_xlfn.SINGLE(pTasaRenta) -> 20195000 | P59: =P58*_xlfn.SINGLE(pTasaRenta) -> 25620000 | ... T59: =T58*_xlfn.SINGLE(pTasaRenta) -> 41790000 | U59: =SUM(I59:T59) -> 242200000 | V59: =V58*_xlfn.SINGLE(pTasaRenta) -> 9964076.5 | W59: =W58*_xlfn.SINGLE(pTasaRenta) -> 16442888 | X59: =X58*_xlfn.SINGLE(pTasaRenta) -> 29208890 | Y59: =Y58*_xlfn.SINGLE(pTasaRenta) -> 29208890 | Z59: =Z58*_xlfn.SINGLE(pTasaRenta) -> 35687701 | AA59: =AA58*_xlfn.SINGLE(pTasaRenta) -> 35687701 | AB59: =AB58*_xlfn.SINGLE(pTasaRenta) -> 35687701 | AC59: =AC58*_xlfn.SINGLE(pTasaRenta) -> 42127372 | ... AG59: =AG58*_xlfn.SINGLE(pTasaRenta) -> 61319044 | AH59: =SUM(V59:AG59) -> 428081850 | AJ59: =AH59-U59 -> 185881850 | AK59: =IFERROR(AJ59/ABS(U59),"") -> 0.76747254 | AL59: =SUM(V59:X59)-SUM(I59:K59) -> 38360854 | AM59: =SUM(Y59:AA59)-SUM(L59:N59) -> 45459292 | AN59: =SUM(AB59:AD59)-SUM(O59:Q59) -> 47492774 | AO59: =SUM(AE59:AG59)-SUM(R59:T59) -> 54568930 | AP59: =IFERROR(AL59/ABS(SUM(I59:K59)),"") -> 2.2231732 | AQ59: =IFERROR(AM59/ABS(SUM(L59:N59)),"") -> 0.82465835 | AR59: =IFERROR(AN59/ABS(SUM(O59:Q59)),"") -> 0.71947847 | AS59: =IFERROR(AO59/ABS(SUM(R59:T59)),"") -> 0.5256616 | AU59: =IFERROR(U59/$U$17,0) -> 0.020183333 | AV59: =IFERROR(AH59/$AH$17,0) -> 0.031346151 | AW59: =(AV59-AU59)*100 -> 1.1162818
B60: Utilidad neta | D60: T | I60: =I58-I59 -> -2730000 | J60: =J58-J59 -> 7410000 | K60: =K58-K59 -> 27365000 | L60: =L58-L59 -> 27365000 | M60: =M58-M59 -> 37505000 | N60: =N58-N59 -> 37505000 | O60: =O58-O59 -> 37505000 | P60: =P58-P59 -> 47580000 | ... T60: =T58-T59 -> 77610000 | U60: =SUM(I60:T60) -> 449800000 | V60: =V58-V59 -> 18504714 | W60: =W58-W59 -> 30536792 | X60: =X58-X59 -> 54245080 | Y60: =Y58-Y59 -> 54245080 | Z60: =Z58-Z59 -> 66277159 | AA60: =AA58-AA59 -> 66277159 | AB60: =AB58-AB59 -> 66277159 | AC60: =AC58-AC59 -> 78236548 | ... AG60: =AG58-AG59 -> 1.1387823e+08 | AH60: =SUM(V60:AG60) -> 795009150 | AJ60: =AH60-U60 -> 345209150 | AK60: =IFERROR(AJ60/ABS(U60),"") -> 0.76747254 | AL60: =SUM(V60:X60)-SUM(I60:K60) -> 71241586 | AM60: =SUM(Y60:AA60)-SUM(L60:N60) -> 84424398 | AN60: =SUM(AB60:AD60)-SUM(O60:Q60) -> 88200866 | AO60: =SUM(AE60:AG60)-SUM(R60:T60) -> 1.013423e+08 | AP60: =IFERROR(AL60/ABS(SUM(I60:K60)),"") -> 2.2231732 | AQ60: =IFERROR(AM60/ABS(SUM(L60:N60)),"") -> 0.82465835 | AR60: =IFERROR(AN60/ABS(SUM(O60:Q60)),"") -> 0.71947847 | AS60: =IFERROR(AO60/ABS(SUM(R60:T60)),"") -> 0.5256616 | AU60: =IFERROR(U60/$U$17,0) -> 0.037483333 | AV60: =IFERROR(AH60/$AH$17,0) -> 0.058214281 | AW60: =(AV60-AU60)*100 -> 2.0730948
B61: Margen neto | D61: M | I61: =IFERROR(I60/I17,0) -> -0.0034125 | J61: =IFERROR(J60/J17,0) -> 0.0087176471 | K61: =IFERROR(K60/K17,0) -> 0.028805263 | L61: =IFERROR(L60/L17,0) -> 0.028805263 | M61: =IFERROR(M60/M17,0) -> 0.037505 | N61: =IFERROR(N60/N17,0) -> 0.037505 | O61: =IFERROR(O60/O17,0) -> 0.037505 | P61: =IFERROR(P60/P17,0) -> 0.045314286 | ... AH61: =IFERROR(AH60/AH17,0) -> 0.058214281 | AK61: =(AH61-U61)*100 -> 2.0730948 | AP61: =(IFERROR(SUM(V60:X60)/SUM(V17:X17),0)-IFERROR(SUM(I60:K60)/SUM(I17:K17),0))*100 -> 2.2581735 | AQ61: =(IFERROR(SUM(Y60:AA60)/SUM(Y17:AA17),0)-IFERROR(SUM(L60:N60)/SUM(L17:N17),0))*100 -> 2.093725 | AR61: =(IFERROR(SUM(AB60:AD60)/SUM(AB17:AD17),0)-IFERROR(SUM(O60:Q60)/SUM(O17:Q17),0))*100 -> 2.0534785 | AS61: =(IFERROR(SUM(AE60:AG60)/SUM(AE17:AG17),0)-IFERROR(SUM(R60:T60)/SUM(R17:T17),0))*100 -> 1.9312612

Sheet Estado de resultados
B2: ESTADO DE RESULTADOS · PRESUPUESTO 2027 VS. REAL 2026
B3: Millones de pesos · se recalcula al instante al cambiar un supuesto en la hoja PPTO 2027 · datos de ejemplo
B4: ← Volver al tablero
B6: Estado de resultados | C6: Real 2026 | D6: Ppto 2027 | E6: Var $ | F6: Var %
B7: Ingresos operacionales | C7: =(SUMIFS(qPPTO[Real],qPPTO[Línea],"Ingresos operacionales"))/1000000 -> 12000 | D7: =(SUMIFS(qPPTO[Presupuesto],qPPTO[Línea],"Ingresos operacionales"))/1000000 -> 13656.6 | E7: =D7-C7 -> 1656.6 | F7: =IFERROR(E7/ABS(C7),"") -> 0.13805
B8: Costo de ventas | C8: =(SUMIFS(qPPTO[Real],qPPTO[Línea],"Costo de ventas"))/1000000 -> 7630 | D8: =(SUMIFS(qPPTO[Presupuesto],qPPTO[Línea],"Costo de ventas"))/1000000 -> 8532.629 | E8: =D8-C8 -> 902.629 | F8: =IFERROR(E8/ABS(C8),"") -> 0.1183
B9: Utilidad bruta | C9: =(SUMIFS(qPPTO[Real],qPPTO[Línea],"Ingresos operacionales")-SUMIFS(qPPTO[Real],qPPTO[Línea],"Costo de ventas"))/1000000 -> 4370 | D9: =(SUMIFS(qPPTO[Presupuesto],qPPTO[Línea],"Ingresos operacionales")-SUMIFS(qPPTO[Presupuesto],qPPTO[Línea],"Costo de ventas"))/1000000 -> 5123.971 | E9: =D9-C9 -> 753.971 | F9: =IFERROR(E9/ABS(C9),"") -> 0.17253341
B10: Gastos de administración | C10: =(SUMIFS(qPPTO[Real],qPPTO[Línea],"Gastos de administración"))/1000000 -> 1260 | D10: =(SUMIFS(qPPTO[Presupuesto],qPPTO[Línea],"Gastos de administración"))/1000000 -> 1290 | E10: =D10-C10 -> 30 | F10: =IFERROR(E10/ABS(C10),"") -> 0.023809524
B11: Gastos de ventas | C11: =(SUMIFS(qPPTO[Real],qPPTO[Línea],"Gastos de ventas"))/1000000 -> 2130 | D11: =(SUMIFS(qPPTO[Presupuesto],qPPTO[Línea],"Gastos de ventas"))/1000000 -> 2349.36 | E11: =D11-C11 -> 219.36 | F11: =IFERROR(E11/ABS(C11),"") -> 0.10298592
B12: Utilidad operativa | C12: =(SUMIFS(qPPTO[Real],qPPTO[Línea],"Ingresos operacionales")-SUMIFS(qPPTO[Real],qPPTO[Línea],"Costo de ventas")-SUMIFS(qPPTO[Real],qPPTO[Línea],"Gastos de administración")-SUMIFS(qPPTO[Real],qPPTO[Línea],"Gastos de ventas"))/1000000 -> 980 | D12: =(SUMIFS(qPPTO[Presupuesto],qPPTO[Línea],"Ingresos operacionales")-SUMIFS(qPPTO[Presupuesto],qPPTO[Línea],"Costo de ventas")-SUMIFS(qPPTO[Presupuesto],qPPTO[Línea],"Gastos de administración")-SUMIFS(qPPTO[Presupuesto],qPPTO[Línea],"Gastos de ventas"))/1000000 -> 1484.611 | E12: =D12-C12 -> 504.611 | F12: =IFERROR(E12/ABS(C12),"") -> 0.51490918
B13: EBITDA | C13: =(SUMIFS(qPPTO[Real],qPPTO[Línea],"Ingresos operacionales")-SUMIFS(qPPTO[Real],qPPTO[Línea],"Costo de ventas")-SUMIFS(qPPTO[Real],qPPTO[Línea],"Gastos de administración")-SUMIFS(qPPTO[Real],qPPTO[Línea],"Gastos de ventas")+SUMIFS(qPPTO[Real],qPPTO[Cuenta],"Depreciación y amortización"))/1000000 -> 1160 | D13: =(SUMIFS(qPPTO[Presupuesto],qPPTO[Línea],"Ingresos operacionales")-SUMIFS(qPPTO[Presupuesto],qPPTO[Línea],"Costo de ventas")-SUMIFS(qPPTO[Presupuesto],qPPTO[Línea],"Gastos de administración")-SUMIFS(qPPTO[Presupuesto],qPPTO[Línea],"Gastos de ventas")+SUMIFS(qPPTO[Presupuesto],qPPTO[Cuenta],"Depreciación y amortización"))/1000000 -> 1664.611 | E13: =D13-C13 -> 504.611 | F13: =IFERROR(E13/ABS(C13),"") -> 0.43500948
B14: Gastos financieros | C14: =(SUMIFS(qPPTO[Real],qPPTO[Línea],"Gastos financieros"))/1000000 -> 308 | D14: =(SUMIFS(qPPTO[Presupuesto],qPPTO[Línea],"Gastos financieros"))/1000000 -> 283.92 | E14: =D14-C14 -> -24.08 | F14: =IFERROR(E14/ABS(C14),"") -> -0.078181818
B15: Otros ingresos no operacionales | C15: =(SUMIFS(qPPTO[Real],qPPTO[Línea],"Otros ingresos no operacionales"))/1000000 -> 60 | D15: =(SUMIFS(qPPTO[Presupuesto],qPPTO[Línea],"Otros ingresos no operacionales"))/1000000 -> 62.4 | E15: =D15-C15 -> 2.4 | F15: =IFERROR(E15/ABS(C15),"") -> 0.04
B16: Otros gastos no operacionales | C16: =(SUMIFS(qPPTO[Real],qPPTO[Línea],"Otros gastos no operacionales"))/1000000 -> 40 | D16: =(SUMIFS(qPPTO[Presupuesto],qPPTO[Línea],"Otros gastos no operacionales"))/1000000 -> 40 | E16: =D16-C16 -> 0 | F16: =IFERROR(E16/ABS(C16),"") -> 0
B17: Utilidad antes de impuestos | C17: =C12-C14+C15-C16 -> 692 | D17: =D12-D14+D15-D16 -> 1223.091 | E17: =D17-C17 -> 531.091 | F17: =IFERROR(E17/ABS(C17),"") -> 0.76747254
B18: Impuesto de renta | C18: =MAX(0,C17)*pTasaRenta -> 242.2 | D18: =MAX(0,D17)*pTasaRenta -> 428.08185 | E18: =D18-C18 -> 185.88185 | F18: =IFERROR(E18/ABS(C18),"") -> 0.76747254
B19: Utilidad neta | C19: =C17-C18 -> 449.8 | D19: =D17-D18 -> 795.00915 | E19: =D19-C19 -> 345.20915 | F19: =IFERROR(E19/ABS(C19),"") -> 0.76747254
B21: Márgenes | E21: Var
B22: Margen bruto | C22: =IFERROR(C9/C7,0) -> 0.36416667 | D22: =IFERROR(D9/D7,0) -> 0.37520107 | E22: =(D22-C22)*100 -> 1.1034408
B23: Margen EBITDA | C23: =IFERROR(C13/C7,0) -> 0.096666667 | D23: =IFERROR(D13/D7,0) -> 0.12189059 | E23: =(D23-C23)*100 -> 2.5223921
B24: Margen neto | C24: =IFERROR(C19/C7,0) -> 0.037483333 | D24: =IFERROR(D19/D7,0) -> 0.058214281 | E24: =(D24-C24)*100 -> 2.0730948
B27: MES A MES · PRESUPUESTO 2027 CONTRA EL MISMO MES DE 2026
B28: Variación de cada mes contra el mismo mes del año anterior, no contra el promedio. Tendencia: cómo se mueve esa variación a lo largo del año (verde el mes más alto, rojo el más bajo).
B30: Línea | C30: Real 2026 | D30: Ppto 2027 | E30: Var % | F30: Tendencia | H30: Ene | I30: Feb | J30: Mar | K30: Abr | L30: May | M30: Jun | N30: Jul | O30: Ago | P30: Sep | Q30: Oct | R30: Nov | S30: Dic
B31: Ingresos operacionales | C31: =C7 -> 12000 | D31: =D7 -> 13656.6 | E31: =F7 -> 0.13805 | H31: =IFERROR((SUMIFS(qPPTO[Presupuesto],qPPTO[Línea],"Ingresos operacionales",qPPTO[Mes],"Ene"))/(SUMIFS(qPPTO[Real],qPPTO[Línea],"Ingresos operacionales",qPPTO[Mes],"Ene"))-1,"") -> 0.13805 | I31: =IFERROR((SUMIFS(qPPTO[Presupuesto],qPPTO[Línea],"Ingresos operacionales",qPPTO[Mes],"Feb"))/(SUMIFS(qPPTO[Real],qPPTO[Línea],"Ingresos operacionales",qPPTO[Mes],"Feb"))-1,"") -> 0.13805 | J31: =IFERROR((SUMIFS(qPPTO[Presupuesto],qPPTO[Línea],"Ingresos operacionales",qPPTO[Mes],"Mar"))/(SUMIFS(qPPTO[Real],qPPTO[Línea],"Ingresos operacionales",qPPTO[Mes],"Mar"))-1,"") -> 0.13805 | K31: =IFERROR((SUMIFS(qPPTO[Presupuesto],qPPTO[Línea],"Ingresos operacionales",qPPTO[Mes],"Abr"))/(SUMIFS(qPPTO[Real],qPPTO[Línea],"Ingresos operacionales",qPPTO[Mes],"Abr"))-1,"") -> 0.13805 | L31: =IFERROR((SUMIFS(qPPTO[Presupuesto],qPPTO[Línea],"Ingresos operacionales",qPPTO[Mes],"May"))/(SUMIFS(qPPTO[Real],qPPTO[Línea],"Ingresos operacionales",qPPTO[Mes],"May"))-1,"") -> 0.13805 | M31: =IFERROR((SUMIFS(qPPTO[Presupuesto],qPPTO[Línea],"Ingresos operacionales",qPPTO[Mes],"Jun"))/(SUMIFS(qPPTO[Real],qPPTO[Línea],"Ingresos operacionales",qPPTO[Mes],"Jun"))-1,"") -> 0.13805 | N31: =IFERROR((SUMIFS(qPPTO[Presupuesto],qPPTO[Línea],"Ingresos operacionales",qPPTO[Mes],"Jul"))/(SUMIFS(qPPTO[Real],qPPTO[Línea],"Ingresos operacionales",qPPTO[Mes],"Jul"))-1,"") -> 0.13805 | O31: =IFERROR((SUMIFS(qPPTO[Presupuesto],qPPTO[Línea],"Ingresos operacionales",qPPTO[Mes],"Ago"))/(SUMIFS(qPPTO[Real],qPPTO[Línea],"Ingresos operacionales",qPPTO[Mes],"Ago"))-1,"") -> 0.13805 | P31: =IFERROR((SUMIFS(qPPTO[Presupuesto],qPPTO[Línea],"Ingresos operacionales",qPPTO[Mes],"Sep"))/(SUMIFS(qPPTO[Real],qPPTO[Línea],"Ingresos operacionales",qPPTO[Mes],"Sep"))-1,"") -> 0.13805 | Q31: =IFERROR((SUMIFS(qPPTO[Presupuesto],qPPTO[Línea],"Ingresos operacionales",qPPTO[Mes],"Oct"))/(SUMIFS(qPPTO[Real],qPPTO[Línea],"Ingresos operacionales",qPPTO[Mes],"Oct"))-1,"") -> 0.13805 | R31: =IFERROR((SUMIFS(qPPTO[Presupuesto],qPPTO[Línea],"Ingresos operacionales",qPPTO[Mes],"Nov"))/(SUMIFS(qPPTO[Real],qPPTO[Línea],"Ingresos operacionales",qPPTO[Mes],"Nov"))-1,"") -> 0.13805 | S31: =IFERROR((SUMIFS(qPPTO[Presupuesto],qPPTO[Línea],"Ingresos operacionales",qPPTO[Mes],"Dic"))/(SUMIFS(qPPTO[Real],qPPTO[Línea],"Ingresos operacionales",qPPTO[Mes],"Dic"))-1,"") -> 0.13805
B32: Utilidad bruta | C32: =C9 -> 4370 | D32: =D9 -> 5123.971 | E32: =F9 -> 0.17253341 | H32: =IFERROR((SUMIFS(qPPTO[Presupuesto],qPPTO[Línea],"Ingresos operacionales",qPPTO[Mes],"Ene")-SUMIFS(qPPTO[Presupuesto],qPPTO[Línea],"Costo de ventas",qPPTO[Mes],"Ene"))/(SUMIFS(qPPTO[Real],qPPTO[Línea],"Ingresos operacionales",qPPTO[Mes],"Ene")-SUMIFS(qPPTO[Real],qPPTO[Línea],"Costo de ventas",qPPTO[Mes],"Ene"))-1,"") -> 0.17253962 | I32: =IFERROR((SUMIFS(qPPTO[Presupuesto],qPPTO[Línea],"Ingresos operacionales",qPPTO[Mes],"Feb")-SUMIFS(qPPTO[Presupuesto],qPPTO[Línea],"Costo de ventas",qPPTO[Mes],"Feb"))/(SUMIFS(qPPTO[Real],qPPTO[Línea],"Ingresos operacionales",qPPTO[Mes],"Feb")-SUMIFS(qPPTO[Real],qPPTO[Línea],"Costo de ventas",qPPTO[Mes],"Feb"))-1,"") -> 0.17252319 | J32: =IFERROR((SUMIFS(qPPTO[Presupuesto],qPPTO[Línea],"Ingresos operacionales",qPPTO[Mes],"Mar")-SUMIFS(qPPTO[Presupuesto],qPPTO[Línea],"Costo de ventas",qPPTO[Mes],"Mar"))/(SUMIFS(qPPTO[Real],qPPTO[Línea],"Ingresos operacionales",qPPTO[Mes],"Mar")-SUMIFS(qPPTO[Real],qPPTO[Línea],"Costo de ventas",qPPTO[Mes],"Mar"))-1,"") -> 0.17254256 | K32: =IFERROR((SUMIFS(qPPTO[Presupuesto],qPPTO[Línea],"Ingresos operacionales",qPPTO[Mes],"Abr")-SUMIFS(qPPTO[Presupuesto],qPPTO[Línea],"Costo de ventas",qPPTO[Mes],"Abr"))/(SUMIFS(qPPTO[Real],qPPTO[Línea],"Ingresos operacionales",qPPTO[Mes],"Abr")-SUMIFS(qPPTO[Real],qPPTO[Línea],"Costo de ventas",qPPTO[Mes],"Abr"))-1,"") -> 0.17254256 | L32: =IFERROR((SUMIFS(qPPTO[Presupuesto],qPPTO[Línea],"Ingresos operacionales",qPPTO[Mes],"May")-SUMIFS(qPPTO[Presupuesto],qPPTO[Línea],"Costo de ventas",qPPTO[Mes],"May"))/(SUMIFS(qPPTO[Real],qPPTO[Línea],"Ingresos operacionales",qPPTO[Mes],"May")-SUMIFS(qPPTO[Real],qPPTO[Línea],"Costo de ventas",qPPTO[Mes],"May"))-1,"") -> 0.17252845 | M32: =IFERROR((SUMIFS(qPPTO[Presupuesto],qPPTO[Línea],"Ingresos operacionales",qPPTO[Mes],"Jun")-SUMIFS(qPPTO[Presupuesto],qPPTO[Línea],"Costo de ventas",qPPTO[Mes],"Jun"))/(SUMIFS(qPPTO[Real],qPPTO[Línea],"Ingresos operacionales",qPPTO[Mes],"Jun")-SUMIFS(qPPTO[Real],qPPTO[Línea],"Costo de ventas",qPPTO[Mes],"Jun"))-1,"") -> 0.17252845 | N32: =IFERROR((SUMIFS(qPPTO[Presupuesto],qPPTO[Línea],"Ingresos operacionales",qPPTO[Mes],"Jul")-SUMIFS(qPPTO[Presupuesto],qPPTO[Línea],"Costo de ventas",qPPTO[Mes],"Jul"))/(SUMIFS(qPPTO[Real],qPPTO[Línea],"Ingresos operacionales",qPPTO[Mes],"Jul")-SUMIFS(qPPTO[Real],qPPTO[Línea],"Costo de ventas",qPPTO[Mes],"Jul"))-1,"") -> 0.17252845 | O32: =IFERROR((SUMIFS(qPPTO[Presupuesto],qPPTO[Línea],"Ingresos operacionales",qPPTO[Mes],"Ago")-SUMIFS(qPPTO[Presupuesto],qPPTO[Línea],"Costo de ventas",qPPTO[Mes],"Ago"))/(SUMIFS(qPPTO[Real],qPPTO[Línea],"Ingresos operacionales",qPPTO[Mes],"Ago")-SUMIFS(qPPTO[Real],qPPTO[Línea],"Costo de ventas",qPPTO[Mes],"Ago"))-1,"") -> 0.17252986 | P32: =IFERROR((SUMIFS(qPPTO[Presupuesto],qPPTO[Línea],"Ingresos operacionales",qPPTO[Mes],"Sep")-SUMIFS(qPPTO[Presupuesto],qPPTO[Línea],"Costo de ventas",qPPTO[Mes],"Sep"))/(SUMIFS(qPPTO[Real],qPPTO[Línea],"Ingresos operacionales",qPPTO[Mes],"Sep")-SUMIFS(qPPTO[Real],qPPTO[Línea],"Costo de ventas",qPPTO[Mes],"Sep"))-1,"") -> 0.17252845 | Q32: =IFERROR((SUMIFS(qPPTO[Presupuesto],qPPTO[Línea],"Ingresos operacionales",qPPTO[Mes],"Oct")-SUMIFS(qPPTO[Presupuesto],qPPTO[Línea],"Costo de ventas",qPPTO[Mes],"Oct"))/(SUMIFS(qPPTO[Real],qPPTO[Línea],"Ingresos operacionales",qPPTO[Mes],"Oct")-SUMIFS(qPPTO[Real],qPPTO[Línea],"Costo de ventas",qPPTO[Mes],"Oct"))-1,"") -> 0.17252986 | R32: =IFERROR((SUMIFS(qPPTO[Presupuesto],qPPTO[Línea],"Ingresos operacionales",qPPTO[Mes],"Nov")-SUMIFS(qPPTO[Presupuesto],qPPTO[Línea],"Costo de ventas",qPPTO[Mes],"Nov"))/(SUMIFS(qPPTO[Real],qPPTO[Línea],"Ingresos operacionales",qPPTO[Mes],"Nov")-SUMIFS(qPPTO[Real],qPPTO[Línea],"Costo de ventas",qPPTO[Mes],"Nov"))-1,"") -> 0.17253233 | S32: =IFERROR((SUMIFS(qPPTO[Presupuesto],qPPTO[Línea],"Ingresos operacionales",qPPTO[Mes],"Dic")-SUMIFS(qPPTO[Presupuesto],qPPTO[Línea],"Costo de ventas",qPPTO[Mes],"Dic"))/(SUMIFS(qPPTO[Real],qPPTO[Línea],"Ingresos operacionales",qPPTO[Mes],"Dic")-SUMIFS(qPPTO[Real],qPPTO[Línea],"Costo de ventas",qPPTO[Mes],"Dic"))-1,"") -> 0.17254582
B33: Utilidad operativa | C33: =C12 -> 980 | D33: =D12 -> 1484.611 | E33: =F12 -> 0.51490918 | H33: =IFERROR((SUMIFS(qPPTO[Presupuesto],qPPTO[Línea],"Ingresos operacionales",qPPTO[Mes],"Ene")-SUMIFS(qPPTO[Presupuesto],qPPTO[Línea],"Costo de ventas",qPPTO[Mes],"Ene")-SUMIFS(qPPTO[Presupuesto],qPPTO[Línea],"Gastos de administración",qPPTO[Mes],"Ene")-SUMIFS(qPPTO[Presupuesto],qPPTO[Línea],"Gastos de ventas",qPPTO[Mes],"Ene"))/(SUMIFS(qPPTO[Real],qPPTO[Línea],"Ingresos operacionales",qPPTO[Mes],"Ene")-SUMIFS(qPPTO[Real],qPPTO[Línea],"Costo de ventas",qPPTO[Mes],"Ene")-SUMIFS(qPPTO[Real],qPPTO[Línea],"Gastos de administración",qPPTO[Mes],"Ene")-SUMIFS(qPPTO[Real],qPPTO[Línea],"Gastos de ventas",qPPTO[Mes],"Ene"))-1,"") -> 1.5383227 | I33: =IFERROR((SUMIFS(qPPTO[Presupuesto],qPPTO[Línea],"Ingresos operacionales",qPPTO[Mes],"Feb")-SUMIFS(qPPTO[Presupuesto],qPPTO[Línea],"Costo de ventas",qPPTO[Mes],"Feb")-SUMIFS(qPPTO[Presupuesto],qPPTO[Línea],"Gastos de administración",qPPTO[Mes],"Feb")-SUMIFS(qPPTO[Presupuesto],qPPTO[Línea],"Gastos de ventas",qPPTO[Mes],"Feb"))/(SUMIFS(qPPTO[Real],qPPTO[Línea],"Ingresos operacionales",qPPTO[Mes],"Feb")-SUMIFS(qPPTO[Real],qPPTO[Línea],"Costo de ventas",qPPTO[Mes],"Feb")-SUMIFS(qPPTO[Real],qPPTO[Línea],"Gastos de administración",qPPTO[Mes],"Feb")-SUMIFS(qPPTO[Real],qPPTO[Línea],"Gastos de ventas",qPPTO[Mes],"Feb"))-1,"") -> 0.94264633 | J33: =IFERROR((SUMIFS(qPPTO[Presupuesto],qPPTO[Línea],"Ingresos operacionales",qPPTO[Mes],"Mar")-SUMIFS(qPPTO[Presupuesto],qPPTO[Línea],"Costo de ventas",qPPTO[Mes],"Mar")-SUMIFS(qPPTO[Presupuesto],qPPTO[Línea],"Gastos de administración",qPPTO[Mes],"Mar")-SUMIFS(qPPTO[Presupuesto],qPPTO[Línea],"Gastos de ventas",qPPTO[Mes],"Mar"))/(SUMIFS(qPPTO[Real],qPPTO[Línea],"Ingresos operacionales",qPPTO[Mes],"Mar")-SUMIFS(qPPTO[Real],qPPTO[Línea],"Costo de ventas",qPPTO[Mes],"Mar")-SUMIFS(qPPTO[Real],qPPTO[Línea],"Gastos de administración",qPPTO[Mes],"Mar")-SUMIFS(qPPTO[Real],qPPTO[Línea],"Gastos de ventas",qPPTO[Mes],"Mar"))-1,"") -> 0.59219319 | K33: =IFERROR((SUMIFS(qPPTO[Presupuesto],qPPTO[Línea],"Ingresos operacionales",qPPTO[Mes],"Abr")-SUMIFS(qPPTO[Presupuesto],qPPTO[Línea],"Costo de ventas",qPPTO[Mes],"Abr")-SUMIFS(qPPTO[Presupuesto],qPPTO[Línea],"Gastos de administración",qPPTO[Mes],"Abr")-SUMIFS(qPPTO[Presupuesto],qPPTO[Línea],"Gastos de ventas",qPPTO[Mes],"Abr"))/(SUMIFS(qPPTO[Real],qPPTO[Línea],"Ingresos operacionales",qPPTO[Mes],"Abr")-SUMIFS(qPPTO[Real],qPPTO[Línea],"Costo de ventas",qPPTO[Mes],"Abr")-SUMIFS(qPPTO[Real],qPPTO[Línea],"Gastos de administración",qPPTO[Mes],"Abr")-SUMIFS(qPPTO[Real],qPPTO[Línea],"Gastos de ventas",qPPTO[Mes],"Abr"))-1,"") -> 0.59219319 | L33: =IFERROR((SUMIFS(qPPTO[Presupuesto],qPPTO[Línea],"Ingresos operacionales",qPPTO[Mes],"May")-SUMIFS(qPPTO[Presupuesto],qPPTO[Línea],"Costo de ventas",qPPTO[Mes],"May")-SUMIFS(qPPTO[Presupuesto],qPPTO[Línea],"Gastos de administración",qPPTO[Mes],"May")-SUMIFS(qPPTO[Presupuesto],qPPTO[Línea],"Gastos de ventas",qPPTO[Mes],"May"))/(SUMIFS(qPPTO[Real],qPPTO[Línea],"Ingresos operacionales",qPPTO[Mes],"May")-SUMIFS(qPPTO[Real],qPPTO[Línea],"Costo de ventas",qPPTO[Mes],"May")-SUMIFS(qPPTO[Real],qPPTO[Línea],"Gastos de administración",qPPTO[Mes],"May")-SUMIFS(qPPTO[Real],qPPTO[Línea],"Gastos de ventas",qPPTO[Mes],"May"))-1,"") -> 0.51474737 | M33: =IFERROR((SUMIFS(qPPTO[Presupuesto],qPPTO[Línea],"Ingresos operacionales",qPPTO[Mes],"Jun")-SUMIFS(qPPTO[Presupuesto],qPPTO[Línea],"Costo de ventas",qPPTO[Mes],"Jun")-SUMIFS(qPPTO[Presupuesto],qPPTO[Línea],"Gastos de administración",qPPTO[Mes],"Jun")-SUMIFS(qPPTO[Presupuesto],qPPTO[Línea],"Gastos de ventas",qPPTO[Mes],"Jun"))/(SUMIFS(qPPTO[Real],qPPTO[Línea],"Ingresos operacionales",qPPTO[Mes],"Jun")-SUMIFS(qPPTO[Real],qPPTO[Línea],"Costo de ventas",qPPTO[Mes],"Jun")-SUMIFS(qPPTO[Real],qPPTO[Línea],"Gastos de administración",qPPTO[Mes],"Jun")-SUMIFS(qPPTO[Real],qPPTO[Línea],"Gastos de ventas",qPPTO[Mes],"Jun"))-1,"") -> 0.51474737 | N33: =IFERROR((SUMIFS(qPPTO[Presupuesto],qPPTO[Línea],"Ingresos operacionales",qPPTO[Mes],"Jul")-SUMIFS(qPPTO[Presupuesto],qPPTO[Línea],"Costo de ventas",qPPTO[Mes],"Jul")-SUMIFS(qPPTO[Presupuesto],qPPTO[Línea],"Gastos de administración",qPPTO[Mes],"Jul")-SUMIFS(qPPTO[Presupuesto],qPPTO[Línea],"Gastos de ventas",qPPTO[Mes],"Jul"))/(SUMIFS(qPPTO[Real],qPPTO[Línea],"Ingresos operacionales",qPPTO[Mes],"Jul")-SUMIFS(qPPTO[Real],qPPTO[Línea],"Costo de ventas",qPPTO[Mes],"Jul")-SUMIFS(qPPTO[Real],qPPTO[Línea],"Gastos de administración",qPPTO[Mes],"Jul")-SUMIFS(qPPTO[Real],qPPTO[Línea],"Gastos de ventas",qPPTO[Mes],"Jul"))-1,"") -> 0.51474737 | O33: =IFERROR((SUMIFS(qPPTO[Presupuesto],qPPTO[Línea],"Ingresos operacionales",qPPTO[Mes],"Ago")-SUMIFS(qPPTO[Presupuesto],qPPTO[Línea],"Costo de ventas",qPPTO[Mes],"Ago")-SUMIFS(qPPTO[Presupuesto],qPPTO[Línea],"Gastos de administración",qPPTO[Mes],"Ago")-SUMIFS(qPPTO[Presupuesto],qPPTO[Línea],"Gastos de ventas",qPPTO[Mes],"Ago"))/(SUMIFS(qPPTO[Real],qPPTO[Línea],"Ingresos operacionales",qPPTO[Mes],"Ago")-SUMIFS(qPPTO[Real],qPPTO[Línea],"Costo de ventas",qPPTO[Mes],"Ago")-SUMIFS(qPPTO[Real],qPPTO[Línea],"Gastos de administración",qPPTO[Mes],"Ago")-SUMIFS(qPPTO[Real],qPPTO[Línea],"Gastos de ventas",qPPTO[Mes],"Ago"))-1,"") -> 0.46248889 | P33: =IFERROR((SUMIFS(qPPTO[Presupuesto],qPPTO[Línea],"Ingresos operacionales",qPPTO[Mes],"Sep")-SUMIFS(qPPTO[Presupuesto],qPPTO[Línea],"Costo de ventas",qPPTO[Mes],"Sep")-SUMIFS(qPPTO[Presupuesto],qPPTO[Línea],"Gastos de administración",qPPTO[Mes],"Sep")-SUMIFS(qPPTO[Presupuesto],qPPTO[Línea],"Gastos de ventas",qPPTO[Mes],"Sep"))/(SUMIFS(qPPTO[Real],qPPTO[Línea],"Ingresos operacionales",qPPTO[Mes],"Sep")-SUMIFS(qPPTO[Real],qPPTO[Línea],"Costo de ventas",qPPTO[Mes],"Sep")-SUMIFS(qPPTO[Real],qPPTO[Línea],"Gastos de administración",qPPTO[Mes],"Sep")-SUMIFS(qPPTO[Real],qPPTO[Línea],"Gastos de ventas",qPPTO[Mes],"Sep"))-1,"") -> 0.51474737 | Q33: =IFERROR((SUMIFS(qPPTO[Presupuesto],qPPTO[Línea],"Ingresos operacionales",qPPTO[Mes],"Oct")-SUMIFS(qPPTO[Presupuesto],qPPTO[Línea],"Costo de ventas",qPPTO[Mes],"Oct")-SUMIFS(qPPTO[Presupuesto],qPPTO[Línea],"Gastos de administración",qPPTO[Mes],"Oct")-SUMIFS(qPPTO[Presupuesto],qPPTO[Línea],"Gastos de ventas",qPPTO[Mes],"Oct"))/(SUMIFS(qPPTO[Real],qPPTO[Línea],"Ingresos operacionales",qPPTO[Mes],"Oct")-SUMIFS(qPPTO[Real],qPPTO[Línea],"Costo de ventas",qPPTO[Mes],"Oct")-SUMIFS(qPPTO[Real],qPPTO[Línea],"Gastos de administración",qPPTO[Mes],"Oct")-SUMIFS(qPPTO[Real],qPPTO[Línea],"Gastos de ventas",qPPTO[Mes],"Oct"))-1,"") -> 0.46248889 | R33: =IFERROR((SUMIFS(qPPTO[Presupuesto],qPPTO[Línea],"Ingresos operacionales",qPPTO[Mes],"Nov")-SUMIFS(qPPTO[Presupuesto],qPPTO[Línea],"Costo de ventas",qPPTO[Mes],"Nov")-SUMIFS(qPPTO[Presupuesto],qPPTO[Línea],"Gastos de administración",qPPTO[Mes],"Nov")-SUMIFS(qPPTO[Presupuesto],qPPTO[Línea],"Gastos de ventas",qPPTO[Mes],"Nov"))/(SUMIFS(qPPTO[Real],qPPTO[Línea],"Ingresos operacionales",qPPTO[Mes],"Nov")-SUMIFS(qPPTO[Real],qPPTO[Línea],"Costo de ventas",qPPTO[Mes],"Nov")-SUMIFS(qPPTO[Real],qPPTO[Línea],"Gastos de administración",qPPTO[Mes],"Nov")-SUMIFS(qPPTO[Real],qPPTO[Línea],"Gastos de ventas",qPPTO[Mes],"Nov"))-1,"") -> 0.39640656 | S33: =IFERROR((SUMIFS(qPPTO[Presupuesto],qPPTO[Línea],"Ingresos operacionales",qPPTO[Mes],"Dic")-SUMIFS(qPPTO[Presupuesto],qPPTO[Línea],"Costo de ventas",qPPTO[Mes],"Dic")-SUMIFS(qPPTO[Presupuesto],qPPTO[Línea],"Gastos de administración",qPPTO[Mes],"Dic")-SUMIFS(qPPTO[Presupuesto],qPPTO[Línea],"Gastos de ventas",qPPTO[Mes],"Dic"))/(SUMIFS(qPPTO[Real],qPPTO[Línea],"Ingresos operacionales",qPPTO[Mes],"Dic")-SUMIFS(qPPTO[Real],qPPTO[Línea],"Costo de ventas",qPPTO[Mes],"Dic")-SUMIFS(qPPTO[Real],qPPTO[Línea],"Gastos de administración",qPPTO[Mes],"Dic")-SUMIFS(qPPTO[Real],qPPTO[Línea],"Gastos de ventas",qPPTO[Mes],"Dic"))-1,"") -> 0.3739698
B34: EBITDA | C34: =C13 -> 1160 | D34: =D13 -> 1664.611 | E34: =F13 -> 0.43500948 | H34: =IFERROR((SUMIFS(qPPTO[Presupuesto],qPPTO[Línea],"Ingresos operacionales",qPPTO[Mes],"Ene")-SUMIFS(qPPTO[Presupuesto],qPPTO[Línea],"Costo de ventas",qPPTO[Mes],"Ene")-SUMIFS(qPPTO[Presupuesto],qPPTO[Línea],"Gastos de administración",qPPTO[Mes],"Ene")-SUMIFS(qPPTO[Presupuesto],qPPTO[Línea],"Gastos de ventas",qPPTO[Mes],"Ene")+SUMIFS(qPPTO[Presupuesto],qPPTO[Cuenta],"Depreciación y amortización",qPPTO[Mes],"Ene"))/(SUMIFS(qPPTO[Real],qPPTO[Línea],"Ingresos operacionales",qPPTO[Mes],"Ene")-SUMIFS(qPPTO[Real],qPPTO[Línea],"Costo de ventas",qPPTO[Mes],"Ene")-SUMIFS(qPPTO[Real],qPPTO[Línea],"Gastos de administración",qPPTO[Mes],"Ene")-SUMIFS(qPPTO[Real],qPPTO[Línea],"Gastos de ventas",qPPTO[Mes],"Ene")+SUMIFS(qPPTO[Real],qPPTO[Cuenta],"Depreciación y amortización",qPPTO[Mes],"Ene"))-1,"") -> 0.87525259 | I34: =IFERROR((SUMIFS(qPPTO[Presupuesto],qPPTO[Línea],"Ingresos operacionales",qPPTO[Mes],"Feb")-SUMIFS(qPPTO[Presupuesto],qPPTO[Línea],"Costo de ventas",qPPTO[Mes],"Feb")-SUMIFS(qPPTO[Presupuesto],qPPTO[Línea],"Gastos de administración",qPPTO[Mes],"Feb")-SUMIFS(qPPTO[Presupuesto],qPPTO[Línea],"Gastos de ventas",qPPTO[Mes],"Feb")+SUMIFS(qPPTO[Presupuesto],qPPTO[Cuenta],"Depreciación y amortización",qPPTO[Mes],"Feb"))/(SUMIFS(qPPTO[Real],qPPTO[Línea],"Ingresos operacionales",qPPTO[Mes],"Feb")-SUMIFS(qPPTO[Real],qPPTO[Línea],"Costo de ventas",qPPTO[Mes],"Feb")-SUMIFS(qPPTO[Real],qPPTO[Línea],"Gastos de administración",qPPTO[Mes],"Feb")-SUMIFS(qPPTO[Real],qPPTO[Línea],"Gastos de ventas",qPPTO[Mes],"Feb")+SUMIFS(qPPTO[Real],qPPTO[Cuenta],"Depreciación y amortización",qPPTO[Mes],"Feb"))-1,"") -> 0.66209683 | J34: =IFERROR((SUMIFS(qPPTO[Presupuesto],qPPTO[Línea],"Ingresos operacionales",qPPTO[Mes],"Mar")-SUMIFS(qPPTO[Presupuesto],qPPTO[Línea],"Costo de ventas",qPPTO[Mes],"Mar")-SUMIFS(qPPTO[Presupuesto],qPPTO[Línea],"Gastos de administración",qPPTO[Mes],"Mar")-SUMIFS(qPPTO[Presupuesto],qPPTO[Línea],"Gastos de ventas",qPPTO[Mes],"Mar")+SUMIFS(qPPTO[Presupuesto],qPPTO[Cuenta],"Depreciación y amortización",qPPTO[Mes],"Mar"))/(SUMIFS(qPPTO[Real],qPPTO[Línea],"Ingresos operacionales",qPPTO[Mes],"Mar")-SUMIFS(qPPTO[Real],qPPTO[Línea],"Costo de ventas",qPPTO[Mes],"Mar")-SUMIFS(qPPTO[Real],qPPTO[Línea],"Gastos de administración",qPPTO[Mes],"Mar")-SUMIFS(qPPTO[Real],qPPTO[Línea],"Gastos de ventas",qPPTO[Mes],"Mar")+SUMIFS(qPPTO[Real],qPPTO[Cuenta],"Depreciación y amortización",qPPTO[Mes],"Mar"))-1,"") -> 0.48266301 | K34: =IFERROR((SUMIFS(qPPTO[Presupuesto],qPPTO[Línea],"Ingresos operacionales",qPPTO[Mes],"Abr")-SUMIFS(qPPTO[Presupuesto],qPPTO[Línea],"Costo de ventas",qPPTO[Mes],"Abr")-SUMIFS(qPPTO[Presupuesto],qPPTO[Línea],"Gastos de administración",qPPTO[Mes],"Abr")-SUMIFS(qPPTO[Presupuesto],qPPTO[Línea],"Gastos de ventas",qPPTO[Mes],"Abr")+SUMIFS(qPPTO[Presupuesto],qPPTO[Cuenta],"Depreciación y amortización",qPPTO[Mes],"Abr"))/(SUMIFS(qPPTO[Real],qPPTO[Línea],"Ingresos operacionales",qPPTO[Mes],"Abr")-SUMIFS(qPPTO[Real],qPPTO[Línea],"Costo de ventas",qPPTO[Mes],"Abr")-SUMIFS(qPPTO[Real],qPPTO[Línea],"Gastos de administración",qPPTO[Mes],"Abr")-SUMIFS(qPPTO[Real],qPPTO[Línea],"Gastos de ventas",qPPTO[Mes],"Abr")+SUMIFS(qPPTO[Real],qPPTO[Cuenta],"Depreciación y amortización",qPPTO[Mes],"Abr"))-1,"") -> 0.48266301 | L34: =IFERROR((SUMIFS(qPPTO[Presupuesto],qPPTO[Línea],"Ingresos operacionales",qPPTO[Mes],"May")-SUMIFS(qPPTO[Presupuesto],qPPTO[Línea],"Costo de ventas",qPPTO[Mes],"May")-SUMIFS(qPPTO[Presupuesto],qPPTO[Línea],"Gastos de administración",qPPTO[Mes],"May")-SUMIFS(qPPTO[Presupuesto],qPPTO[Línea],"Gastos de ventas",qPPTO[Mes],"May")+SUMIFS(qPPTO[Presupuesto],qPPTO[Cuenta],"Depreciación y amortización",qPPTO[Mes],"May"))/(SUMIFS(qPPTO[Real],qPPTO[Línea],"Ingresos operacionales",qPPTO[Mes],"May")-SUMIFS(qPPTO[Real],qPPTO[Línea],"Costo de ventas",qPPTO[Mes],"May")-SUMIFS(qPPTO[Real],qPPTO[Línea],"Gastos de administración",qPPTO[Mes],"May")-SUMIFS(qPPTO[Real],qPPTO[Línea],"Gastos de ventas",qPPTO[Mes],"May")+SUMIFS(qPPTO[Real],qPPTO[Cuenta],"Depreciación y amortización",qPPTO[Mes],"May"))-1,"") -> 0.43490031 | M34: =IFERROR((SUMIFS(qPPTO[Presupuesto],qPPTO[Línea],"Ingresos operacionales",qPPTO[Mes],"Jun")-SUMIFS(qPPTO[Presupuesto],qPPTO[Línea],"Costo de ventas",qPPTO[Mes],"Jun")-SUMIFS(qPPTO[Presupuesto],qPPTO[Línea],"Gastos de administración",qPPTO[Mes],"Jun")-SUMIFS(qPPTO[Presupuesto],qPPTO[Línea],"Gastos de ventas",qPPTO[Mes],"Jun")+SUMIFS(qPPTO[Presupuesto],qPPTO[Cuenta],"Depreciación y amortización",qPPTO[Mes],"Jun"))/(SUMIFS(qPPTO[Real],qPPTO[Línea],"Ingresos operacionales",qPPTO[Mes],"Jun")-SUMIFS(qPPTO[Real],qPPTO[Línea],"Costo de ventas",qPPTO[Mes],"Jun")-SUMIFS(qPPTO[Real],qPPTO[Línea],"Gastos de administración",qPPTO[Mes],"Jun")-SUMIFS(qPPTO[Real],qPPTO[Línea],"Gastos de ventas",qPPTO[Mes],"Jun")+SUMIFS(qPPTO[Real],qPPTO[Cuenta],"Depreciación y amortización",qPPTO[Mes],"Jun"))-1,"") -> 0.43490031 | N34: =IFERROR((SUMIFS(qPPTO[Presupuesto],qPPTO[Línea],"Ingresos operacionales",qPPTO[Mes],"Jul")-SUMIFS(qPPTO[Presupuesto],qPPTO[Línea],"Costo de ventas",qPPTO[Mes],"Jul")-SUMIFS(qPPTO[Presupuesto],qPPTO[Línea],"Gastos de administración",qPPTO[Mes],"Jul")-SUMIFS(qPPTO[Presupuesto],qPPTO[Línea],"Gastos de ventas",qPPTO[Mes],"Jul")+SUMIFS(qPPTO[Presupuesto],qPPTO[Cuenta],"Depreciación y amortización",qPPTO[Mes],"Jul"))/(SUMIFS(qPPTO[Real],qPPTO[Línea],"Ingresos operacionales",qPPTO[Mes],"Jul")-SUMIFS(qPPTO[Real],qPPTO[Línea],"Costo de ventas",qPPTO[Mes],"Jul")-SUMIFS(qPPTO[Real],qPPTO[Línea],"Gastos de administración",qPPTO[Mes],"Jul")-SUMIFS(qPPTO[Real],qPPTO[Línea],"Gastos de ventas",qPPTO[Mes],"Jul")+SUMIFS(qPPTO[Real],qPPTO[Cuenta],"Depreciación y amortización",qPPTO[Mes],"Jul"))-1,"") -> 0.43490031 | O34: =IFERROR((SUMIFS(qPPTO[Presupuesto],qPPTO[Línea],"Ingresos operacionales",qPPTO[Mes],"Ago")-SUMIFS(qPPTO[Presupuesto],qPPTO[Línea],"Costo de ventas",qPPTO[Mes],"Ago")-SUMIFS(qPPTO[Presupuesto],qPPTO[Línea],"Gastos de administración",qPPTO[Mes],"Ago")-SUMIFS(qPPTO[Presupuesto],qPPTO[Línea],"Gastos de ventas",qPPTO[Mes],"Ago")+SUMIFS(qPPTO[Presupuesto],qPPTO[Cuenta],"Depreciación y amortización",qPPTO[Mes],"Ago"))/(SUMIFS(qPPTO[Real],qPPTO[Línea],"Ingresos operacionales",qPPTO[Mes],"Ago")-SUMIFS(qPPTO[Real],qPPTO[Línea],"Costo de ventas",qPPTO[Mes],"Ago")-SUMIFS(qPPTO[Real],qPPTO[Línea],"Gastos de administración",qPPTO[Mes],"Ago")-SUMIFS(qPPTO[Real],qPPTO[Línea],"Gastos de ventas",qPPTO[Mes],"Ago")+SUMIFS(qPPTO[Real],qPPTO[Cuenta],"Depreciación y amortización",qPPTO[Mes],"Ago"))-1,"") -> 0.40065882 | P34: =IFERROR((SUMIFS(qPPTO[Presupuesto],qPPTO[Línea],"Ingresos operacionales",qPPTO[Mes],"Sep")-SUMIFS(qPPTO[Presupuesto],qPPTO[Línea],"Costo de ventas",qPPTO[Mes],"Sep")-SUMIFS(qPPTO[Presupuesto],qPPTO[Línea],"Gastos de administración",qPPTO[Mes],"Sep")-SUMIFS(qPPTO[Presupuesto],qPPTO[Línea],"Gastos de ventas",qPPTO[Mes],"Sep")+SUMIFS(qPPTO[Presupuesto],qPPTO[Cuenta],"Depreciación y amortización",qPPTO[Mes],"Sep"))/(SUMIFS(qPPTO[Real],qPPTO[Línea],"Ingresos operacionales",qPPTO[Mes],"Sep")-SUMIFS(qPPTO[Real],qPPTO[Línea],"Costo de ventas",qPPTO[Mes],"Sep")-SUMIFS(qPPTO[Real],qPPTO[Línea],"Gastos de administración",qPPTO[Mes],"Sep")-SUMIFS(qPPTO[Real],qPPTO[Línea],"Gastos de ventas",qPPTO[Mes],"Sep")+SUMIFS(qPPTO[Real],qPPTO[Cuenta],"Depreciación y amortización",qPPTO[Mes],"Sep"))-1,"") -> 0.43490031 | Q34: =IFERROR((SUMIFS(qPPTO[Presupuesto],qPPTO[Línea],"Ingresos operacionales",qPPTO[Mes],"Oct")-SUMIFS(qPPTO[Presupuesto],qPPTO[Línea],"Costo de ventas",qPPTO[Mes],"Oct")-SUMIFS(qPPTO[Presupuesto],qPPTO[Línea],"Gastos de administración",qPPTO[Mes],"Oct")-SUMIFS(qPPTO[Presupuesto],qPPTO[Línea],"Gastos de ventas",qPPTO[Mes],"Oct")+SUMIFS(qPPTO[Presupuesto],qPPTO[Cuenta],"Depreciación y amortización",qPPTO[Mes],"Oct"))/(SUMIFS(qPPTO[Real],qPPTO[Línea],"Ingresos operacionales",qPPTO[Mes],"Oct")-SUMIFS(qPPTO[Real],qPPTO[Línea],"Costo de ventas",qPPTO[Mes],"Oct")-SUMIFS(qPPTO[Real],qPPTO[Línea],"Gastos de administración",qPPTO[Mes],"Oct")-SUMIFS(qPPTO[Real],qPPTO[Línea],"Gastos de ventas",qPPTO[Mes],"Oct")+SUMIFS(qPPTO[Real],qPPTO[Cuenta],"Depreciación y amortización",qPPTO[Mes],"Oct"))-1,"") -> 0.40065882 | R34: =IFERROR((SUMIFS(qPPTO[Presupuesto],qPPTO[Línea],"Ingresos operacionales",qPPTO[Mes],"Nov")-SUMIFS(qPPTO[Presupuesto],qPPTO[Línea],"Costo de ventas",qPPTO[Mes],"Nov")-SUMIFS(qPPTO[Presupuesto],qPPTO[Línea],"Gastos de administración",qPPTO[Mes],"Nov")-SUMIFS(qPPTO[Presupuesto],qPPTO[Línea],"Gastos de ventas",qPPTO[Mes],"Nov")+SUMIFS(qPPTO[Presupuesto],qPPTO[Cuenta],"Depreciación y amortización",qPPTO[Mes],"Nov"))/(SUMIFS(qPPTO[Real],qPPTO[Línea],"Ingresos operacionales",qPPTO[Mes],"Nov")-SUMIFS(qPPTO[Real],qPPTO[Línea],"Costo de ventas",qPPTO[Mes],"Nov")-SUMIFS(qPPTO[Real],qPPTO[Línea],"Gastos de administración",qPPTO[Mes],"Nov")-SUMIFS(qPPTO[Real],qPPTO[Línea],"Gastos de ventas",qPPTO[Mes],"Nov")+SUMIFS(qPPTO[Real],qPPTO[Cuenta],"Depreciación y amortización",qPPTO[Mes],"Nov"))-1,"") -> 0.35482545 | S34: =IFERROR((SUMIFS(qPPTO[Presupuesto],qPPTO[Línea],"Ingresos operacionales",qPPTO[Mes],"Dic")-SUMIFS(qPPTO[Presupuesto],qPPTO[Línea],"Costo de ventas",qPPTO[Mes],"Dic")-SUMIFS(qPPTO[Presupuesto],qPPTO[Línea],"Gastos de administración",qPPTO[Mes],"Dic")-SUMIFS(qPPTO[Presupuesto],qPPTO[Línea],"Gastos de ventas",qPPTO[Mes],"Dic")+SUMIFS(qPPTO[Presupuesto],qPPTO[Cuenta],"Depreciación y amortización",qPPTO[Mes],"Dic"))/(SUMIFS(qPPTO[Real],qPPTO[Línea],"Ingresos operacionales",qPPTO[Mes],"Dic")-SUMIFS(qPPTO[Real],qPPTO[Línea],"Costo de ventas",qPPTO[Mes],"Dic")-SUMIFS(qPPTO[Real],qPPTO[Línea],"Gastos de administración",qPPTO[Mes],"Dic")-SUMIFS(qPPTO[Real],qPPTO[Línea],"Gastos de ventas",qPPTO[Mes],"Dic")+SUMIFS(qPPTO[Real],qPPTO[Cuenta],"Depreciación y amortización",qPPTO[Mes],"Dic"))-1,"") -> 0.338556
B36: Cómo leerlo: en ingresos la variación es la misma todos los meses porque el presupuesto conserva la estacionalidad del 2026. La utilidad operativa crece mucho más en los meses flojos (enero) que en los fuertes: con una base pequeña, los gastos fijos pesan más y cada peso de venta adicional mueve más la utilidad. Ese es el apalancamiento operativo.

Sheet Seguimiento
B2: SEGUIMIENTO 2027 · REAL CONTRA PRESUPUESTO AL MES DE CORTE
B3: Pega tu real 2027 en la tabla de abajo (celdas lila; hoy trae cifras sintéticas) y elige el mes de corte. Millones de pesos.
B4: ← Volver al tablero
B6: Mes de corte | C6: Ago | D6: ="Acumulado enero a "&LOWER(TEXT(pCorte,"mmmm"))&" de 2027" -> Acumulado enero a agosto de 2027 | K6: =MATCH($C$6,{"Ene","Feb","Mar","Abr","May","Jun","Jul","Ago","Sep","Oct","Nov","Dic"},0) -> 8 | L6: =DATE(2027,pMesCorte+1,0) -> 46630
B8: Resumen al corte | C8: Ppto acum. | D8: Real acum. | E8: Var $ | F8: Var %
B9: Ingresos operacionales | C9: =SUMIFS(tReal27[Ppto acum.],tReal27[Línea],$B9) -> 8649180000 | D9: =SUMIFS(tReal27[Real acum.],tReal27[Línea],$B9) -> 8529643000 | E9: =D9-C9 -> -119537000 | F9: =IFERROR(E9/ABS(C9),"") -> -0.013820617
B10: Costo de ventas | C10: =SUMIFS(tReal27[Ppto acum.],tReal27[Línea],$B10) -> 5403961090 | D10: =SUMIFS(tReal27[Real acum.],tReal27[Línea],$B10) -> 5311892000 | E10: =D10-C10 -> -92069090 | F10: =IFERROR(E10/ABS(C10),"") -> -0.017037334
B11: Utilidad bruta | C11: =C9-C10 -> 3245218910 | D11: =D9-D10 -> 3217751000 | E11: =D11-C11 -> -27467910 | F11: =IFERROR(E11/ABS(C11),"") -> -0.0084641162
B12: Gastos de administración | C12: =SUMIFS(tReal27[Ppto acum.],tReal27[Línea],$B12) -> 860000000 | D12: =SUMIFS(tReal27[Real acum.],tReal27[Línea],$B12) -> 868803000 | E12: =D12-C12 -> 8803000 | F12: =IFERROR(E12/ABS(C12),"") -> 0.010236047
B13: Gastos de ventas | C13: =SUMIFS(tReal27[Ppto acum.],tReal27[Línea],$B13) -> 1542284000 | D13: =SUMIFS(tReal27[Real acum.],tReal27[Línea],$B13) -> 1579533000 | E13: =D13-C13 -> 37249000 | F13: =IFERROR(E13/ABS(C13),"") -> 0.024151842
B14: Utilidad operativa | C14: =C11-C12-C13 -> 842934910 | D14: =D11-D12-D13 -> 769415000 | E14: =D14-C14 -> -73519910 | F14: =IFERROR(E14/ABS(C14),"") -> -0.087218965
B15: Gastos financieros | C15: =SUMIFS(tReal27[Ppto acum.],tReal27[Línea],$B15) -> 189520000 | D15: =SUMIFS(tReal27[Real acum.],tReal27[Línea],$B15) -> 181759000 | E15: =D15-C15 -> -7761000 | F15: =IFERROR(E15/ABS(C15),"") -> -0.040950823
B16: Otros ingresos no operacionales | C16: =SUMIFS(tReal27[Ppto acum.],tReal27[Línea],$B16) -> 41600000 | D16: =SUMIFS(tReal27[Real acum.],tReal27[Línea],$B16) -> 41606000 | E16: =D16-C16 -> 6000 | F16: =IFERROR(E16/ABS(C16),"") -> 0.00014423077
B17: Otros gastos no operacionales | C17: =SUMIFS(tReal27[Ppto acum.],tReal27[Línea],$B17) -> 26400000 | D17: =SUMIFS(tReal27[Real acum.],tReal27[Línea],$B17) -> 26355000 | E17: =D17-C17 -> -45000 | F17: =IFERROR(E17/ABS(C17),"") -> -0.0017045455
B18: Utilidad antes de impuestos | C18: =C14-C15+C16-C17 -> 668614910 | D18: =D14-D15+D16-D17 -> 602907000 | E18: =D18-C18 -> -65707910 | F18: =IFERROR(E18/ABS(C18),"") -> -0.098274671
B19: Impuesto de renta | C19: =MAX(0,C18)*pTasaRenta -> 2.3401522e+08 | D19: =MAX(0,D18)*pTasaRenta -> 211017450 | E19: =D19-C19 -> -22997768 | F19: =IFERROR(E19/ABS(C19),"") -> -0.098274671
B20: Utilidad neta | C20: =C18-C19 -> 4.3459969e+08 | D20: =D18-D19 -> 391889550 | E20: =D20-C20 -> -42710142 | F20: =IFERROR(E20/ABS(C20),"") -> -0.098274671
B21: ="Cumplimiento de utilidad neta: "&TEXT(IFERROR(D20/C20,0),"0%")&" del presupuesto al corte" -> Cumplimiento de utilidad neta: 90% del presupuesto al corte
B28: REAL 2027 · pega aquí tu P&G mes a mes (misma lista de cuentas que la hoja PPTO 2027)
B30: Cuenta | C30: Línea | D30: Tipo | E30: Ene | F30: Feb | G30: Mar | H30: Abr | I30: May | J30: Jun | K30: Jul | L30: Ago | M30: Sep | N30: Oct | O30: Nov | P30: Dic | Q30: Ppto acum. | R30: Real acum. | S30: Var $ | T30: Var %
B31: Venta de mercancía nacional | C31: Ingresos operacionales | D31: Ingreso | E31: 713046000 | F31: 755737000 | G31: 846885000 | H31: 836683000 | I31: 855672000 | J31: 895817000 | K31: 883130000 | L31: 931777000 | M31: 870837000 | N31: 917337000 | O31: 1009300000 | P31: 1049757000 | Q31: =SUM(INDEX('PPTO 2027'!$V$1:$AG$400,MATCH(tReal27[[#This Row],[Cuenta]],'PPTO 2027'!$B$1:$B$400,0),1):INDEX('PPTO 2027'!$V$1:$AG$400,MATCH(tReal27[[#This Row],[Cuenta]],'PPTO 2027'!$B$1:$B$400,0),pMesCorte)) -> 6767040000 | R31: =SUM(INDEX(tReal27[[#This Row],[Ene]:[Dic]],1,1):INDEX(tReal27[[#This Row],[Ene]:[Dic]],1,pMesCorte)) -> 6718747000 | S31: =tReal27[[#This Row],[Real acum.]]-tReal27[[#This Row],[Ppto acum.]] -> -48293000 | T31: =IFERROR(tReal27[[#This Row],[Var $]]/ABS(tReal27[[#This Row],[Ppto acum.]]),"") -> -0.0071365028
B32: Ventas canal digital | C32: Ingresos operacionales | D32: Ingreso | E32: 144875000 | F32: 153285000 | G32: 173145000 | H32: 177842000 | I32: 187633000 | J32: 180180000 | K32: 180550000 | L32: 192505000 | M32: 182139000 | N32: 188789000 | O32: 208436000 | P32: 220883000 | Q32: =SUM(INDEX('PPTO 2027'!$V$1:$AG$400,MATCH(tReal27[[#This Row],[Cuenta]],'PPTO 2027'!$B$1:$B$400,0),1):INDEX('PPTO 2027'!$V$1:$AG$400,MATCH(tReal27[[#This Row],[Cuenta]],'PPTO 2027'!$B$1:$B$400,0),pMesCorte)) -> 1459200000 | R32: =SUM(INDEX(tReal27[[#This Row],[Ene]:[Dic]],1,1):INDEX(tReal27[[#This Row],[Ene]:[Dic]],1,pMesCorte)) -> 1390015000 | S32: =tReal27[[#This Row],[Real acum.]]-tReal27[[#This Row],[Ppto acum.]] -> -69185000 | T32: =IFERROR(tReal27[[#This Row],[Var $]]/ABS(tReal27[[#This Row],[Ppto acum.]]),"") -> -0.047412966
B33: Servicios de instalación | C33: Ingresos operacionales | D33: Ingreso | E33: 44137000 | F33: 47424000 | G33: 53065000 | H33: 52126000 | I33: 55589000 | J33: 54926000 | K33: 56436000 | L33: 57178000 | M33: 56871000 | N33: 57258000 | O33: 65007000 | P33: 67211000 | Q33: =SUM(INDEX('PPTO 2027'!$V$1:$AG$400,MATCH(tReal27[[#This Row],[Cuenta]],'PPTO 2027'!$B$1:$B$400,0),1):INDEX('PPTO 2027'!$V$1:$AG$400,MATCH(tReal27[[#This Row],[Cuenta]],'PPTO 2027'!$B$1:$B$400,0),pMesCorte)) -> 422940000 | R33: =SUM(INDEX(tReal27[[#This Row],[Ene]:[Dic]],1,1):INDEX(tReal27[[#This Row],[Ene]:[Dic]],1,pMesCorte)) -> 420881000 | S33: =tReal27[[#This Row],[Real acum.]]-tReal27[[#This Row],[Ppto acum.]] -> -2059000 | T33: =IFERROR(tReal27[[#This Row],[Var $]]/ABS(tReal27[[#This Row],[Ppto acum.]]),"") -> -0.0048683028
B34: Costo de mercancía vendida | C34: Costo de ventas | D34: Costo | E34: 505292000 | F34: 542318000 | G34: 616983000 | H34: 607213000 | I34: 624229000 | J34: 632414000 | K34: 638716000 | L34: 675199000 | M34: 643661000 | N34: 657894000 | O34: 734942000 | P34: 753382000 | Q34: =SUM(INDEX('PPTO 2027'!$V$1:$AG$400,MATCH(tReal27[[#This Row],[Cuenta]],'PPTO 2027'!$B$1:$B$400,0),1):INDEX('PPTO 2027'!$V$1:$AG$400,MATCH(tReal27[[#This Row],[Cuenta]],'PPTO 2027'!$B$1:$B$400,0),pMesCorte)) -> 4957759390 | R34: =SUM(INDEX(tReal27[[#This Row],[Ene]:[Dic]],1,1):INDEX(tReal27[[#This Row],[Ene]:[Dic]],1,pMesCorte)) -> 4842364000 | S34: =tReal27[[#This Row],[Real acum.]]-tReal27[[#This Row],[Ppto acum.]] -> -115395390 | T34: =IFERROR(tReal27[[#This Row],[Var $]]/ABS(tReal27[[#This Row],[Ppto acum.]]),"") -> -0.023275714
B35: Fletes de compra | C35: Costo de ventas | D35: Costo | E35: 38643000 | F35: 40855000 | G35: 45998000 | H35: 45589000 | I35: 47318000 | J35: 47281000 | K35: 47999000 | L35: 50347000 | M35: 47220000 | N35: 49564000 | O35: 54976000 | P35: 57551000 | Q35: =SUM(INDEX('PPTO 2027'!$V$1:$AG$400,MATCH(tReal27[[#This Row],[Cuenta]],'PPTO 2027'!$B$1:$B$400,0),1):INDEX('PPTO 2027'!$V$1:$AG$400,MATCH(tReal27[[#This Row],[Cuenta]],'PPTO 2027'!$B$1:$B$400,0),pMesCorte)) -> 339963200 | R35: =SUM(INDEX(tReal27[[#This Row],[Ene]:[Dic]],1,1):INDEX(tReal27[[#This Row],[Ene]:[Dic]],1,pMesCorte)) -> 364030000 | S35: =tReal27[[#This Row],[Real acum.]]-tReal27[[#This Row],[Ppto acum.]] -> 24066800 | T35: =IFERROR(tReal27[[#This Row],[Var $]]/ABS(tReal27[[#This Row],[Ppto acum.]]),"") -> 0.070792368
B36: Mermas y averías | C36: Costo de ventas | D36: Costo | E36: 11415000 | F36: 11898000 | G36: 13149000 | H36: 13128000 | I36: 13589000 | J36: 13975000 | K36: 13599000 | L36: 14745000 | M36: 13881000 | N36: 14746000 | O36: 15926000 | P36: 16801000 | Q36: =SUM(INDEX('PPTO 2027'!$V$1:$AG$400,MATCH(tReal27[[#This Row],[Cuenta]],'PPTO 2027'!$B$1:$B$400,0),1):INDEX('PPTO 2027'!$V$1:$AG$400,MATCH(tReal27[[#This Row],[Cuenta]],'PPTO 2027'!$B$1:$B$400,0),pMesCorte)) -> 106238500 | R36: =SUM(INDEX(tReal27[[#This Row],[Ene]:[Dic]],1,1):INDEX(tReal27[[#This Row],[Ene]:[Dic]],1,pMesCorte)) -> 105498000 | S36: =tReal27[[#This Row],[Real acum.]]-tReal27[[#This Row],[Ppto acum.]] -> -740500 | T36: =IFERROR(tReal27[[#This Row],[Var $]]/ABS(tReal27[[#This Row],[Ppto acum.]]),"") -> -0.0069701662
B37: Nómina comercial | C37: Gastos de ventas | D37: Gasto | E37: 47396000 | F37: 46502000 | G37: 46270000 | H37: 47321000 | I37: 45991000 | J37: 46121000 | K37: 45673000 | L37: 47112000 | M37: 46477000 | N37: 47539000 | O37: 46051000 | P37: 47445000 | Q37: =SUM(INDEX('PPTO 2027'!$V$1:$AG$400,MATCH(tReal27[[#This Row],[Cuenta]],'PPTO 2027'!$B$1:$B$400,0),1):INDEX('PPTO 2027'!$V$1:$AG$400,MATCH(tReal27[[#This Row],[Cuenta]],'PPTO 2027'!$B$1:$B$400,0),pMesCorte)) -> 370648000 | R37: =SUM(INDEX(tReal27[[#This Row],[Ene]:[Dic]],1,1):INDEX(tReal27[[#This Row],[Ene]:[Dic]],1,pMesCorte)) -> 372386000 | S37: =tReal27[[#This Row],[Real acum.]]-tReal27[[#This Row],[Ppto acum.]] -> 1738000 | T37: =IFERROR(tReal27[[#This Row],[Var $]]/ABS(tReal27[[#This Row],[Ppto acum.]]),"") -> 0.0046890851
B38: Comisiones de ventas | C38: Gastos de ventas | D38: Gasto | E38: 28100000 | F38: 29683000 | G38: 35003000 | H38: 33378000 | I38: 35263000 | J38: 34880000 | K38: 35746000 | L38: 37036000 | M38: 34932000 | N38: 36921000 | O38: 40042000 | P38: 41480000 | Q38: =SUM(INDEX('PPTO 2027'!$V$1:$AG$400,MATCH(tReal27[[#This Row],[Cuenta]],'PPTO 2027'!$B$1:$B$400,0),1):INDEX('PPTO 2027'!$V$1:$AG$400,MATCH(tReal27[[#This Row],[Cuenta]],'PPTO 2027'!$B$1:$B$400,0),pMesCorte)) -> 253764000 | R38: =SUM(INDEX(tReal27[[#This Row],[Ene]:[Dic]],1,1):INDEX(tReal27[[#This Row],[Ene]:[Dic]],1,pMesCorte)) -> 269089000 | S38: =tReal27[[#This Row],[Real acum.]]-tReal27[[#This Row],[Ppto acum.]] -> 15325000 | T38: =IFERROR(tReal27[[#This Row],[Var $]]/ABS(tReal27[[#This Row],[Ppto acum.]]),"") -> 0.060390757
B39: Publicidad y mercadeo | C39: Gastos de ventas | D39: Gasto | E39: 29722000 | F39: 29291000 | G39: 29305000 | H39: 29112000 | I39: 29892000 | J39: 29566000 | K39: 29512000 | L39: 29596000 | M39: 29407000 | N39: 30161000 | O39: 29506000 | P39: 29543000 | Q39: =SUM(INDEX('PPTO 2027'!$V$1:$AG$400,MATCH(tReal27[[#This Row],[Cuenta]],'PPTO 2027'!$B$1:$B$400,0),1):INDEX('PPTO 2027'!$V$1:$AG$400,MATCH(tReal27[[#This Row],[Cuenta]],'PPTO 2027'!$B$1:$B$400,0),pMesCorte)) -> 2.1632e+08 | R39: =SUM(INDEX(tReal27[[#This Row],[Ene]:[Dic]],1,1):INDEX(tReal27[[#This Row],[Ene]:[Dic]],1,pMesCorte)) -> 235996000 | S39: =tReal27[[#This Row],[Real acum.]]-tReal27[[#This Row],[Ppto acum.]] -> 19676000 | T39: =IFERROR(tReal27[[#This Row],[Var $]]/ABS(tReal27[[#This Row],[Ppto acum.]]),"") -> 0.09095784
B40: Transporte y distribución | C40: Gastos de ventas | D40: Gasto | E40: 21133000 | F40: 22730000 | G40: 25324000 | H40: 25080000 | I40: 26498000 | J40: 26669000 | K40: 25842000 | L40: 27921000 | M40: 26759000 | N40: 28096000 | O40: 30186000 | P40: 31595000 | Q40: =SUM(INDEX('PPTO 2027'!$V$1:$AG$400,MATCH(tReal27[[#This Row],[Cuenta]],'PPTO 2027'!$B$1:$B$400,0),1):INDEX('PPTO 2027'!$V$1:$AG$400,MATCH(tReal27[[#This Row],[Cuenta]],'PPTO 2027'!$B$1:$B$400,0),pMesCorte)) -> 201400000 | R40: =SUM(INDEX(tReal27[[#This Row],[Ene]:[Dic]],1,1):INDEX(tReal27[[#This Row],[Ene]:[Dic]],1,pMesCorte)) -> 201197000 | S40: =tReal27[[#This Row],[Real acum.]]-tReal27[[#This Row],[Ppto acum.]] -> -203000 | T40: =IFERROR(tReal27[[#This Row],[Var $]]/ABS(tReal27[[#This Row],[Ppto acum.]]),"") -> -0.0010079444
B41: Nómina de bodega | C41: Gastos de ventas | D41: Gasto | E41: 34354000 | F41: 33469000 | G41: 34070000 | H41: 34069000 | I41: 34295000 | J41: 33829000 | K41: 34227000 | L41: 34060000 | M41: 33425000 | N41: 34349000 | O41: 33754000 | P41: 33261000 | Q41: =SUM(INDEX('PPTO 2027'!$V$1:$AG$400,MATCH(tReal27[[#This Row],[Cuenta]],'PPTO 2027'!$B$1:$B$400,0),1):INDEX('PPTO 2027'!$V$1:$AG$400,MATCH(tReal27[[#This Row],[Cuenta]],'PPTO 2027'!$B$1:$B$400,0),pMesCorte)) -> 271352000 | R41: =SUM(INDEX(tReal27[[#This Row],[Ene]:[Dic]],1,1):INDEX(tReal27[[#This Row],[Ene]:[Dic]],1,pMesCorte)) -> 272373000 | S41: =tReal27[[#This Row],[Real acum.]]-tReal27[[#This Row],[Ppto acum.]] -> 1021000 | T41: =IFERROR(tReal27[[#This Row],[Var $]]/ABS(tReal27[[#This Row],[Ppto acum.]]),"") -> 0.0037626404
B42: Arrendamiento de bodega | C42: Gastos de ventas | D42: Gasto | E42: 20459000 | F42: 20497000 | G42: 21405000 | H42: 20692000 | I42: 20346000 | J42: 21225000 | K42: 20739000 | L42: 20612000 | M42: 20155000 | N42: 20484000 | O42: 20592000 | P42: 20796000 | Q42: =SUM(INDEX('PPTO 2027'!$V$1:$AG$400,MATCH(tReal27[[#This Row],[Cuenta]],'PPTO 2027'!$B$1:$B$400,0),1):INDEX('PPTO 2027'!$V$1:$AG$400,MATCH(tReal27[[#This Row],[Cuenta]],'PPTO 2027'!$B$1:$B$400,0),pMesCorte)) -> 166400000 | R42: =SUM(INDEX(tReal27[[#This Row],[Ene]:[Dic]],1,1):INDEX(tReal27[[#This Row],[Ene]:[Dic]],1,pMesCorte)) -> 165975000 | S42: =tReal27[[#This Row],[Real acum.]]-tReal27[[#This Row],[Ppto acum.]] -> -425000 | T42: =IFERROR(tReal27[[#This Row],[Var $]]/ABS(tReal27[[#This Row],[Ppto acum.]]),"") -> -0.0025540865
... B53: Gastos extraordinarios | C53: Otros gastos no operacionales | D53: Gasto | E53: 3254000 | F53: 3350000 | G53: 3371000 | H53: 3246000 | I53: 3247000 | J53: 3300000 | K53: 3308000 | L53: 3279000 | M53: 3352000 | N53: 3337000 | O53: 3317000 | P53: 3737000 | Q53: =SUM(INDEX('PPTO 2027'!$V$1:$AG$400,MATCH(tReal27[[#This Row],[Cuenta]],'PPTO 2027'!$B$1:$B$400,0),1):INDEX('PPTO 2027'!$V$1:$AG$400,MATCH(tReal27[[#This Row],[Cuenta]],'PPTO 2027'!$B$1:$B$400,0),pMesCorte)) -> 26400000 | R53: =SUM(INDEX(tReal27[[#This Row],[Ene]:[Dic]],1,1):INDEX(tReal27[[#This Row],[Ene]:[Dic]],1,pMesCorte)) -> 26355000 | S53: =tReal27[[#This Row],[Real acum.]]-tReal27[[#This Row],[Ppto acum.]] -> -45000 | T53: =IFERROR(tReal27[[#This Row],[Var $]]/ABS(tReal27[[#This Row],[Ppto acum.]]),"") -> -0.0017045455

Sheet Calculos
A1: CAPA DE CÁLCULO - no editar. Responde a las pestañas del Tablero.
L3: LíneaTab
L4: 1 · Ingresos
B5: Valores | G5: Valores | L5: 2 · Costo de ventas | O5: LíneaTab | BX5: Corte | BY5: =CHOOSE(MONTH(pCorte),"ene","feb","mar","abr","may","jun","jul","ago","sep","oct","nov","dic")&"/"&RIGHT(YEAR(pCorte),2) -> ago/27 | BZ5: Paso | CA5: Cambio | CB5: Nivel | CC5: Base | CD5: Sube | CE5: Baja | CF5: Total | CG5: Etiqueta | CH5: Mes | CI5: Real 2026 | CJ5: Presupuesto 2027 | CL5: MesNum | CM5: Ing R | CN5: Ing P | CO5: Costo R | CP5: Costo P | CQ5: GOp R | CR5: GOp P | CS5: NoOp R | CT5: NoOp P | CW5: Soporte etiqueta | CZ5: Centro de costo | DA5: Real 2026 | DB5: Presupuesto 2027 | DC5: Var % | DH5: Meta de margen bruto | DI5: 0.35
A6: Línea | B6: Total Real | C6: Total Presupuesto | F6: Cuenta | G6: Total Real | H6: Total Presupuesto | I6: Total Var | J6: Total VarAbs | L6: 3 · Gastos operativos | O6: 1 · Ingresos | AK6: Tipo | AL6: Gasto | BX6: Ingresos Real | BY6: =IFERROR(SUMIFS(qPPTO[Real],qPPTO[Línea],"Ingresos operacionales"),0) -> 12000000000 | BZ6: Utilidad 2026 | CA6: =ROUND(BY34/1000000,0) -> 450 | CB6: =CA6 -> 450 | CC6: 0 | CD6: 0 | CE6: 0 | CF6: =CA6 -> 450 | CG6: =FIXED(CA6,0) -> 450 | CH6: Ene | CI6: =ROUND(IF($BY$46="1 · Ingresos",CM6,IF($BY$46="2 · Costo de ventas",CO6,IF($BY$46="3 · Gastos operativos",CQ6,(CM6-CO6-CQ6-CS6)*(1-pTasaRenta))))/1000000,0) -> 800 | CJ6: =ROUND(IF($BY$46="1 · Ingresos",CN6,IF($BY$46="2 · Costo de ventas",CP6,IF($BY$46="3 · Gastos operativos",CR6,(CN6-CP6-CR6-CT6)*(1-pTasaRenta))))/1000000,0) -> 910 | CL6: 1 | CM6: =SUMIFS(qPPTO[Real],qPPTO[MesNum],CL6,qPPTO[Línea],"Ingresos operacionales") -> 800000000 | CN6: =SUMIFS(qPPTO[Presupuesto],qPPTO[MesNum],CL6,qPPTO[Línea],"Ingresos operacionales") -> 910440000 | CO6: =SUMIFS(qPPTO[Real],qPPTO[MesNum],CL6,qPPTO[Línea],"Costo de ventas") -> 508700000 | CP6: =SUMIFS(qPPTO[Presupuesto],qPPTO[MesNum],CL6,qPPTO[Línea],"Costo de ventas") -> 568879210 | CQ6: =SUMIFS(qPPTO[Real],qPPTO[MesNum],CL6,qPPTO[Línea],"Gastos de administración")+SUMIFS(qPPTO[Real],qPPTO[MesNum],CL6,qPPTO[Línea],"Gastos de ventas") -> 271500000 | CR6: =SUMIFS(qPPTO[Presupuesto],qPPTO[MesNum],CL6,qPPTO[Línea],"Gastos de administración")+SUMIFS(qPPTO[Presupuesto],qPPTO[MesNum],CL6,qPPTO[Línea],"Gastos de ventas") -> 291302000 | CS6: =SUMIFS(qPPTO[Real],qPPTO[MesNum],CL6,qPPTO[Línea],"Gastos financieros")-SUMIFS(qPPTO[Real],qPPTO[MesNum],CL6,qPPTO[Línea],"Otros ingresos no operacionales")+SUMIFS(qPPTO[Real],qPPTO[MesNum],CL6,qPPTO[Línea],"Otros gastos no operacionales") -> 24000000 | CT6: =SUMIFS(qPPTO[Presupuesto],qPPTO[MesNum],CL6,qPPTO[Línea],"Gastos financieros")-SUMIFS(qPPTO[Presupuesto],qPPTO[MesNum],CL6,qPPTO[Línea],"Otros ingresos no operacionales")+SUMIFS(qPPTO[Presupuesto],qPPTO[MesNum],CL6,qPPTO[Línea],"Otros gastos no operacionales") -> 21790000 | CW6: 1 | CZ6: =IF(ccN<1,"",INDEX(ccLbl,1)) -> Administración | DA6: =IF(CZ6="","",ROUND(INDEX(ccReal,1)/1000000,0)) -> 1260 | DB6: =IF(CZ6="","",ROUND(INDEX(ccPpto,1)/1000000,0)) -> 1290 | DC6: =IF(CZ6="","",IFERROR(DB6/DA6-1,0)) -> 0.023809524 | DH6: Meta de margen EBITDA | DI6: 0.1
A7: Costo de ventas | B7: 7630000000 | C7: 8532629000 | F7: Venta de mercancía nacional | G7: 9600000000 | H7: 10684800000 | I7: 1084800000 | J7: 1084800000 | L7: 4 · Utilidad neta | BX7: Ingresos Presupuesto | BY7: =IFERROR(SUMIFS(qPPTO[Presupuesto],qPPTO[Línea],"Ingresos operacionales"),0) -> 13656600000 | BZ7: Ingresos | CA7: =ROUND((BY7-BY6)/1000000,0) -> 1657 | CB7: =CB6+CA7 -> 2107 | CC7: =MIN(CB6,CB7) -> 450 | CD7: =MAX(CA7,0) -> 1657 | CE7: =MAX(-CA7,0) -> 0 | CF7: 0 | CG7: =IF(CA7>=0,"+","-")&FIXED(ABS(CA7),0) -> +1.657 | CH7: Feb | CI7: =ROUND(IF($BY$46="1 · Ingresos",CM7,IF($BY$46="2 · Costo de ventas",CO7,IF($BY$46="3 · Gastos operativos",CQ7,(CM7-CO7-CQ7-CS7)*(1-pTasaRenta))))/1000000,0) -> 850 | CJ7: =ROUND(IF($BY$46="1 · Ingresos",CN7,IF($BY$46="2 · Costo de ventas",CP7,IF($BY$46="3 · Gastos operativos",CR7,(CN7-CP7-CR7-CT7)*(1-pTasaRenta))))/1000000,0) -> 967 | CL7: 2 | CM7: =SUMIFS(qPPTO[Real],qPPTO[MesNum],CL7,qPPTO[Línea],"Ingresos operacionales") -> 850000000 | CN7: =SUMIFS(qPPTO[Presupuesto],qPPTO[MesNum],CL7,qPPTO[Línea],"Ingresos operacionales") -> 967342500 | CO7: =SUMIFS(qPPTO[Real],qPPTO[MesNum],CL7,qPPTO[Línea],"Costo de ventas") -> 540400000 | CP7: =SUMIFS(qPPTO[Presupuesto],qPPTO[MesNum],CL7,qPPTO[Línea],"Costo de ventas") -> 604329320 | CQ7: =SUMIFS(qPPTO[Real],qPPTO[MesNum],CL7,qPPTO[Línea],"Gastos de administración")+SUMIFS(qPPTO[Real],qPPTO[MesNum],CL7,qPPTO[Línea],"Gastos de ventas") -> 274200000 | CR7: =SUMIFS(qPPTO[Presupuesto],qPPTO[MesNum],CL7,qPPTO[Línea],"Gastos de administración")+SUMIFS(qPPTO[Presupuesto],qPPTO[MesNum],CL7,qPPTO[Línea],"Gastos de ventas") -> 294243500 | CS7: =SUMIFS(qPPTO[Real],qPPTO[MesNum],CL7,qPPTO[Línea],"Gastos financieros")-SUMIFS(qPPTO[Real],qPPTO[MesNum],CL7,qPPTO[Línea],"Otros ingresos no operacionales")+SUMIFS(qPPTO[Real],qPPTO[MesNum],CL7,qPPTO[Línea],"Otros gastos no operacionales") -> 24000000 | CT7: =SUMIFS(qPPTO[Presupuesto],qPPTO[MesNum],CL7,qPPTO[Línea],"Gastos financieros")-SUMIFS(qPPTO[Presupuesto],qPPTO[MesNum],CL7,qPPTO[Línea],"Otros ingresos no operacionales")+SUMIFS(qPPTO[Presupuesto],qPPTO[MesNum],CL7,qPPTO[Línea],"Otros gastos no operacionales") -> 21790000 | CW7: 1 | CZ7: =IF(ccN<2,"",INDEX(ccLbl,2)) -> Comercial | DA7: =IF(CZ7="","",ROUND(INDEX(ccReal,2)/1000000,0)) -> 1120 | DB7: =IF(CZ7="","",ROUND(INDEX(ccPpto,2)/1000000,0)) -> 1282 | DC7: =IF(CZ7="","",IFERROR(DB7/DA7-1,0)) -> 0.14464286 | DH7: Meta de margen neto | DI7: 0.05
A8: Gastos de administración | B8: 1260000000 | C8: 1290000000 | F8: Costo de mercancía vendida | G8: 7000000000 | H8: 7828100000 | I8: 828100000 | J8: 828100000 | AL8: Valores | BX8: Costo de ventas Real | BY8: =IFERROR(SUMIFS(qPPTO[Real],qPPTO[Línea],"Costo de ventas"),0) -> 7630000000 | BZ8: Costo de ventas | CA8: =-ROUND((BY9-BY8)/1000000,0) -> -903 | CB8: =CB7+CA8 -> 1204 | CC8: =MIN(CB7,CB8) -> 1204 | CD8: =MAX(CA8,0) -> 0 | CE8: =MAX(-CA8,0) -> 903 | CF8: 0 | CG8: =IF(CA8>=0,"+","-")&FIXED(ABS(CA8),0) -> -903 | CH8: Mar | CI8: =ROUND(IF($BY$46="1 · Ingresos",CM8,IF($BY$46="2 · Costo de ventas",CO8,IF($BY$46="3 · Gastos operativos",CQ8,(CM8-CO8-CQ8-CS8)*(1-pTasaRenta))))/1000000,0) -> 950 | CJ8: =ROUND(IF($BY$46="1 · Ingresos",CN8,IF($BY$46="2 · Costo de ventas",CP8,IF($BY$46="3 · Gastos operativos",CR8,(CN8-CP8-CR8-CT8)*(1-pTasaRenta))))/1000000,0) -> 1081 | CL8: 3 | CM8: =SUMIFS(qPPTO[Real],qPPTO[MesNum],CL8,qPPTO[Línea],"Ingresos operacionales") -> 950000000 | CN8: =SUMIFS(qPPTO[Presupuesto],qPPTO[MesNum],CL8,qPPTO[Línea],"Ingresos operacionales") -> 1081147500 | CO8: =SUMIFS(qPPTO[Real],qPPTO[MesNum],CL8,qPPTO[Línea],"Costo de ventas") -> 604100000 | CP8: =SUMIFS(qPPTO[Presupuesto],qPPTO[MesNum],CL8,qPPTO[Línea],"Costo de ventas") -> 675565030 | CQ8: =SUMIFS(qPPTO[Real],qPPTO[MesNum],CL8,qPPTO[Línea],"Gastos de administración")+SUMIFS(qPPTO[Real],qPPTO[MesNum],CL8,qPPTO[Línea],"Gastos de ventas") -> 279800000 | CR8: =SUMIFS(qPPTO[Presupuesto],qPPTO[MesNum],CL8,qPPTO[Línea],"Gastos de administración")+SUMIFS(qPPTO[Presupuesto],qPPTO[MesNum],CL8,qPPTO[Línea],"Gastos de ventas") -> 300338500 | CS8: =SUMIFS(qPPTO[Real],qPPTO[MesNum],CL8,qPPTO[Línea],"Gastos financieros")-SUMIFS(qPPTO[Real],qPPTO[MesNum],CL8,qPPTO[Línea],"Otros ingresos no operacionales")+SUMIFS(qPPTO[Real],qPPTO[MesNum],CL8,qPPTO[Línea],"Otros gastos no operacionales") -> 24000000 | CT8: =SUMIFS(qPPTO[Presupuesto],qPPTO[MesNum],CL8,qPPTO[Línea],"Gastos financieros")-SUMIFS(qPPTO[Presupuesto],qPPTO[MesNum],CL8,qPPTO[Línea],"Otros ingresos no operacionales")+SUMIFS(qPPTO[Presupuesto],qPPTO[MesNum],CL8,qPPTO[Línea],"Otros gastos no operacionales") -> 21790000 | CW8: 1 | CZ8: =IF(ccN<3,"",INDEX(ccLbl,3)) -> Corporativo | DA8: =IF(CZ8="","",ROUND(INDEX(ccReal,3)/1000000,0)) -> 348 | DB8: =IF(CZ8="","",ROUND(INDEX(ccPpto,3)/1000000,0)) -> 324 | DC8: =IF(CZ8="","",IFERROR(DB8/DA8-1,0)) -> -0.068965517 | DH8: Meta de gastos operativos sobre ingresos | DI8: 0.28
A9: Gastos de ventas | B9: 2130000000 | C9: 2349360000 | F9: Ventas canal digital | G9: 1800000000 | H9: 2304000000 | I9: 504000000 | J9: 504000000 | AK9: Centro de costo | AL9: Total Real | AM9: Total Presupuesto | BX9: Costo de ventas Presupuesto | BY9: =IFERROR(SUMIFS(qPPTO[Presupuesto],qPPTO[Línea],"Costo de ventas"),0) -> 8532629000 | BZ9: Gastos operativos | CA9: =-ROUND((BY17-BY16)/1000000,0) -> -249 | CB9: =CB8+CA9 -> 955 | CC9: =MIN(CB8,CB9) -> 955 | CD9: =MAX(CA9,0) -> 0 | CE9: =MAX(-CA9,0) -> 249 | CF9: 0 | CG9: =IF(CA9>=0,"+","-")&FIXED(ABS(CA9),0) -> -249 | CH9: Abr | CI9: =ROUND(IF($BY$46="1 · Ingresos",CM9,IF($BY$46="2 · Costo de ventas",CO9,IF($BY$46="3 · Gastos operativos",CQ9,(CM9-CO9-CQ9-CS9)*(1-pTasaRenta))))/1000000,0) -> 950 | CJ9: =ROUND(IF($BY$46="1 · Ingresos",CN9,IF($BY$46="2 · Costo de ventas",CP9,IF($BY$46="3 · Gastos operativos",CR9,(CN9-CP9-CR9-CT9)*(1-pTasaRenta))))/1000000,0) -> 1081 | CL9: 4 | CM9: =SUMIFS(qPPTO[Real],qPPTO[MesNum],CL9,qPPTO[Línea],"Ingresos operacionales") -> 950000000 | CN9: =SUMIFS(qPPTO[Presupuesto],qPPTO[MesNum],CL9,qPPTO[Línea],"Ingresos operacionales") -> 1081147500 | CO9: =SUMIFS(qPPTO[Real],qPPTO[MesNum],CL9,qPPTO[Línea],"Costo de ventas") -> 604100000 | CP9: =SUMIFS(qPPTO[Presupuesto],qPPTO[MesNum],CL9,qPPTO[Línea],"Costo de ventas") -> 675565030 | CQ9: =SUMIFS(qPPTO[Real],qPPTO[MesNum],CL9,qPPTO[Línea],"Gastos de administración")+SUMIFS(qPPTO[Real],qPPTO[MesNum],CL9,qPPTO[Línea],"Gastos de ventas") -> 279800000 | CR9: =SUMIFS(qPPTO[Presupuesto],qPPTO[MesNum],CL9,qPPTO[Línea],"Gastos de administración")+SUMIFS(qPPTO[Presupuesto],qPPTO[MesNum],CL9,qPPTO[Línea],"Gastos de ventas") -> 300338500 | CS9: =SUMIFS(qPPTO[Real],qPPTO[MesNum],CL9,qPPTO[Línea],"Gastos financieros")-SUMIFS(qPPTO[Real],qPPTO[MesNum],CL9,qPPTO[Línea],"Otros ingresos no operacionales")+SUMIFS(qPPTO[Real],qPPTO[MesNum],CL9,qPPTO[Línea],"Otros gastos no operacionales") -> 24000000 | CT9: =SUMIFS(qPPTO[Presupuesto],qPPTO[MesNum],CL9,qPPTO[Línea],"Gastos financieros")-SUMIFS(qPPTO[Presupuesto],qPPTO[MesNum],CL9,qPPTO[Línea],"Otros ingresos no operacionales")+SUMIFS(qPPTO[Presupuesto],qPPTO[MesNum],CL9,qPPTO[Línea],"Otros gastos no operacionales") -> 21790000 | CW9: 1 | CZ9: =IF(ccN<4,"",INDEX(ccLbl,4)) -> Operaciones | DA9: =IF(CZ9="","",ROUND(INDEX(ccReal,4)/1000000,0)) -> 1010 | DB9: =IF(CZ9="","",ROUND(INDEX(ccPpto,4)/1000000,0)) -> 1068 | DC9: =IF(CZ9="","",IFERROR(DB9/DA9-1,0)) -> 0.057425743
A10: Gastos financieros | B10: 308000000 | C10: 283920000 | F10: Publicidad y mercadeo | G10: 240000000 | H10: 3.2448e+08 | I10: 84480000 | J10: 84480000 | AK10: Administración | AL10: 1260000000 | AM10: 1290000000 | BX10: Utilidad bruta Real | BY10: =BY6-BY8 -> 4370000000 | BZ10: Financieros y otros | CA10: =ROUND((-(BY25-BY24)+(BY27-BY26)-(BY29-BY28))/1000000,0) -> 26 | CB10: =CB9+CA10 -> 981 | CC10: =MIN(CB9,CB10) -> 955 | CD10: =MAX(CA10,0) -> 26 | CE10: =MAX(-CA10,0) -> 0 | CF10: 0 | CG10: =IF(CA10>=0,"+","-")&FIXED(ABS(CA10),0) -> +26 | CH10: May | CI10: =ROUND(IF($BY$46="1 · Ingresos",CM10,IF($BY$46="2 · Costo de ventas",CO10,IF($BY$46="3 · Gastos operativos",CQ10,(CM10-CO10-CQ10-CS10)*(1-pTasaRenta))))/1000000,0) -> 1000 | CJ10: =ROUND(IF($BY$46="1 · Ingresos",CN10,IF($BY$46="2 · Costo de ventas",CP10,IF($BY$46="3 · Gastos operativos",CR10,(CN10-CP10-CR10-CT10)*(1-pTasaRenta))))/1000000,0) -> 1138 | CL10: 5 | CM10: =SUMIFS(qPPTO[Real],qPPTO[MesNum],CL10,qPPTO[Línea],"Ingresos operacionales") -> 1000000000 | CN10: =SUMIFS(qPPTO[Presupuesto],qPPTO[MesNum],CL10,qPPTO[Línea],"Ingresos operacionales") -> 1138050000 | CO10: =SUMIFS(qPPTO[Real],qPPTO[MesNum],CL10,qPPTO[Línea],"Costo de ventas") -> 635800000 | CP10: =SUMIFS(qPPTO[Presupuesto],qPPTO[MesNum],CL10,qPPTO[Línea],"Costo de ventas") -> 711015140 | CQ10: =SUMIFS(qPPTO[Real],qPPTO[MesNum],CL10,qPPTO[Línea],"Gastos de administración")+SUMIFS(qPPTO[Real],qPPTO[MesNum],CL10,qPPTO[Línea],"Gastos de ventas") -> 282500000 | CR10: =SUMIFS(qPPTO[Presupuesto],qPPTO[MesNum],CL10,qPPTO[Línea],"Gastos de administración")+SUMIFS(qPPTO[Presupuesto],qPPTO[MesNum],CL10,qPPTO[Línea],"Gastos de ventas") -> 303280000 | CS10: =SUMIFS(qPPTO[Real],qPPTO[MesNum],CL10,qPPTO[Línea],"Gastos financieros")-SUMIFS(qPPTO[Real],qPPTO[MesNum],CL10,qPPTO[Línea],"Otros ingresos no operacionales")+SUMIFS(qPPTO[Real],qPPTO[MesNum],CL10,qPPTO[Línea],"Otros gastos no operacionales") -> 24000000 | CT10: =SUMIFS(qPPTO[Presupuesto],qPPTO[MesNum],CL10,qPPTO[Línea],"Gastos financieros")-SUMIFS(qPPTO[Presupuesto],qPPTO[MesNum],CL10,qPPTO[Línea],"Otros ingresos no operacionales")+SUMIFS(qPPTO[Presupuesto],qPPTO[MesNum],CL10,qPPTO[Línea],"Otros gastos no operacionales") -> 21790000 | CW10: 1 | CZ10: =IF(ccN<5,"",INDEX(ccLbl,5)) | DA10: =IF(CZ10="","",ROUND(INDEX(ccReal,5)/1000000,0)) | DB10: =IF(CZ10="","",ROUND(INDEX(ccPpto,5)/1000000,0)) | DC10: =IF(CZ10="","",IFERROR(DB10/DA10-1,0))
A11: Ingresos operacionales | B11: 12000000000 | C11: 13656600000 | F11: Servicios de instalación | G11: 600000000 | H11: 667800000 | I11: 67800000 | J11: 67800000 | AK11: Comercial | AL11: 1120000000 | AM11: 1281560000 | BX11: Utilidad bruta Presupuesto | BY11: =BY7-BY9 -> 5123971000 | BZ11: Impuesto | CA11: =CA12-SUM(CA6:CA10) -> -186 | CB11: =CB10+CA11 -> 795 | CC11: =MIN(CB10,CB11) -> 795 | CD11: =MAX(CA11,0) -> 0 | CE11: =MAX(-CA11,0) -> 186 | CF11: 0 | CG11: =IF(CA11>=0,"+","-")&FIXED(ABS(CA11),0) -> -186 | CH11: Jun | CI11: =ROUND(IF($BY$46="1 · Ingresos",CM11,IF($BY$46="2 · Costo de ventas",CO11,IF($BY$46="3 · Gastos operativos",CQ11,(CM11-CO11-CQ11-CS11)*(1-pTasaRenta))))/1000000,0) -> 1000 | CJ11: =ROUND(IF($BY$46="1 · Ingresos",CN11,IF($BY$46="2 · Costo de ventas",CP11,IF($BY$46="3 · Gastos operativos",CR11,(CN11-CP11-CR11-CT11)*(1-pTasaRenta))))/1000000,0) -> 1138 | CL11: 6 | CM11: =SUMIFS(qPPTO[Real],qPPTO[MesNum],CL11,qPPTO[Línea],"Ingresos operacionales") -> 1000000000 | CN11: =SUMIFS(qPPTO[Presupuesto],qPPTO[MesNum],CL11,qPPTO[Línea],"Ingresos operacionales") -> 1138050000 | CO11: =SUMIFS(qPPTO[Real],qPPTO[MesNum],CL11,qPPTO[Línea],"Costo de ventas") -> 635800000 | CP11: =SUMIFS(qPPTO[Presupuesto],qPPTO[MesNum],CL11,qPPTO[Línea],"Costo de ventas") -> 711015140 | CQ11: =SUMIFS(qPPTO[Real],qPPTO[MesNum],CL11,qPPTO[Línea],"Gastos de administración")+SUMIFS(qPPTO[Real],qPPTO[MesNum],CL11,qPPTO[Línea],"Gastos de ventas") -> 282500000 | CR11: =SUMIFS(qPPTO[Presupuesto],qPPTO[MesNum],CL11,qPPTO[Línea],"Gastos de administración")+SUMIFS(qPPTO[Presupuesto],qPPTO[MesNum],CL11,qPPTO[Línea],"Gastos de ventas") -> 303280000 | CS11: =SUMIFS(qPPTO[Real],qPPTO[MesNum],CL11,qPPTO[Línea],"Gastos financieros")-SUMIFS(qPPTO[Real],qPPTO[MesNum],CL11,qPPTO[Línea],"Otros ingresos no operacionales")+SUMIFS(qPPTO[Real],qPPTO[MesNum],CL11,qPPTO[Línea],"Otros gastos no operacionales") -> 24000000 | CT11: =SUMIFS(qPPTO[Presupuesto],qPPTO[MesNum],CL11,qPPTO[Línea],"Gastos financieros")-SUMIFS(qPPTO[Presupuesto],qPPTO[MesNum],CL11,qPPTO[Línea],"Otros ingresos no operacionales")+SUMIFS(qPPTO[Presupuesto],qPPTO[MesNum],CL11,qPPTO[Línea],"Otros gastos no operacionales") -> 21790000 | CW11: 1 | CZ11: =IF(ccN<6,"",INDEX(ccLbl,6)) | DA11: =IF(CZ11="","",ROUND(INDEX(ccReal,6)/1000000,0)) | DB11: =IF(CZ11="","",ROUND(INDEX(ccPpto,6)/1000000,0)) | DC11: =IF(CZ11="","",IFERROR(DB11/DA11-1,0))
A12: Otros gastos no operacionales | B12: 40000000 | C12: 40000000 | F12: Fletes de compra | G12: 480000000 | H12: 536784000 | I12: 56784000 | J12: 56784000 | AK12: Corporativo | AL12: 348000000 | AM12: 323920000 | BX12: Gastos administración Real | BY12: =IFERROR(SUMIFS(qPPTO[Real],qPPTO[Línea],"Gastos de administración"),0) -> 1260000000 | BZ12: Utilidad 2027 | CA12: =ROUND(BY35/1000000,0) -> 795 | CB12: =CA12 -> 795 | CC12: 0 | CD12: 0 | CE12: 0 | CF12: =CA12 -> 795 | CG12: =FIXED(CA12,0) -> 795 | CH12: Jul | CI12: =ROUND(IF($BY$46="1 · Ingresos",CM12,IF($BY$46="2 · Costo de ventas",CO12,IF($BY$46="3 · Gastos operativos",CQ12,(CM12-CO12-CQ12-CS12)*(1-pTasaRenta))))/1000000,0) -> 1000 | CJ12: =ROUND(IF($BY$46="1 · Ingresos",CN12,IF($BY$46="2 · Costo de ventas",CP12,IF($BY$46="3 · Gastos operativos",CR12,(CN12-CP12-CR12-CT12)*(1-pTasaRenta))))/1000000,0) -> 1138 | CL12: 7 | CM12: =SUMIFS(qPPTO[Real],qPPTO[MesNum],CL12,qPPTO[Línea],"Ingresos operacionales") -> 1000000000 | CN12: =SUMIFS(qPPTO[Presupuesto],qPPTO[MesNum],CL12,qPPTO[Línea],"Ingresos operacionales") -> 1138050000 | CO12: =SUMIFS(qPPTO[Real],qPPTO[MesNum],CL12,qPPTO[Línea],"Costo de ventas") -> 635800000 | CP12: =SUMIFS(qPPTO[Presupuesto],qPPTO[MesNum],CL12,qPPTO[Línea],"Costo de ventas") -> 711015140 | CQ12: =SUMIFS(qPPTO[Real],qPPTO[MesNum],CL12,qPPTO[Línea],"Gastos de administración")+SUMIFS(qPPTO[Real],qPPTO[MesNum],CL12,qPPTO[Línea],"Gastos de ventas") -> 282500000 | CR12: =SUMIFS(qPPTO[Presupuesto],qPPTO[MesNum],CL12,qPPTO[Línea],"Gastos de administración")+SUMIFS(qPPTO[Presupuesto],qPPTO[MesNum],CL12,qPPTO[Línea],"Gastos de ventas") -> 303280000 | CS12: =SUMIFS(qPPTO[Real],qPPTO[MesNum],CL12,qPPTO[Línea],"Gastos financieros")-SUMIFS(qPPTO[Real],qPPTO[MesNum],CL12,qPPTO[Línea],"Otros ingresos no operacionales")+SUMIFS(qPPTO[Real],qPPTO[MesNum],CL12,qPPTO[Línea],"Otros gastos no operacionales") -> 24000000 | CT12: =SUMIFS(qPPTO[Presupuesto],qPPTO[MesNum],CL12,qPPTO[Línea],"Gastos financieros")-SUMIFS(qPPTO[Presupuesto],qPPTO[MesNum],CL12,qPPTO[Línea],"Otros ingresos no operacionales")+SUMIFS(qPPTO[Presupuesto],qPPTO[MesNum],CL12,qPPTO[Línea],"Otros gastos no operacionales") -> 21790000 | CW12: 1
A13: Otros ingresos no operacionales | B13: 60000000 | C13: 62400000 | F13: Nómina administrativa | G13: 600000000 | H13: 642000000 | I13: 42000000 | J13: 42000000 | AK13: Operaciones | AL13: 1010000000 | AM13: 1067800000 | BX13: Gastos administración Presupuesto | BY13: =IFERROR(SUMIFS(qPPTO[Presupuesto],qPPTO[Línea],"Gastos de administración"),0) -> 1290000000 | CH13: Ago | CI13: =ROUND(IF($BY$46="1 · Ingresos",CM13,IF($BY$46="2 · Costo de ventas",CO13,IF($BY$46="3 · Gastos operativos",CQ13,(CM13-CO13-CQ13-CS13)*(1-pTasaRenta))))/1000000,0) -> 1050 | CJ13: =ROUND(IF($BY$46="1 · Ingresos",CN13,IF($BY$46="2 · Costo de ventas",CP13,IF($BY$46="3 · Gastos operativos",CR13,(CN13-CP13-CR13-CT13)*(1-pTasaRenta))))/1000000,0) -> 1195 | CL13: 8 | CM13: =SUMIFS(qPPTO[Real],qPPTO[MesNum],CL13,qPPTO[Línea],"Ingresos operacionales") -> 1050000000 | CN13: =SUMIFS(qPPTO[Presupuesto],qPPTO[MesNum],CL13,qPPTO[Línea],"Ingresos operacionales") -> 1194952500 | CO13: =SUMIFS(qPPTO[Real],qPPTO[MesNum],CL13,qPPTO[Línea],"Costo de ventas") -> 667600000 | CP13: =SUMIFS(qPPTO[Presupuesto],qPPTO[MesNum],CL13,qPPTO[Línea],"Costo de ventas") -> 746577080 | CQ13: =SUMIFS(qPPTO[Real],qPPTO[MesNum],CL13,qPPTO[Línea],"Gastos de administración")+SUMIFS(qPPTO[Real],qPPTO[MesNum],CL13,qPPTO[Línea],"Gastos de ventas") -> 285200000 | CR13: =SUMIFS(qPPTO[Presupuesto],qPPTO[MesNum],CL13,qPPTO[Línea],"Gastos de administración")+SUMIFS(qPPTO[Presupuesto],qPPTO[MesNum],CL13,qPPTO[Línea],"Gastos de ventas") -> 306221500 | CS13: =SUMIFS(qPPTO[Real],qPPTO[MesNum],CL13,qPPTO[Línea],"Gastos financieros")-SUMIFS(qPPTO[Real],qPPTO[MesNum],CL13,qPPTO[Línea],"Otros ingresos no operacionales")+SUMIFS(qPPTO[Real],qPPTO[MesNum],CL13,qPPTO[Línea],"Otros gastos no operacionales") -> 24000000 | CT13: =SUMIFS(qPPTO[Presupuesto],qPPTO[MesNum],CL13,qPPTO[Línea],"Gastos financieros")-SUMIFS(qPPTO[Presupuesto],qPPTO[MesNum],CL13,qPPTO[Línea],"Otros ingresos no operacionales")+SUMIFS(qPPTO[Presupuesto],qPPTO[MesNum],CL13,qPPTO[Línea],"Otros gastos no operacionales") -> 21790000
F14: Comisiones de ventas | G14: 360000000 | H14: 400680000 | I14: 40680000 | J14: 40680000 | BX14: Gastos de ventas Real | BY14: =IFERROR(SUMIFS(qPPTO[Real],qPPTO[Línea],"Gastos de ventas"),0) -> 2130000000 | CH14: Sep | CI14: =ROUND(IF($BY$46="1 · Ingresos",CM14,IF($BY$46="2 · Costo de ventas",CO14,IF($BY$46="3 · Gastos operativos",CQ14,(CM14-CO14-CQ14-CS14)*(1-pTasaRenta))))/1000000,0) -> 1000 | CJ14: =ROUND(IF($BY$46="1 · Ingresos",CN14,IF($BY$46="2 · Costo de ventas",CP14,IF($BY$46="3 · Gastos operativos",CR14,(CN14-CP14-CR14-CT14)*(1-pTasaRenta))))/1000000,0) -> 1138 | CL14: 9 | CM14: =SUMIFS(qPPTO[Real],qPPTO[MesNum],CL14,qPPTO[Línea],"Ingresos operacionales") -> 1000000000 | CN14: =SUMIFS(qPPTO[Presupuesto],qPPTO[MesNum],CL14,qPPTO[Línea],"Ingresos operacionales") -> 1138050000 | CO14: =SUMIFS(qPPTO[Real],qPPTO[MesNum],CL14,qPPTO[Línea],"Costo de ventas") -> 635800000 | CP14: =SUMIFS(qPPTO[Presupuesto],qPPTO[MesNum],CL14,qPPTO[Línea],"Costo de ventas") -> 711015140 | CQ14: =SUMIFS(qPPTO[Real],qPPTO[MesNum],CL14,qPPTO[Línea],"Gastos de administración")+SUMIFS(qPPTO[Real],qPPTO[MesNum],CL14,qPPTO[Línea],"Gastos de ventas") -> 282500000 | CR14: =SUMIFS(qPPTO[Presupuesto],qPPTO[MesNum],CL14,qPPTO[Línea],"Gastos de administración")+SUMIFS(qPPTO[Presupuesto],qPPTO[MesNum],CL14,qPPTO[Línea],"Gastos de ventas") -> 303280000 | CS14: =SUMIFS(qPPTO[Real],qPPTO[MesNum],CL14,qPPTO[Línea],"Gastos financieros")-SUMIFS(qPPTO[Real],qPPTO[MesNum],CL14,qPPTO[Línea],"Otros ingresos no operacionales")+SUMIFS(qPPTO[Real],qPPTO[MesNum],CL14,qPPTO[Línea],"Otros gastos no operacionales") -> 24000000 | CT14: =SUMIFS(qPPTO[Presupuesto],qPPTO[MesNum],CL14,qPPTO[Línea],"Gastos financieros")-SUMIFS(qPPTO[Presupuesto],qPPTO[MesNum],CL14,qPPTO[Línea],"Otros ingresos no operacionales")+SUMIFS(qPPTO[Presupuesto],qPPTO[MesNum],CL14,qPPTO[Línea],"Otros gastos no operacionales") -> 21790000
F15: Nómina comercial | G15: 520000000 | H15: 556400000 | I15: 36400000 | J15: 36400000 | BX15: Gastos de ventas Presupuesto | BY15: =IFERROR(SUMIFS(qPPTO[Presupuesto],qPPTO[Línea],"Gastos de ventas"),0) -> 2349360000 | CH15: Oct | CI15: =ROUND(IF($BY$46="1 · Ingresos",CM15,IF($BY$46="2 · Costo de ventas",CO15,IF($BY$46="3 · Gastos operativos",CQ15,(CM15-CO15-CQ15-CS15)*(1-pTasaRenta))))/1000000,0) -> 1050 | CJ15: =ROUND(IF($BY$46="1 · Ingresos",CN15,IF($BY$46="2 · Costo de ventas",CP15,IF($BY$46="3 · Gastos operativos",CR15,(CN15-CP15-CR15-CT15)*(1-pTasaRenta))))/1000000,0) -> 1195 | CL15: 10 | CM15: =SUMIFS(qPPTO[Real],qPPTO[MesNum],CL15,qPPTO[Línea],"Ingresos operacionales") -> 1050000000 | CN15: =SUMIFS(qPPTO[Presupuesto],qPPTO[MesNum],CL15,qPPTO[Línea],"Ingresos operacionales") -> 1194952500 | CO15: =SUMIFS(qPPTO[Real],qPPTO[MesNum],CL15,qPPTO[Línea],"Costo de ventas") -> 667600000 | CP15: =SUMIFS(qPPTO[Presupuesto],qPPTO[MesNum],CL15,qPPTO[Línea],"Costo de ventas") -> 746577080 | CQ15: =SUMIFS(qPPTO[Real],qPPTO[MesNum],CL15,qPPTO[Línea],"Gastos de administración")+SUMIFS(qPPTO[Real],qPPTO[MesNum],CL15,qPPTO[Línea],"Gastos de ventas") -> 285200000 | CR15: =SUMIFS(qPPTO[Presupuesto],qPPTO[MesNum],CL15,qPPTO[Línea],"Gastos de administración")+SUMIFS(qPPTO[Presupuesto],qPPTO[MesNum],CL15,qPPTO[Línea],"Gastos de ventas") -> 306221500 | CS15: =SUMIFS(qPPTO[Real],qPPTO[MesNum],CL15,qPPTO[Línea],"Gastos financieros")-SUMIFS(qPPTO[Real],qPPTO[MesNum],CL15,qPPTO[Línea],"Otros ingresos no operacionales")+SUMIFS(qPPTO[Real],qPPTO[MesNum],CL15,qPPTO[Línea],"Otros gastos no operacionales") -> 24000000 | CT15: =SUMIFS(qPPTO[Presupuesto],qPPTO[MesNum],CL15,qPPTO[Línea],"Gastos financieros")-SUMIFS(qPPTO[Presupuesto],qPPTO[MesNum],CL15,qPPTO[Línea],"Otros ingresos no operacionales")+SUMIFS(qPPTO[Presupuesto],qPPTO[MesNum],CL15,qPPTO[Línea],"Otros gastos no operacionales") -> 21790000
F16: Nómina de bodega | G16: 380000000 | H16: 406600000 | I16: 26600000 | J16: 26600000 | BX16: Gastos operativos Real | BY16: =BY12+BY14 -> 3390000000 | CH16: Nov | CI16: =ROUND(IF($BY$46="1 · Ingresos",CM16,IF($BY$46="2 · Costo de ventas",CO16,IF($BY$46="3 · Gastos operativos",CQ16,(CM16-CO16-CQ16-CS16)*(1-pTasaRenta))))/1000000,0) -> 1150 | CJ16: =ROUND(IF($BY$46="1 · Ingresos",CN16,IF($BY$46="2 · Costo de ventas",CP16,IF($BY$46="3 · Gastos operativos",CR16,(CN16-CP16-CR16-CT16)*(1-pTasaRenta))))/1000000,0) -> 1309 | CL16: 11 | CM16: =SUMIFS(qPPTO[Real],qPPTO[MesNum],CL16,qPPTO[Línea],"Ingresos operacionales") -> 1150000000 | CN16: =SUMIFS(qPPTO[Presupuesto],qPPTO[MesNum],CL16,qPPTO[Línea],"Ingresos operacionales") -> 1308757500 | CO16: =SUMIFS(qPPTO[Real],qPPTO[MesNum],CL16,qPPTO[Línea],"Costo de ventas") -> 731200000 | CP16: =SUMIFS(qPPTO[Presupuesto],qPPTO[MesNum],CL16,qPPTO[Línea],"Costo de ventas") -> 817700960 | CQ16: =SUMIFS(qPPTO[Real],qPPTO[MesNum],CL16,qPPTO[Línea],"Gastos de administración")+SUMIFS(qPPTO[Real],qPPTO[MesNum],CL16,qPPTO[Línea],"Gastos de ventas") -> 290800000 | CR16: =SUMIFS(qPPTO[Presupuesto],qPPTO[MesNum],CL16,qPPTO[Línea],"Gastos de administración")+SUMIFS(qPPTO[Presupuesto],qPPTO[MesNum],CL16,qPPTO[Línea],"Gastos de ventas") -> 312316500 | CS16: =SUMIFS(qPPTO[Real],qPPTO[MesNum],CL16,qPPTO[Línea],"Gastos financieros")-SUMIFS(qPPTO[Real],qPPTO[MesNum],CL16,qPPTO[Línea],"Otros ingresos no operacionales")+SUMIFS(qPPTO[Real],qPPTO[MesNum],CL16,qPPTO[Línea],"Otros gastos no operacionales") -> 24000000 | CT16: =SUMIFS(qPPTO[Presupuesto],qPPTO[MesNum],CL16,qPPTO[Línea],"Gastos financieros")-SUMIFS(qPPTO[Presupuesto],qPPTO[MesNum],CL16,qPPTO[Línea],"Otros ingresos no operacionales")+SUMIFS(qPPTO[Presupuesto],qPPTO[MesNum],CL16,qPPTO[Línea],"Otros gastos no operacionales") -> 21790000
F17: Honorarios profesionales | G17: 120000000 | H17: 93600000 | I17: -26400000 | J17: 26400000 | BX17: Gastos operativos Presupuesto | BY17: =BY13+BY15 -> 3639360000 | CH17: Dic | CI17: =ROUND(IF($BY$46="1 · Ingresos",CM17,IF($BY$46="2 · Costo de ventas",CO17,IF($BY$46="3 · Gastos operativos",CQ17,(CM17-CO17-CQ17-CS17)*(1-pTasaRenta))))/1000000,0) -> 1200 | CJ17: =ROUND(IF($BY$46="1 · Ingresos",CN17,IF($BY$46="2 · Costo de ventas",CP17,IF($BY$46="3 · Gastos operativos",CR17,(CN17-CP17-CR17-CT17)*(1-pTasaRenta))))/1000000,0) -> 1366 | CL17: 12 | CM17: =SUMIFS(qPPTO[Real],qPPTO[MesNum],CL17,qPPTO[Línea],"Ingresos operacionales") -> 1200000000 | CN17: =SUMIFS(qPPTO[Presupuesto],qPPTO[MesNum],CL17,qPPTO[Línea],"Ingresos operacionales") -> 1365660000 | CO17: =SUMIFS(qPPTO[Real],qPPTO[MesNum],CL17,qPPTO[Línea],"Costo de ventas") -> 763100000 | CP17: =SUMIFS(qPPTO[Presupuesto],qPPTO[MesNum],CL17,qPPTO[Línea],"Costo de ventas") -> 853374730 | CQ17: =SUMIFS(qPPTO[Real],qPPTO[MesNum],CL17,qPPTO[Línea],"Gastos de administración")+SUMIFS(qPPTO[Real],qPPTO[MesNum],CL17,qPPTO[Línea],"Gastos de ventas") -> 293500000 | CR17: =SUMIFS(qPPTO[Presupuesto],qPPTO[MesNum],CL17,qPPTO[Línea],"Gastos de administración")+SUMIFS(qPPTO[Presupuesto],qPPTO[MesNum],CL17,qPPTO[Línea],"Gastos de ventas") -> 315258000 | CS17: =SUMIFS(qPPTO[Real],qPPTO[MesNum],CL17,qPPTO[Línea],"Gastos financieros")-SUMIFS(qPPTO[Real],qPPTO[MesNum],CL17,qPPTO[Línea],"Otros ingresos no operacionales")+SUMIFS(qPPTO[Real],qPPTO[MesNum],CL17,qPPTO[Línea],"Otros gastos no operacionales") -> 24000000 | CT17: =SUMIFS(qPPTO[Presupuesto],qPPTO[MesNum],CL17,qPPTO[Línea],"Gastos financieros")-SUMIFS(qPPTO[Presupuesto],qPPTO[MesNum],CL17,qPPTO[Línea],"Otros ingresos no operacionales")+SUMIFS(qPPTO[Presupuesto],qPPTO[MesNum],CL17,qPPTO[Línea],"Otros gastos no operacionales") -> 21830000
F18: Intereses financieros | G18: 260000000 | H18: 234000000 | I18: -26000000 | J18: 26000000 | BX18: Utilidad operativa Real | BY18: =BY10-BY16 -> 980000000
F19: Transporte y distribución | G19: 300000000 | H19: 318000000 | I19: 18000000 | J19: 18000000 | BX19: Utilidad operativa Presupuesto | BY19: =BY11-BY17 -> 1484611000
F20: Mermas y averías | G20: 150000000 | H20: 167745000 | I20: 17745000 | J20: 17745000 | BX20: Depreciación y amortización Real | BY20: =IFERROR(SUMIFS(qPPTO[Real],qPPTO[Cuenta],"Depreciación y amortización"),0) -> 180000000
F21: Arrendamiento de bodega | G21: 240000000 | H21: 249600000 | I21: 9600000 | J21: 9600000 | BX21: Depreciación y amortización Presupuesto | BY21: =IFERROR(SUMIFS(qPPTO[Presupuesto],qPPTO[Cuenta],"Depreciación y amortización"),0) -> 180000000
F22: Arrendamiento de oficinas | G22: 180000000 | H22: 187200000 | I22: 7200000 | J22: 7200000 | BX22: EBITDA Real | BY22: =BY18+BY20 -> 1160000000
F23: Tecnología y software | G23: 96000000 | H23: 99840000 | I23: 3840000 | J23: 3840000 | BX23: EBITDA Presupuesto | BY23: =BY19+BY21 -> 1664611000
F24: Mantenimiento | G24: 90000000 | H24: 93600000 | I24: 3600000 | J24: 3600000 | BX24: Gastos financieros Real | BY24: =IFERROR(SUMIFS(qPPTO[Real],qPPTO[Línea],"Gastos financieros"),0) -> 308000000
F25: Servicios públicos | G25: 84000000 | H25: 87360000 | I25: 3360000 | J25: 3360000 | BX25: Gastos financieros Presupuesto | BY25: =IFERROR(SUMIFS(qPPTO[Presupuesto],qPPTO[Línea],"Gastos financieros"),0) -> 283920000
F26: Ingresos por arrendamientos | G26: 60000000 | H26: 62400000 | I26: 2400000 | J26: 2400000 | BX26: Otros ingresos no operacionales Real | BY26: =IFERROR(SUMIFS(qPPTO[Real],qPPTO[Línea],"Otros ingresos no operacionales"),0) -> 60000000
F27: Comisiones bancarias | G27: 48000000 | H27: 49920000 | I27: 1920000 | J27: 1920000 | BX27: Otros ingresos no operacionales Presupuesto | BY27: =IFERROR(SUMIFS(qPPTO[Presupuesto],qPPTO[Línea],"Otros ingresos no operacionales"),0) -> 62400000
F28: Depreciación y amortización | G28: 180000000 | H28: 180000000 | I28: 0 | J28: 0 | BX28: Otros gastos no operacionales Real | BY28: =IFERROR(SUMIFS(qPPTO[Real],qPPTO[Línea],"Otros gastos no operacionales"),0) -> 40000000
F29: Gastos extraordinarios | G29: 40000000 | H29: 40000000 | I29: 0 | J29: 0 | BX29: Otros gastos no operacionales Presupuesto | BY29: =IFERROR(SUMIFS(qPPTO[Presupuesto],qPPTO[Línea],"Otros gastos no operacionales"),0) -> 40000000
BX30: Utilidad antes de impuestos Real | BY30: =BY18-BY24+BY26-BY28 -> 692000000
BX31: Utilidad antes de impuestos Presupuesto | BY31: =BY19-BY25+BY27-BY29 -> 1223091000
BX32: Impuesto de renta Real | BY32: =MAX(0,BY30)*pTasaRenta -> 2.422e+08
BX33: Impuesto de renta Presupuesto | BY33: =MAX(0,BY31)*pTasaRenta -> 428081850
BX34: Utilidad neta Real | BY34: =BY30-BY32 -> 449800000
BX35: Utilidad neta Presupuesto | BY35: =BY31-BY33 -> 795009150
BX36: Suma directa UAI Presupuesto (control) | BY36: =SUMPRODUCT((qPPTO[Tipo]="Ingreso")*qPPTO[Presupuesto])-SUMPRODUCT((qPPTO[Tipo]<>"Ingreso")*qPPTO[Presupuesto]) -> 1223091000
BX37: Cuadre (debe ser 0) | BY37: =BY31-BY36 -> 0
BX38: Margen bruto Real | BY38: =IFERROR(BY10/BY6,0) -> 0.36416667
BX39: Margen bruto Presupuesto | BY39: =IFERROR(BY11/BY7,0) -> 0.37520107
BX40: Margen EBITDA Real | BY40: =IFERROR(BY22/BY6,0) -> 0.096666667
AD41: MARGEN BRUTO 2027 | AE41: MARGEN EBITDA 2027 | AF41: MARGEN NETO 2027 | AG41: GASTOS OPER. / INGRESOS 2027 | BX41: Margen EBITDA Presupuesto | BY41: =IFERROR(BY23/BY7,0) -> 0.12189059
AD42: =BY39 -> 0.37520107 | AE42: =BY41 -> 0.12189059 | AF42: =BY43 -> 0.058214281 | AG42: =BY45 -> 0.26649093 | BX42: Margen neto Real | BY42: =IFERROR(BY34/BY6,0) -> 0.037483333
AD43: ="2026: "&FIXED(BY38*100,1)&"% · "&IF(AD42>=pMetaMargenBruto,"dentro de la meta","meta "&FIXED(pMetaMargenBruto*100,0)&"%") -> 2026: 36,4% · dentro de la meta | AE43: ="2026: "&FIXED(BY40*100,1)&"% · "&IF(AE42>=pMetaMargenEbitda,"dentro de la meta","meta "&FIXED(pMetaMargenEbitda*100,0)&"%") -> 2026: 9,7% · dentro de la meta | AF43: ="2026: "&FIXED(BY42*100,1)&"% · "&IF(AF42>=pMetaMargenNeto,"dentro de la meta","meta "&FIXED(pMetaMargenNeto*100,0)&"%") -> 2026: 3,7% · dentro de la meta | AG43: ="2026: "&FIXED(BY44*100,1)&"% · "&IF(AG42<=pMetaGastosIngresos,"dentro de la meta","meta "&FIXED(pMetaGastosIngresos*100,0)&"%") -> 2026: 28,3% · dentro de la meta | BX43: Margen neto Presupuesto | BY43: =IFERROR(BY35/BY7,0) -> 0.058214281
BX44: Gastos operativos / Ingresos Real | BY44: =IFERROR(BY16/BY6,0) -> 0.2825
BX45: Gastos operativos / Ingresos Presupuesto | BY45: =IFERROR(BY17/BY7,0) -> 0.26649093
BX46: Línea activa | BY46: =IF(linTabN<>1,"1 · Ingresos",INDEX(linTabLbl,1)) -> 1 · Ingresos
BX47: Pestaña Real | BY47: =IF(BY46="1 · Ingresos",BY6,IF(BY46="2 · Costo de ventas",BY8,IF(BY46="3 · Gastos operativos",BY16,BY34))) -> 12000000000
BX48: Pestaña Presupuesto | BY48: =IF(BY46="1 · Ingresos",BY7,IF(BY46="2 · Costo de ventas",BY9,IF(BY46="3 · Gastos operativos",BY17,BY35))) -> 13656600000
BX49: Pestaña Var $ | BY49: =BY48-BY47 -> 1656600000
BX50: Pestaña Var % | BY50: =IFERROR(BY49/BY47,0) -> 0.13805
BX51: Pestaña es gasto/costo | BY51: =IF(OR(BY46="2 · Costo de ventas",BY46="3 · Gastos operativos"),1,0) -> 0
BX52: Pestaña favorable | BY52: =IF(BY51=1,IF(BY50<=BY60,1,0),IF(BY49>=0,1,0)) -> 1
BX53: Píldora favorable | BY53: =IF(BY52=0,"",IF(BY49>=0,"+","-")&FIXED(ABS(BY49),0)&" | "&IF(BY49>=0,"+","-")&FIXED(ABS(BY50)*100,1)&"%") -> +1.656.600.000 | +13,8%
BX54: Píldora desfavorable | BY54: =IF(BY52=1,"",IF(BY49>=0,"+","-")&FIXED(ABS(BY49),0)&" | "&IF(BY49>=0,"+","-")&FIXED(ABS(BY50)*100,1)&"%")
BX55: Total línea (título) | BY55: =MID(BY46,5,50)&" · presupuesto 2027" -> Ingresos · presupuesto 2027
BX56: Presupuesto de la línea (texto) | BY56: ="Real 2026: $"&FIXED(BY47,0) -> Real 2026: $12.000.000.000
BX57: Subtítulo tablero | BY57: ="Distribuidora Altamira S.A.S. · presupuesto 2027 contra real 2026 · cifras en pesos colombianos" -> Distribuidora Altamira S.A.S. · presupuesto 2027 contra real 2026 · cifras en pesos colombianos
BX58: Narrativa cascada | BY58: ="Utilidad neta: $"&FIXED(BY34/1000000,0)&" M en 2026 y $"&FIXED(BY35/1000000,0)&" M en 2027 ("&IF(BY61>=0,"+","-")&FIXED(ABS(BY61)*100,1)&"%). Control: cascada - suma directa = $"&FIXED(BY37,0) -> Utilidad neta: $450 M en 2026 y $795 M en 2027 (+76,7%). Control: cascada - suma directa = $0
BX59: Footer rubros | BY59: ="Mostrando "&FIXED(MIN(15,cuentaN),0)&" de "&FIXED(cuentaN,0)&" cuentas, ordenadas por mayor variación absoluta entre 2026 y 2027" -> Mostrando 15 de 23 cuentas, ordenadas por mayor variación absoluta entre 2026 y 2027
N60: CUENTA | O60: CENTRO DE COSTO | P60: DRIVER | Q60: REAL 2026 | R60: PPTO 2027 | S60: VAR $ | T60: VAR % | BX60: Crecimiento ingresos | BY60: =IFERROR(BY7/BY6-1,0) -> 0.13805
N61: =IF(cuentaN<1,"",INDEX(cuentaLbl,1)) -> Venta de mercancía nacional | O61: =IF(N61="","",IFERROR(INDEX(qPPTO[Centro de costo],MATCH(N61,qPPTO[Cuenta],0)),"")) -> Comercial | P61: =IF(N61="","",IFERROR(INDEX(qPPTO[Driver],MATCH(N61,qPPTO[Cuenta],0)),"")) -> Ventas | Q61: =IF(N61="","",INDEX(cuentaReal,1)) -> 9600000000 | R61: =IF(N61="","",INDEX(cuentaPpto,1)) -> 10684800000 | S61: =IF(N61="","",R61-Q61) -> 1084800000 | T61: =IF(N61="","",IF(Q61=0,0,S61/Q61)) -> 0.113 | U61: =IF(N61="",0,IF(IFERROR(INDEX(qPPTO[Tipo],MATCH(N61,qPPTO[Cuenta],0)),"")="Ingreso",1,0)) -> 1 | BX61: Crecimiento utilidad neta | BY61: =IFERROR(BY35/BY34-1,0) -> 0.76747254
N62: =IF(cuentaN<2,"",INDEX(cuentaLbl,2)) -> Costo de mercancía vendida | O62: =IF(N62="","",IFERROR(INDEX(qPPTO[Centro de costo],MATCH(N62,qPPTO[Cuenta],0)),"")) -> Operaciones | P62: =IF(N62="","",IFERROR(INDEX(qPPTO[Driver],MATCH(N62,qPPTO[Cuenta],0)),"")) -> Costo variable | Q62: =IF(N62="","",INDEX(cuentaReal,2)) -> 7000000000 | R62: =IF(N62="","",INDEX(cuentaPpto,2)) -> 7828100000 | S62: =IF(N62="","",R62-Q62) -> 828100000 | T62: =IF(N62="","",IF(Q62=0,0,S62/Q62)) -> 0.1183 | U62: =IF(N62="",0,IF(IFERROR(INDEX(qPPTO[Tipo],MATCH(N62,qPPTO[Cuenta],0)),"")="Ingreso",1,0)) -> 0 | BX62: Narrativa centro de costo | BY62: =IFERROR("Mayor aumento de gasto: "&INDEX(ccEtq,MATCH(MAX(ccVar),ccVar,0))&" (+"&FIXED(MAX(ccVar)*100,1)&"%) · millones de pesos","Millones de pesos") -> Mayor aumento de gasto: Comercial (+14,5%) · millones de pesos
N63: =IF(cuentaN<3,"",INDEX(cuentaLbl,3)) -> Ventas canal digital | O63: =IF(N63="","",IFERROR(INDEX(qPPTO[Centro de costo],MATCH(N63,qPPTO[Cuenta],0)),"")) -> Comercial | P63: =IF(N63="","",IFERROR(INDEX(qPPTO[Driver],MATCH(N63,qPPTO[Cuenta],0)),"")) -> Ventas | Q63: =IF(N63="","",INDEX(cuentaReal,3)) -> 1800000000 | R63: =IF(N63="","",INDEX(cuentaPpto,3)) -> 2304000000 | S63: =IF(N63="","",R63-Q63) -> 504000000 | T63: =IF(N63="","",IF(Q63=0,0,S63/Q63)) -> 0.28 | U63: =IF(N63="",0,IF(IFERROR(INDEX(qPPTO[Tipo],MATCH(N63,qPPTO[Cuenta],0)),"")="Ingreso",1,0)) -> 1 | BX63: Narrativa mensual | BY63: =MID(BY46,5,50)&" · millones de pesos · mes pico 2027: "&INDEX($CH$6:$CH$17,MATCH(MAX($CJ$6:$CJ$17),$CJ$6:$CJ$17,0)) -> Ingresos · millones de pesos · mes pico 2027: Dic
N64: =IF(cuentaN<4,"",INDEX(cuentaLbl,4)) -> Publicidad y mercadeo | O64: =IF(N64="","",IFERROR(INDEX(qPPTO[Centro de costo],MATCH(N64,qPPTO[Cuenta],0)),"")) -> Comercial | P64: =IF(N64="","",IFERROR(INDEX(qPPTO[Driver],MATCH(N64,qPPTO[Cuenta],0)),"")) -> IPC | Q64: =IF(N64="","",INDEX(cuentaReal,4)) -> 240000000 | R64: =IF(N64="","",INDEX(cuentaPpto,4)) -> 3.2448e+08 | S64: =IF(N64="","",R64-Q64) -> 84480000 | T64: =IF(N64="","",IF(Q64=0,0,S64/Q64)) -> 0.352 | U64: =IF(N64="",0,IF(IFERROR(INDEX(qPPTO[Tipo],MATCH(N64,qPPTO[Cuenta],0)),"")="Ingreso",1,0)) -> 0
N65: =IF(cuentaN<5,"",INDEX(cuentaLbl,5)) -> Servicios de instalación | O65: =IF(N65="","",IFERROR(INDEX(qPPTO[Centro de costo],MATCH(N65,qPPTO[Cuenta],0)),"")) -> Comercial | P65: =IF(N65="","",IFERROR(INDEX(qPPTO[Driver],MATCH(N65,qPPTO[Cuenta],0)),"")) -> Ventas | Q65: =IF(N65="","",INDEX(cuentaReal,5)) -> 600000000 | R65: =IF(N65="","",INDEX(cuentaPpto,5)) -> 667800000 | S65: =IF(N65="","",R65-Q65) -> 67800000 | T65: =IF(N65="","",IF(Q65=0,0,S65/Q65)) -> 0.113 | U65: =IF(N65="",0,IF(IFERROR(INDEX(qPPTO[Tipo],MATCH(N65,qPPTO[Cuenta],0)),"")="Ingreso",1,0)) -> 1
N66: =IF(cuentaN<6,"",INDEX(cuentaLbl,6)) -> Fletes de compra | O66: =IF(N66="","",IFERROR(INDEX(qPPTO[Centro de costo],MATCH(N66,qPPTO[Cuenta],0)),"")) -> Operaciones | P66: =IF(N66="","",IFERROR(INDEX(qPPTO[Driver],MATCH(N66,qPPTO[Cuenta],0)),"")) -> Costo variable | Q66: =IF(N66="","",INDEX(cuentaReal,6)) -> 480000000 | R66: =IF(N66="","",INDEX(cuentaPpto,6)) -> 536784000 | S66: =IF(N66="","",R66-Q66) -> 56784000 | T66: =IF(N66="","",IF(Q66=0,0,S66/Q66)) -> 0.1183 | U66: =IF(N66="",0,IF(IFERROR(INDEX(qPPTO[Tipo],MATCH(N66,qPPTO[Cuenta],0)),"")="Ingreso",1,0)) -> 0
N67: =IF(cuentaN<7,"",INDEX(cuentaLbl,7)) -> Nómina administrativa | O67: =IF(N67="","",IFERROR(INDEX(qPPTO[Centro de costo],MATCH(N67,qPPTO[Cuenta],0)),"")) -> Administración | P67: =IF(N67="","",IFERROR(INDEX(qPPTO[Driver],MATCH(N67,qPPTO[Cuenta],0)),"")) -> Nómina | Q67: =IF(N67="","",INDEX(cuentaReal,7)) -> 600000000 | R67: =IF(N67="","",INDEX(cuentaPpto,7)) -> 642000000 | S67: =IF(N67="","",R67-Q67) -> 42000000 | T67: =IF(N67="","",IF(Q67=0,0,S67/Q67)) -> 0.07 | U67: =IF(N67="",0,IF(IFERROR(INDEX(qPPTO[Tipo],MATCH(N67,qPPTO[Cuenta],0)),"")="Ingreso",1,0)) -> 0
N68: =IF(cuentaN<8,"",INDEX(cuentaLbl,8)) -> Comisiones de ventas | O68: =IF(N68="","",IFERROR(INDEX(qPPTO[Centro de costo],MATCH(N68,qPPTO[Cuenta],0)),"")) -> Comercial | P68: =IF(N68="","",IFERROR(INDEX(qPPTO[Driver],MATCH(N68,qPPTO[Cuenta],0)),"")) -> Ventas | Q68: =IF(N68="","",INDEX(cuentaReal,8)) -> 360000000 | R68: =IF(N68="","",INDEX(cuentaPpto,8)) -> 400680000 | S68: =IF(N68="","",R68-Q68) -> 40680000 | T68: =IF(N68="","",IF(Q68=0,0,S68/Q68)) -> 0.113 | U68: =IF(N68="",0,IF(IFERROR(INDEX(qPPTO[Tipo],MATCH(N68,qPPTO[Cuenta],0)),"")="Ingreso",1,0)) -> 0
N69: =IF(cuentaN<9,"",INDEX(cuentaLbl,9)) -> Nómina comercial | O69: =IF(N69="","",IFERROR(INDEX(qPPTO[Centro de costo],MATCH(N69,qPPTO[Cuenta],0)),"")) -> Comercial | P69: =IF(N69="","",IFERROR(INDEX(qPPTO[Driver],MATCH(N69,qPPTO[Cuenta],0)),"")) -> Nómina | Q69: =IF(N69="","",INDEX(cuentaReal,9)) -> 520000000 | R69: =IF(N69="","",INDEX(cuentaPpto,9)) -> 556400000 | S69: =IF(N69="","",R69-Q69) -> 36400000 | T69: =IF(N69="","",IF(Q69=0,0,S69/Q69)) -> 0.07 | U69: =IF(N69="",0,IF(IFERROR(INDEX(qPPTO[Tipo],MATCH(N69,qPPTO[Cuenta],0)),"")="Ingreso",1,0)) -> 0
N70: =IF(cuentaN<10,"",INDEX(cuentaLbl,10)) -> Nómina de bodega | O70: =IF(N70="","",IFERROR(INDEX(qPPTO[Centro de costo],MATCH(N70,qPPTO[Cuenta],0)),"")) -> Operaciones | P70: =IF(N70="","",IFERROR(INDEX(qPPTO[Driver],MATCH(N70,qPPTO[Cuenta],0)),"")) -> Nómina | Q70: =IF(N70="","",INDEX(cuentaReal,10)) -> 380000000 | R70: =IF(N70="","",INDEX(cuentaPpto,10)) -> 406600000 | S70: =IF(N70="","",R70-Q70) -> 26600000 | T70: =IF(N70="","",IF(Q70=0,0,S70/Q70)) -> 0.07 | U70: =IF(N70="",0,IF(IFERROR(INDEX(qPPTO[Tipo],MATCH(N70,qPPTO[Cuenta],0)),"")="Ingreso",1,0)) -> 0
N71: =IF(cuentaN<11,"",INDEX(cuentaLbl,11)) -> Honorarios profesionales | O71: =IF(N71="","",IFERROR(INDEX(qPPTO[Centro de costo],MATCH(N71,qPPTO[Cuenta],0)),"")) -> Administración | P71: =IF(N71="","",IFERROR(INDEX(qPPTO[Driver],MATCH(N71,qPPTO[Cuenta],0)),"")) -> IPC | Q71: =IF(N71="","",INDEX(cuentaReal,11)) -> 120000000 | R71: =IF(N71="","",INDEX(cuentaPpto,11)) -> 93600000 | S71: =IF(N71="","",R71-Q71) -> -26400000 | T71: =IF(N71="","",IF(Q71=0,0,S71/Q71)) -> -0.22 | U71: =IF(N71="",0,IF(IFERROR(INDEX(qPPTO[Tipo],MATCH(N71,qPPTO[Cuenta],0)),"")="Ingreso",1,0)) -> 0
N72: =IF(cuentaN<12,"",INDEX(cuentaLbl,12)) -> Intereses financieros | O72: =IF(N72="","",IFERROR(INDEX(qPPTO[Centro de costo],MATCH(N72,qPPTO[Cuenta],0)),"")) -> Corporativo | P72: =IF(N72="","",IFERROR(INDEX(qPPTO[Driver],MATCH(N72,qPPTO[Cuenta],0)),"")) -> Financiero | Q72: =IF(N72="","",INDEX(cuentaReal,12)) -> 260000000 | R72: =IF(N72="","",INDEX(cuentaPpto,12)) -> 234000000 | S72: =IF(N72="","",R72-Q72) -> -26000000 | T72: =IF(N72="","",IF(Q72=0,0,S72/Q72)) -> -0.1 | U72: =IF(N72="",0,IF(IFERROR(INDEX(qPPTO[Tipo],MATCH(N72,qPPTO[Cuenta],0)),"")="Ingreso",1,0)) -> 0
N73: =IF(cuentaN<13,"",INDEX(cuentaLbl,13)) -> Transporte y distribución | O73: =IF(N73="","",IFERROR(INDEX(qPPTO[Centro de costo],MATCH(N73,qPPTO[Cuenta],0)),"")) -> Operaciones | P73: =IF(N73="","",IFERROR(INDEX(qPPTO[Driver],MATCH(N73,qPPTO[Cuenta],0)),"")) -> Volumen | Q73: =IF(N73="","",INDEX(cuentaReal,13)) -> 300000000 | R73: =IF(N73="","",INDEX(cuentaPpto,13)) -> 318000000 | S73: =IF(N73="","",R73-Q73) -> 18000000 | T73: =IF(N73="","",IF(Q73=0,0,S73/Q73)) -> 0.06 | U73: =IF(N73="",0,IF(IFERROR(INDEX(qPPTO[Tipo],MATCH(N73,qPPTO[Cuenta],0)),"")="Ingreso",1,0)) -> 0
N74: =IF(cuentaN<14,"",INDEX(cuentaLbl,14)) -> Mermas y averías | O74: =IF(N74="","",IFERROR(INDEX(qPPTO[Centro de costo],MATCH(N74,qPPTO[Cuenta],0)),"")) -> Operaciones | P74: =IF(N74="","",IFERROR(INDEX(qPPTO[Driver],MATCH(N74,qPPTO[Cuenta],0)),"")) -> Costo variable | Q74: =IF(N74="","",INDEX(cuentaReal,14)) -> 150000000 | R74: =IF(N74="","",INDEX(cuentaPpto,14)) -> 167745000 | S74: =IF(N74="","",R74-Q74) -> 17745000 | T74: =IF(N74="","",IF(Q74=0,0,S74/Q74)) -> 0.1183 | U74: =IF(N74="",0,IF(IFERROR(INDEX(qPPTO[Tipo],MATCH(N74,qPPTO[Cuenta],0)),"")="Ingreso",1,0)) -> 0
N75: =IF(cuentaN<15,"",INDEX(cuentaLbl,15)) -> Arrendamiento de bodega | O75: =IF(N75="","",IFERROR(INDEX(qPPTO[Centro de costo],MATCH(N75,qPPTO[Cuenta],0)),"")) -> Operaciones | P75: =IF(N75="","",IFERROR(INDEX(qPPTO[Driver],MATCH(N75,qPPTO[Cuenta],0)),"")) -> IPC | Q75: =IF(N75="","",INDEX(cuentaReal,15)) -> 240000000 | R75: =IF(N75="","",INDEX(cuentaPpto,15)) -> 249600000 | S75: =IF(N75="","",R75-Q75) -> 9600000 | T75: =IF(N75="","",IF(Q75=0,0,S75/Q75)) -> 0.04 | U75: =IF(N75="",0,IF(IFERROR(INDEX(qPPTO[Tipo],MATCH(N75,qPPTO[Cuenta],0)),"")="Ingreso",1,0)) -> 0

Sheet Base
A1: Centro de costo | B1: Línea | C1: Cuenta | D1: Tipo | E1: Driver | F1: Mes | G1: MesNum | H1: Real | I1: Presupuesto | J1: Var | K1: VarAbs | L1: VarPct | M1: Real 2027
A2: ='PPTO 2027'!$E$14 -> Comercial | B2: ='PPTO 2027'!$C$14 -> Ingresos operacionales | C2: ='PPTO 2027'!$B$14 -> Venta de mercancía nacional | D2: ='PPTO 2027'!$D$14 -> Ingreso | E2: ='PPTO 2027'!$F$14 -> Ventas | F2: =CHOOSE(1,"Ene","Feb","Mar","Abr","May","Jun","Jul","Ago","Sep","Oct","Nov","Dic") -> Ene | G2: 1 | H2: ='PPTO 2027'!$I$14 -> 640000000 | I2: ='PPTO 2027'!$V$14 -> 712320000 | J2: =I2-H2 -> 72320000 | K2: =ABS(J2) -> 72320000 | L2: =IF(H2=0,"",J2/H2) -> 0.113 | M2: =IFERROR(INDEX(tReal27[[Ene]:[Dic]],MATCH(C2,tReal27[Cuenta],0),1),0) -> 713046000
A3: ='PPTO 2027'!$E$14 -> Comercial | B3: ='PPTO 2027'!$C$14 -> Ingresos operacionales | C3: ='PPTO 2027'!$B$14 -> Venta de mercancía nacional | D3: ='PPTO 2027'!$D$14 -> Ingreso | E3: ='PPTO 2027'!$F$14 -> Ventas | F3: =CHOOSE(2,"Ene","Feb","Mar","Abr","May","Jun","Jul","Ago","Sep","Oct","Nov","Dic") -> Feb | G3: 2 | H3: ='PPTO 2027'!$J$14 -> 680000000 | I3: ='PPTO 2027'!$W$14 -> 756840000 | J3: =I3-H3 -> 76840000 | K3: =ABS(J3) -> 76840000 | L3: =IF(H3=0,"",J3/H3) -> 0.113 | M3: =IFERROR(INDEX(tReal27[[Ene]:[Dic]],MATCH(C3,tReal27[Cuenta],0),2),0) -> 755737000
A4: ='PPTO 2027'!$E$14 -> Comercial | B4: ='PPTO 2027'!$C$14 -> Ingresos operacionales | C4: ='PPTO 2027'!$B$14 -> Venta de mercancía nacional | D4: ='PPTO 2027'!$D$14 -> Ingreso | E4: ='PPTO 2027'!$F$14 -> Ventas | F4: =CHOOSE(3,"Ene","Feb","Mar","Abr","May","Jun","Jul","Ago","Sep","Oct","Nov","Dic") -> Mar | G4: 3 | H4: ='PPTO 2027'!$K$14 -> 760000000 | I4: ='PPTO 2027'!$X$14 -> 845880000 | J4: =I4-H4 -> 85880000 | K4: =ABS(J4) -> 85880000 | L4: =IF(H4=0,"",J4/H4) -> 0.113 | M4: =IFERROR(INDEX(tReal27[[Ene]:[Dic]],MATCH(C4,tReal27[Cuenta],0),3),0) -> 846885000
A5: ='PPTO 2027'!$E$14 -> Comercial | B5: ='PPTO 2027'!$C$14 -> Ingresos operacionales | C5: ='PPTO 2027'!$B$14 -> Venta de mercancía nacional | D5: ='PPTO 2027'!$D$14 -> Ingreso | E5: ='PPTO 2027'!$F$14 -> Ventas | F5: =CHOOSE(4,"Ene","Feb","Mar","Abr","May","Jun","Jul","Ago","Sep","Oct","Nov","Dic") -> Abr | G5: 4 | H5: ='PPTO 2027'!$L$14 -> 760000000 | I5: ='PPTO 2027'!$Y$14 -> 845880000 | J5: =I5-H5 -> 85880000 | K5: =ABS(J5) -> 85880000 | L5: =IF(H5=0,"",J5/H5) -> 0.113 | M5: =IFERROR(INDEX(tReal27[[Ene]:[Dic]],MATCH(C5,tReal27[Cuenta],0),4),0) -> 836683000
A6: ='PPTO 2027'!$E$14 -> Comercial | B6: ='PPTO 2027'!$C$14 -> Ingresos operacionales | C6: ='PPTO 2027'!$B$14 -> Venta de mercancía nacional | D6: ='PPTO 2027'!$D$14 -> Ingreso | E6: ='PPTO 2027'!$F$14 -> Ventas | F6: =CHOOSE(5,"Ene","Feb","Mar","Abr","May","Jun","Jul","Ago","Sep","Oct","Nov","Dic") -> May | G6: 5 | H6: ='PPTO 2027'!$M$14 -> 800000000 | I6: ='PPTO 2027'!$Z$14 -> 890400000 | J6: =I6-H6 -> 90400000 | K6: =ABS(J6) -> 90400000 | L6: =IF(H6=0,"",J6/H6) -> 0.113 | M6: =IFERROR(INDEX(tReal27[[Ene]:[Dic]],MATCH(C6,tReal27[Cuenta],0),5),0) -> 855672000
A7: ='PPTO 2027'!$E$14 -> Comercial | B7: ='PPTO 2027'!$C$14 -> Ingresos operacionales | C7: ='PPTO 2027'!$B$14 -> Venta de mercancía nacional | D7: ='PPTO 2027'!$D$14 -> Ingreso | E7: ='PPTO 2027'!$F$14 -> Ventas | F7: =CHOOSE(6,"Ene","Feb","Mar","Abr","May","Jun","Jul","Ago","Sep","Oct","Nov","Dic") -> Jun | G7: 6 | H7: ='PPTO 2027'!$N$14 -> 800000000 | I7: ='PPTO 2027'!$AA$14 -> 890400000 | J7: =I7-H7 -> 90400000 | K7: =ABS(J7) -> 90400000 | L7: =IF(H7=0,"",J7/H7) -> 0.113 | M7: =IFERROR(INDEX(tReal27[[Ene]:[Dic]],MATCH(C7,tReal27[Cuenta],0),6),0) -> 895817000
A8: ='PPTO 2027'!$E$14 -> Comercial | B8: ='PPTO 2027'!$C$14 -> Ingresos operacionales | C8: ='PPTO 2027'!$B$14 -> Venta de mercancía nacional | D8: ='PPTO 2027'!$D$14 -> Ingreso | E8: ='PPTO 2027'!$F$14 -> Ventas | F8: =CHOOSE(7,"Ene","Feb","Mar","Abr","May","Jun","Jul","Ago","Sep","Oct","Nov","Dic") -> Jul | G8: 7 | H8: ='PPTO 2027'!$O$14 -> 800000000 | I8: ='PPTO 2027'!$AB$14 -> 890400000 | J8: =I8-H8 -> 90400000 | K8: =ABS(J8) -> 90400000 | L8: =IF(H8=0,"",J8/H8) -> 0.113 | M8: =IFERROR(INDEX(tReal27[[Ene]:[Dic]],MATCH(C8,tReal27[Cuenta],0),7),0) -> 883130000
A9: ='PPTO 2027'!$E$14 -> Comercial | B9: ='PPTO 2027'!$C$14 -> Ingresos operacionales | C9: ='PPTO 2027'!$B$14 -> Venta de mercancía nacional | D9: ='PPTO 2027'!$D$14 -> Ingreso | E9: ='PPTO 2027'!$F$14 -> Ventas | F9: =CHOOSE(8,"Ene","Feb","Mar","Abr","May","Jun","Jul","Ago","Sep","Oct","Nov","Dic") -> Ago | G9: 8 | H9: ='PPTO 2027'!$P$14 -> 840000000 | I9: ='PPTO 2027'!$AC$14 -> 934920000 | J9: =I9-H9 -> 94920000 | K9: =ABS(J9) -> 94920000 | L9: =IF(H9=0,"",J9/H9) -> 0.113 | M9: =IFERROR(INDEX(tReal27[[Ene]:[Dic]],MATCH(C9,tReal27[Cuenta],0),8),0) -> 931777000
A10: ='PPTO 2027'!$E$14 -> Comercial | B10: ='PPTO 2027'!$C$14 -> Ingresos operacionales | C10: ='PPTO 2027'!$B$14 -> Venta de mercancía nacional | D10: ='PPTO 2027'!$D$14 -> Ingreso | E10: ='PPTO 2027'!$F$14 -> Ventas | F10: =CHOOSE(9,"Ene","Feb","Mar","Abr","May","Jun","Jul","Ago","Sep","Oct","Nov","Dic") -> Sep | G10: 9 | H10: ='PPTO 2027'!$Q$14 -> 800000000 | I10: ='PPTO 2027'!$AD$14 -> 890400000 | J10: =I10-H10 -> 90400000 | K10: =ABS(J10) -> 90400000 | L10: =IF(H10=0,"",J10/H10) -> 0.113 | M10: =IFERROR(INDEX(tReal27[[Ene]:[Dic]],MATCH(C10,tReal27[Cuenta],0),9),0) -> 870837000
A11: ='PPTO 2027'!$E$14 -> Comercial | B11: ='PPTO 2027'!$C$14 -> Ingresos operacionales | C11: ='PPTO 2027'!$B$14 -> Venta de mercancía nacional | D11: ='PPTO 2027'!$D$14 -> Ingreso | E11: ='PPTO 2027'!$F$14 -> Ventas | F11: =CHOOSE(10,"Ene","Feb","Mar","Abr","May","Jun","Jul","Ago","Sep","Oct","Nov","Dic") -> Oct | G11: 10 | H11: ='PPTO 2027'!$R$14 -> 840000000 | I11: ='PPTO 2027'!$AE$14 -> 934920000 | J11: =I11-H11 -> 94920000 | K11: =ABS(J11) -> 94920000 | L11: =IF(H11=0,"",J11/H11) -> 0.113 | M11: =IFERROR(INDEX(tReal27[[Ene]:[Dic]],MATCH(C11,tReal27[Cuenta],0),10),0) -> 917337000
A12: ='PPTO 2027'!$E$14 -> Comercial | B12: ='PPTO 2027'!$C$14 -> Ingresos operacionales | C12: ='PPTO 2027'!$B$14 -> Venta de mercancía nacional | D12: ='PPTO 2027'!$D$14 -> Ingreso | E12: ='PPTO 2027'!$F$14 -> Ventas | F12: =CHOOSE(11,"Ene","Feb","Mar","Abr","May","Jun","Jul","Ago","Sep","Oct","Nov","Dic") -> Nov | G12: 11 | H12: ='PPTO 2027'!$S$14 -> 920000000 | I12: ='PPTO 2027'!$AF$14 -> 1023960000 | J12: =I12-H12 -> 103960000 | K12: =ABS(J12) -> 103960000 | L12: =IF(H12=0,"",J12/H12) -> 0.113 | M12: =IFERROR(INDEX(tReal27[[Ene]:[Dic]],MATCH(C12,tReal27[Cuenta],0),11),0) -> 1009300000
A13: ='PPTO 2027'!$E$14 -> Comercial | B13: ='PPTO 2027'!$C$14 -> Ingresos operacionales | C13: ='PPTO 2027'!$B$14 -> Venta de mercancía nacional | D13: ='PPTO 2027'!$D$14 -> Ingreso | E13: ='PPTO 2027'!$F$14 -> Ventas | F13: =CHOOSE(12,"Ene","Feb","Mar","Abr","May","Jun","Jul","Ago","Sep","Oct","Nov","Dic") -> Dic | G13: 12 | H13: ='PPTO 2027'!$T$14 -> 960000000 | I13: ='PPTO 2027'!$AG$14 -> 1068480000 | J13: =I13-H13 -> 108480000 | K13: =ABS(J13) -> 108480000 | L13: =IF(H13=0,"",J13/H13) -> 0.113 | M13: =IFERROR(INDEX(tReal27[[Ene]:[Dic]],MATCH(C13,tReal27[Cuenta],0),12),0) -> 1049757000
A14: ='PPTO 2027'!$E$15 -> Comercial | B14: ='PPTO 2027'!$C$15 -> Ingresos operacionales | C14: ='PPTO 2027'!$B$15 -> Ventas canal digital | D14: ='PPTO 2027'!$D$15 -> Ingreso | E14: ='PPTO 2027'!$F$15 -> Ventas | F14: =CHOOSE(1,"Ene","Feb","Mar","Abr","May","Jun","Jul","Ago","Sep","Oct","Nov","Dic") -> Ene | G14: 1 | H14: ='PPTO 2027'!$I$15 -> 120000000 | I14: ='PPTO 2027'!$V$15 -> 153600000 | J14: =I14-H14 -> 33600000 | K14: =ABS(J14) -> 33600000 | L14: =IF(H14=0,"",J14/H14) -> 0.28 | M14: =IFERROR(INDEX(tReal27[[Ene]:[Dic]],MATCH(C14,tReal27[Cuenta],0),1),0) -> 144875000
A15: ='PPTO 2027'!$E$15 -> Comercial | B15: ='PPTO 2027'!$C$15 -> Ingresos operacionales | C15: ='PPTO 2027'!$B$15 -> Ventas canal digital | D15: ='PPTO 2027'!$D$15 -> Ingreso | E15: ='PPTO 2027'!$F$15 -> Ventas | F15: =CHOOSE(2,"Ene","Feb","Mar","Abr","May","Jun","Jul","Ago","Sep","Oct","Nov","Dic") -> Feb | G15: 2 | H15: ='PPTO 2027'!$J$15 -> 127500000 | I15: ='PPTO 2027'!$W$15 -> 163200000 | J15: =I15-H15 -> 35700000 | K15: =ABS(J15) -> 35700000 | L15: =IF(H15=0,"",J15/H15) -> 0.28 | M15: =IFERROR(INDEX(tReal27[[Ene]:[Dic]],MATCH(C15,tReal27[Cuenta],0),2),0) -> 153285000
A16: ='PPTO 2027'!$E$15 -> Comercial | B16: ='PPTO 2027'!$C$15 -> Ingresos operacionales | C16: ='PPTO 2027'!$B$15 -> Ventas canal digital | D16: ='PPTO 2027'!$D$15 -> Ingreso | E16: ='PPTO 2027'!$F$15 -> Ventas | F16: =CHOOSE(3,"Ene","Feb","Mar","Abr","May","Jun","Jul","Ago","Sep","Oct","Nov","Dic") -> Mar | G16: 3 | H16: ='PPTO 2027'!$K$15 -> 142500000 | I16: ='PPTO 2027'!$X$15 -> 182400000 | J16: =I16-H16 -> 39900000 | K16: =ABS(J16) -> 39900000 | L16: =IF(H16=0,"",J16/H16) -> 0.28 | M16: =IFERROR(INDEX(tReal27[[Ene]:[Dic]],MATCH(C16,tReal27[Cuenta],0),3),0) -> 173145000
A17: ='PPTO 2027'!$E$15 -> Comercial | B17: ='PPTO 2027'!$C$15 -> Ingresos operacionales | C17: ='PPTO 2027'!$B$15 -> Ventas canal digital | D17: ='PPTO 2027'!$D$15 -> Ingreso | E17: ='PPTO 2027'!$F$15 -> Ventas | F17: =CHOOSE(4,"Ene","Feb","Mar","Abr","May","Jun","Jul","Ago","Sep","Oct","Nov","Dic") -> Abr | G17: 4 | H17: ='PPTO 2027'!$L$15 -> 142500000 | I17: ='PPTO 2027'!$Y$15 -> 182400000 | J17: =I17-H17 -> 39900000 | K17: =ABS(J17) -> 39900000 | L17: =IF(H17=0,"",J17/H17) -> 0.28 | M17: =IFERROR(INDEX(tReal27[[Ene]:[Dic]],MATCH(C17,tReal27[Cuenta],0),4),0) -> 177842000
A18: ='PPTO 2027'!$E$15 -> Comercial | B18: ='PPTO 2027'!$C$15 -> Ingresos operacionales | C18: ='PPTO 2027'!$B$15 -> Ventas canal digital | D18: ='PPTO 2027'!$D$15 -> Ingreso | E18: ='PPTO 2027'!$F$15 -> Ventas | F18: =CHOOSE(5,"Ene","Feb","Mar","Abr","May","Jun","Jul","Ago","Sep","Oct","Nov","Dic") -> May | G18: 5 | H18: ='PPTO 2027'!$M$15 -> 150000000 | I18: ='PPTO 2027'!$Z$15 -> 192000000 | J18: =I18-H18 -> 42000000 | K18: =ABS(J18) -> 42000000 | L18: =IF(H18=0,"",J18/H18) -> 0.28 | M18: =IFERROR(INDEX(tReal27[[Ene]:[Dic]],MATCH(C18,tReal27[Cuenta],0),5),0) -> 187633000
A19: ='PPTO 2027'!$E$15 -> Comercial | B19: ='PPTO 2027'!$C$15 -> Ingresos operacionales | C19: ='PPTO 2027'!$B$15 -> Ventas canal digital | D19: ='PPTO 2027'!$D$15 -> Ingreso | E19: ='PPTO 2027'!$F$15 -> Ventas | F19: =CHOOSE(6,"Ene","Feb","Mar","Abr","May","Jun","Jul","Ago","Sep","Oct","Nov","Dic") -> Jun | G19: 6 | H19: ='PPTO 2027'!$N$15 -> 150000000 | I19: ='PPTO 2027'!$AA$15 -> 192000000 | J19: =I19-H19 -> 42000000 | K19: =ABS(J19) -> 42000000 | L19: =IF(H19=0,"",J19/H19) -> 0.28 | M19: =IFERROR(INDEX(tReal27[[Ene]:[Dic]],MATCH(C19,tReal27[Cuenta],0),6),0) -> 180180000
A20: ='PPTO 2027'!$E$15 -> Comercial | B20: ='PPTO 2027'!$C$15 -> Ingresos operacionales | C20: ='PPTO 2027'!$B$15 -> Ventas canal digital | D20: ='PPTO 2027'!$D$15 -> Ingreso | E20: ='PPTO 2027'!$F$15 -> Ventas | F20: =CHOOSE(7,"Ene","Feb","Mar","Abr","May","Jun","Jul","Ago","Sep","Oct","Nov","Dic") -> Jul | G20: 7 | H20: ='PPTO 2027'!$O$15 -> 150000000 | I20: ='PPTO 2027'!$AB$15 -> 192000000 | J20: =I20-H20 -> 42000000 | K20: =ABS(J20) -> 42000000 | L20: =IF(H20=0,"",J20/H20) -> 0.28 | M20: =IFERROR(INDEX(tReal27[[Ene]:[Dic]],MATCH(C20,tReal27[Cuenta],0),7),0) -> 180550000
A21: ='PPTO 2027'!$E$15 -> Comercial | B21: ='PPTO 2027'!$C$15 -> Ingresos operacionales | C21: ='PPTO 2027'!$B$15 -> Ventas canal digital | D21: ='PPTO 2027'!$D$15 -> Ingreso | E21: ='PPTO 2027'!$F$15 -> Ventas | F21: =CHOOSE(8,"Ene","Feb","Mar","Abr","May","Jun","Jul","Ago","Sep","Oct","Nov","Dic") -> Ago | G21: 8 | H21: ='PPTO 2027'!$P$15 -> 157500000 | I21: ='PPTO 2027'!$AC$15 -> 201600000 | J21: =I21-H21 -> 44100000 | K21: =ABS(J21) -> 44100000 | L21: =IF(H21=0,"",J21/H21) -> 0.28 | M21: =IFERROR(INDEX(tReal27[[Ene]:[Dic]],MATCH(C21,tReal27[Cuenta],0),8),0) -> 192505000
A22: ='PPTO 2027'!$E$15 -> Comercial | B22: ='PPTO 2027'!$C$15 -> Ingresos operacionales | C22: ='PPTO 2027'!$B$15 -> Ventas canal digital | D22: ='PPTO 2027'!$D$15 -> Ingreso | E22: ='PPTO 2027'!$F$15 -> Ventas | F22: =CHOOSE(9,"Ene","Feb","Mar","Abr","May","Jun","Jul","Ago","Sep","Oct","Nov","Dic") -> Sep | G22: 9 | H22: ='PPTO 2027'!$Q$15 -> 150000000 | I22: ='PPTO 2027'!$AD$15 -> 192000000 | J22: =I22-H22 -> 42000000 | K22: =ABS(J22) -> 42000000 | L22: =IF(H22=0,"",J22/H22) -> 0.28 | M22: =IFERROR(INDEX(tReal27[[Ene]:[Dic]],MATCH(C22,tReal27[Cuenta],0),9),0) -> 182139000
A23: ='PPTO 2027'!$E$15 -> Comercial | B23: ='PPTO 2027'!$C$15 -> Ingresos operacionales | C23: ='PPTO 2027'!$B$15 -> Ventas canal digital | D23: ='PPTO 2027'!$D$15 -> Ingreso | E23: ='PPTO 2027'!$F$15 -> Ventas | F23: =CHOOSE(10,"Ene","Feb","Mar","Abr","May","Jun","Jul","Ago","Sep","Oct","Nov","Dic") -> Oct | G23: 10 | H23: ='PPTO 2027'!$R$15 -> 157500000 | I23: ='PPTO 2027'!$AE$15 -> 201600000 | J23: =I23-H23 -> 44100000 | K23: =ABS(J23) -> 44100000 | L23: =IF(H23=0,"",J23/H23) -> 0.28 | M23: =IFERROR(INDEX(tReal27[[Ene]:[Dic]],MATCH(C23,tReal27[Cuenta],0),10),0) -> 188789000
A24: ='PPTO 2027'!$E$15 -> Comercial | B24: ='PPTO 2027'!$C$15 -> Ingresos operacionales | C24: ='PPTO 2027'!$B$15 -> Ventas canal digital | D24: ='PPTO 2027'!$D$15 -> Ingreso | E24: ='PPTO 2027'!$F$15 -> Ventas | F24: =CHOOSE(11,"Ene","Feb","Mar","Abr","May","Jun","Jul","Ago","Sep","Oct","Nov","Dic") -> Nov | G24: 11 | H24: ='PPTO 2027'!$S$15 -> 172500000 | I24: ='PPTO 2027'!$AF$15 -> 220800000 | J24: =I24-H24 -> 48300000 | K24: =ABS(J24) -> 48300000 | L24: =IF(H24=0,"",J24/H24) -> 0.28 | M24: =IFERROR(INDEX(tReal27[[Ene]:[Dic]],MATCH(C24,tReal27[Cuenta],0),11),0) -> 208436000
A25: ='PPTO 2027'!$E$15 -> Comercial | B25: ='PPTO 2027'!$C$15 -> Ingresos operacionales | C25: ='PPTO 2027'!$B$15 -> Ventas canal digital | D25: ='PPTO 2027'!$D$15 -> Ingreso | E25: ='PPTO 2027'!$F$15 -> Ventas | F25: =CHOOSE(12,"Ene","Feb","Mar","Abr","May","Jun","Jul","Ago","Sep","Oct","Nov","Dic") -> Dic | G25: 12 | H25: ='PPTO 2027'!$T$15 -> 180000000 | I25: ='PPTO 2027'!$AG$15 -> 230400000 | J25: =I25-H25 -> 50400000 | K25: =ABS(J25) -> 50400000 | L25: =IF(H25=0,"",J25/H25) -> 0.28 | M25: =IFERROR(INDEX(tReal27[[Ene]:[Dic]],MATCH(C25,tReal27[Cuenta],0),12),0) -> 220883000
A26: ='PPTO 2027'!$E$16 -> Comercial | B26: ='PPTO 2027'!$C$16 -> Ingresos operacionales | C26: ='PPTO 2027'!$B$16 -> Servicios de instalación | D26: ='PPTO 2027'!$D$16 -> Ingreso | E26: ='PPTO 2027'!$F$16 -> Ventas | F26: =CHOOSE(1,"Ene","Feb","Mar","Abr","May","Jun","Jul","Ago","Sep","Oct","Nov","Dic") -> Ene | G26: 1 | H26: ='PPTO 2027'!$I$16 -> 40000000 | I26: ='PPTO 2027'!$V$16 -> 44520000 | J26: =I26-H26 -> 4520000 | K26: =ABS(J26) -> 4520000 | L26: =IF(H26=0,"",J26/H26) -> 0.113 | M26: =IFERROR(INDEX(tReal27[[Ene]:[Dic]],MATCH(C26,tReal27[Cuenta],0),1),0) -> 44137000
A27: ='PPTO 2027'!$E$16 -> Comercial | B27: ='PPTO 2027'!$C$16 -> Ingresos operacionales | C27: ='PPTO 2027'!$B$16 -> Servicios de instalación | D27: ='PPTO 2027'!$D$16 -> Ingreso | E27: ='PPTO 2027'!$F$16 -> Ventas | F27: =CHOOSE(2,"Ene","Feb","Mar","Abr","May","Jun","Jul","Ago","Sep","Oct","Nov","Dic") -> Feb | G27: 2 | H27: ='PPTO 2027'!$J$16 -> 42500000 | I27: ='PPTO 2027'!$W$16 -> 47302500 | J27: =I27-H27 -> 4802500 | K27: =ABS(J27) -> 4802500 | L27: =IF(H27=0,"",J27/H27) -> 0.113 | M27: =IFERROR(INDEX(tReal27[[Ene]:[Dic]],MATCH(C27,tReal27[Cuenta],0),2),0) -> 47424000
A28: ='PPTO 2027'!$E$16 -> Comercial | B28: ='PPTO 2027'!$C$16 -> Ingresos operacionales | C28: ='PPTO 2027'!$B$16 -> Servicios de instalación | D28: ='PPTO 2027'!$D$16 -> Ingreso | E28: ='PPTO 2027'!$F$16 -> Ventas | F28: =CHOOSE(3,"Ene","Feb","Mar","Abr","May","Jun","Jul","Ago","Sep","Oct","Nov","Dic") -> Mar | G28: 3 | H28: ='PPTO 2027'!$K$16 -> 47500000 | I28: ='PPTO 2027'!$X$16 -> 52867500 | J28: =I28-H28 -> 5367500 | K28: =ABS(J28) -> 5367500 | L28: =IF(H28=0,"",J28/H28) -> 0.113 | M28: =IFERROR(INDEX(tReal27[[Ene]:[Dic]],MATCH(C28,tReal27[Cuenta],0),3),0) -> 53065000
A29: ='PPTO 2027'!$E$16 -> Comercial | B29: ='PPTO 2027'!$C$16 -> Ingresos operacionales | C29: ='PPTO 2027'!$B$16 -> Servicios de instalación | D29: ='PPTO 2027'!$D$16 -> Ingreso | E29: ='PPTO 2027'!$F$16 -> Ventas | F29: =CHOOSE(4,"Ene","Feb","Mar","Abr","May","Jun","Jul","Ago","Sep","Oct","Nov","Dic") -> Abr | G29: 4 | H29: ='PPTO 2027'!$L$16 -> 47500000 | I29: ='PPTO 2027'!$Y$16 -> 52867500 | J29: =I29-H29 -> 5367500 | K29: =ABS(J29) -> 5367500 | L29: =IF(H29=0,"",J29/H29) -> 0.113 | M29: =IFERROR(INDEX(tReal27[[Ene]:[Dic]],MATCH(C29,tReal27[Cuenta],0),4),0) -> 52126000
A30: ='PPTO 2027'!$E$16 -> Comercial | B30: ='PPTO 2027'!$C$16 -> Ingresos operacionales | C30: ='PPTO 2027'!$B$16 -> Servicios de instalación | D30: ='PPTO 2027'!$D$16 -> Ingreso | E30: ='PPTO 2027'!$F$16 -> Ventas | F30: =CHOOSE(5,"Ene","Feb","Mar","Abr","May","Jun","Jul","Ago","Sep","Oct","Nov","Dic") -> May | G30: 5 | H30: ='PPTO 2027'!$M$16 -> 50000000 | I30: ='PPTO 2027'!$Z$16 -> 55650000 | J30: =I30-H30 -> 5650000 | K30: =ABS(J30) -> 5650000 | L30: =IF(H30=0,"",J30/H30) -> 0.113 | M30: =IFERROR(INDEX(tReal27[[Ene]:[Dic]],MATCH(C30,tReal27[Cuenta],0),5),0) -> 55589000
A31: ='PPTO 2027'!$E$16 -> Comercial | B31: ='PPTO 2027'!$C$16 -> Ingresos operacionales | C31: ='PPTO 2027'!$B$16 -> Servicios de instalación | D31: ='PPTO 2027'!$D$16 -> Ingreso | E31: ='PPTO 2027'!$F$16 -> Ventas | F31: =CHOOSE(6,"Ene","Feb","Mar","Abr","May","Jun","Jul","Ago","Sep","Oct","Nov","Dic") -> Jun | G31: 6 | H31: ='PPTO 2027'!$N$16 -> 50000000 | I31: ='PPTO 2027'!$AA$16 -> 55650000 | J31: =I31-H31 -> 5650000 | K31: =ABS(J31) -> 5650000 | L31: =IF(H31=0,"",J31/H31) -> 0.113 | M31: =IFERROR(INDEX(tReal27[[Ene]:[Dic]],MATCH(C31,tReal27[Cuenta],0),6),0) -> 54926000
A32: ='PPTO 2027'!$E$16 -> Comercial | B32: ='PPTO 2027'!$C$16 -> Ingresos operacionales | C32: ='PPTO 2027'!$B$16 -> Servicios de instalación | D32: ='PPTO 2027'!$D$16 -> Ingreso | E32: ='PPTO 2027'!$F$16 -> Ventas | F32: =CHOOSE(7,"Ene","Feb","Mar","Abr","May","Jun","Jul","Ago","Sep","Oct","Nov","Dic") -> Jul | G32: 7 | H32: ='PPTO 2027'!$O$16 -> 50000000 | I32: ='PPTO 2027'!$AB$16 -> 55650000 | J32: =I32-H32 -> 5650000 | K32: =ABS(J32) -> 5650000 | L32: =IF(H32=0,"",J32/H32) -> 0.113 | M32: =IFERROR(INDEX(tReal27[[Ene]:[Dic]],MATCH(C32,tReal27[Cuenta],0),7),0) -> 56436000
A33: ='PPTO 2027'!$E$16 -> Comercial | B33: ='PPTO 2027'!$C$16 -> Ingresos operacionales | C33: ='PPTO 2027'!$B$16 -> Servicios de instalación | D33: ='PPTO 2027'!$D$16 -> Ingreso | E33: ='PPTO 2027'!$F$16 -> Ventas | F33: =CHOOSE(8,"Ene","Feb","Mar","Abr","May","Jun","Jul","Ago","Sep","Oct","Nov","Dic") -> Ago | G33: 8 | H33: ='PPTO 2027'!$P$16 -> 52500000 | I33: ='PPTO 2027'!$AC$16 -> 58432500 | J33: =I33-H33 -> 5932500 | K33: =ABS(J33) -> 5932500 | L33: =IF(H33=0,"",J33/H33) -> 0.113 | M33: =IFERROR(INDEX(tReal27[[Ene]:[Dic]],MATCH(C33,tReal27[Cuenta],0),8),0) -> 57178000
A34: ='PPTO 2027'!$E$16 -> Comercial | B34: ='PPTO 2027'!$C$16 -> Ingresos operacionales | C34: ='PPTO 2027'!$B$16 -> Servicios de instalación | D34: ='PPTO 2027'!$D$16 -> Ingreso | E34: ='PPTO 2027'!$F$16 -> Ventas | F34: =CHOOSE(9,"Ene","Feb","Mar","Abr","May","Jun","Jul","Ago","Sep","Oct","Nov","Dic") -> Sep | G34: 9 | H34: ='PPTO 2027'!$Q$16 -> 50000000 | I34: ='PPTO 2027'!$AD$16 -> 55650000 | J34: =I34-H34 -> 5650000 | K34: =ABS(J34) -> 5650000 | L34: =IF(H34=0,"",J34/H34) -> 0.113 | M34: =IFERROR(INDEX(tReal27[[Ene]:[Dic]],MATCH(C34,tReal27[Cuenta],0),9),0) -> 56871000
A35: ='PPTO 2027'!$E$16 -> Comercial | B35: ='PPTO 2027'!$C$16 -> Ingresos operacionales | C35: ='PPTO 2027'!$B$16 -> Servicios de instalación | D35: ='PPTO 2027'!$D$16 -> Ingreso | E35: ='PPTO 2027'!$F$16 -> Ventas | F35: =CHOOSE(10,"Ene","Feb","Mar","Abr","May","Jun","Jul","Ago","Sep","Oct","Nov","Dic") -> Oct | G35: 10 | H35: ='PPTO 2027'!$R$16 -> 52500000 | I35: ='PPTO 2027'!$AE$16 -> 58432500 | J35: =I35-H35 -> 5932500 | K35: =ABS(J35) -> 5932500 | L35: =IF(H35=0,"",J35/H35) -> 0.113 | M35: =IFERROR(INDEX(tReal27[[Ene]:[Dic]],MATCH(C35,tReal27[Cuenta],0),10),0) -> 57258000
A36: ='PPTO 2027'!$E$16 -> Comercial | B36: ='PPTO 2027'!$C$16 -> Ingresos operacionales | C36: ='PPTO 2027'!$B$16 -> Servicios de instalación | D36: ='PPTO 2027'!$D$16 -> Ingreso | E36: ='PPTO 2027'!$F$16 -> Ventas | F36: =CHOOSE(11,"Ene","Feb","Mar","Abr","May","Jun","Jul","Ago","Sep","Oct","Nov","Dic") -> Nov | G36: 11 | H36: ='PPTO 2027'!$S$16 -> 57500000 | I36: ='PPTO 2027'!$AF$16 -> 63997500 | J36: =I36-H36 -> 6497500 | K36: =ABS(J36) -> 6497500 | L36: =IF(H36=0,"",J36/H36) -> 0.113 | M36: =IFERROR(INDEX(tReal27[[Ene]:[Dic]],MATCH(C36,tReal27[Cuenta],0),11),0) -> 65007000
A37: ='PPTO 2027'!$E$16 -> Comercial | B37: ='PPTO 2027'!$C$16 -> Ingresos operacionales | C37: ='PPTO 2027'!$B$16 -> Servicios de instalación | D37: ='PPTO 2027'!$D$16 -> Ingreso | E37: ='PPTO 2027'!$F$16 -> Ventas | F37: =CHOOSE(12,"Ene","Feb","Mar","Abr","May","Jun","Jul","Ago","Sep","Oct","Nov","Dic") -> Dic | G37: 12 | H37: ='PPTO 2027'!$T$16 -> 60000000 | I37: ='PPTO 2027'!$AG$16 -> 66780000 | J37: =I37-H37 -> 6780000 | K37: =ABS(J37) -> 6780000 | L37: =IF(H37=0,"",J37/H37) -> 0.113 | M37: =IFERROR(INDEX(tReal27[[Ene]:[Dic]],MATCH(C37,tReal27[Cuenta],0),12),0) -> 67211000
A38: ='PPTO 2027'!$E$19 -> Operaciones | B38: ='PPTO 2027'!$C$19 -> Costo de ventas | C38: ='PPTO 2027'!$B$19 -> Costo de mercancía vendida | D38: ='PPTO 2027'!$D$19 -> Costo | E38: ='PPTO 2027'!$F$19 -> Costo variable | F38: =CHOOSE(1,"Ene","Feb","Mar","Abr","May","Jun","Jul","Ago","Sep","Oct","Nov","Dic") -> Ene | G38: 1 | H38: ='PPTO 2027'!$I$19 -> 466700000 | I38: ='PPTO 2027'!$V$19 -> 5.2191061e+08 | J38: =I38-H38 -> 55210610 | K38: =ABS(J38) -> 55210610 | L38: =IF(H38=0,"",J38/H38) -> 0.1183 | M38: =IFERROR(INDEX(tReal27[[Ene]:[Dic]],MATCH(C38,tReal27[Cuenta],0),1),0) -> 505292000
A39: ='PPTO 2027'!$E$19 -> Operaciones | B39: ='PPTO 2027'!$C$19 -> Costo de ventas | C39: ='PPTO 2027'!$B$19 -> Costo de mercancía vendida | D39: ='PPTO 2027'!$D$19 -> Costo | E39: ='PPTO 2027'!$F$19 -> Costo variable | F39: =CHOOSE(2,"Ene","Feb","Mar","Abr","May","Jun","Jul","Ago","Sep","Oct","Nov","Dic") -> Feb | G39: 2 | H39: ='PPTO 2027'!$J$19 -> 495800000 | I39: ='PPTO 2027'!$W$19 -> 554453140 | J39: =I39-H39 -> 58653140 | K39: =ABS(J39) -> 58653140 | L39: =IF(H39=0,"",J39/H39) -> 0.1183 | M39: =IFERROR(INDEX(tReal27[[Ene]:[Dic]],MATCH(C39,tReal27[Cuenta],0),2),0) -> 542318000
A40: ='PPTO 2027'!$E$19 -> Operaciones | B40: ='PPTO 2027'!$C$19 -> Costo de ventas | C40: ='PPTO 2027'!$B$19 -> Costo de mercancía vendida | D40: ='PPTO 2027'!$D$19 -> Costo | E40: ='PPTO 2027'!$F$19 -> Costo variable | F40: =CHOOSE(3,"Ene","Feb","Mar","Abr","May","Jun","Jul","Ago","Sep","Oct","Nov","Dic") -> Mar | G40: 3 | H40: ='PPTO 2027'!$K$19 -> 554200000 | I40: ='PPTO 2027'!$X$19 -> 619761860 | J40: =I40-H40 -> 65561860 | K40: =ABS(J40) -> 65561860 | L40: =IF(H40=0,"",J40/H40) -> 0.1183 | M40: =IFERROR(INDEX(tReal27[[Ene]:[Dic]],MATCH(C40,tReal27[Cuenta],0),3),0) -> 616983000
A41: ='PPTO 2027'!$E$19 -> Operaciones | B41: ='PPTO 2027'!$C$19 -> Costo de ventas | C41: ='PPTO 2027'!$B$19 -> Costo de mercancía vendida | D41: ='PPTO 2027'!$D$19 -> Costo | E41: ='PPTO 2027'!$F$19 -> Costo variable | F41: =CHOOSE(4,"Ene","Feb","Mar","Abr","May","Jun","Jul","Ago","Sep","Oct","Nov","Dic") -> Abr | G41: 4 | H41: ='PPTO 2027'!$L$19 -> 554200000 | I41: ='PPTO 2027'!$Y$19 -> 619761860 | J41: =I41-H41 -> 65561860 | K41: =ABS(J41) -> 65561860 | L41: =IF(H41=0,"",J41/H41) -> 0.1183 | M41: =IFERROR(INDEX(tReal27[[Ene]:[Dic]],MATCH(C41,tReal27[Cuenta],0),4),0) -> 607213000
A42: ='PPTO 2027'!$E$19 -> Operaciones | B42: ='PPTO 2027'!$C$19 -> Costo de ventas | C42: ='PPTO 2027'!$B$19 -> Costo de mercancía vendida | D42: ='PPTO 2027'!$D$19 -> Costo | E42: ='PPTO 2027'!$F$19 -> Costo variable | F42: =CHOOSE(5,"Ene","Feb","Mar","Abr","May","Jun","Jul","Ago","Sep","Oct","Nov","Dic") -> May | G42: 5 | H42: ='PPTO 2027'!$M$19 -> 583300000 | I42: ='PPTO 2027'!$Z$19 -> 652304390 | J42: =I42-H42 -> 69004390 | K42: =ABS(J42) -> 69004390 | L42: =IF(H42=0,"",J42/H42) -> 0.1183 | M42: =IFERROR(INDEX(tReal27[[Ene]:[Dic]],MATCH(C42,tReal27[Cuenta],0),5),0) -> 624229000
A43: ='PPTO 2027'!$E$19 -> Operaciones | B43: ='PPTO 2027'!$C$19 -> Costo de ventas | C43: ='PPTO 2027'!$B$19 -> Costo de mercancía vendida | D43: ='PPTO 2027'!$D$19 -> Costo | E43: ='PPTO 2027'!$F$19 -> Costo variable | F43: =CHOOSE(6,"Ene","Feb","Mar","Abr","May","Jun","Jul","Ago","Sep","Oct","Nov","Dic") -> Jun | G43: 6 | H43: ='PPTO 2027'!$N$19 -> 583300000 | I43: ='PPTO 2027'!$AA$19 -> 652304390 | J43: =I43-H43 -> 69004390 | K43: =ABS(J43) -> 69004390 | L43: =IF(H43=0,"",J43/H43) -> 0.1183 | M43: =IFERROR(INDEX(tReal27[[Ene]:[Dic]],MATCH(C43,tReal27[Cuenta],0),6),0) -> 632414000
A44: ='PPTO 2027'!$E$19 -> Operaciones | B44: ='PPTO 2027'!$C$19 -> Costo de ventas | C44: ='PPTO 2027'!$B$19 -> Costo de mercancía vendida | D44: ='PPTO 2027'!$D$19 -> Costo | E44: ='PPTO 2027'!$F$19 -> Costo variable | F44: =CHOOSE(7,"Ene","Feb","Mar","Abr","May","Jun","Jul","Ago","Sep","Oct","Nov","Dic") -> Jul | G44: 7 | H44: ='PPTO 2027'!$O$19 -> 583300000 | I44: ='PPTO 2027'!$AB$19 -> 652304390 | J44: =I44-H44 -> 69004390 | K44: =ABS(J44) -> 69004390 | L44: =IF(H44=0,"",J44/H44) -> 0.1183 | M44: =IFERROR(INDEX(tReal27[[Ene]:[Dic]],MATCH(C44,tReal27[Cuenta],0),7),0) -> 638716000
A45: ='PPTO 2027'!$E$19 -> Operaciones | B45: ='PPTO 2027'!$C$19 -> Costo de ventas | C45: ='PPTO 2027'!$B$19 -> Costo de mercancía vendida | D45: ='PPTO 2027'!$D$19 -> Costo | E45: ='PPTO 2027'!$F$19 -> Costo variable | F45: =CHOOSE(8,"Ene","Feb","Mar","Abr","May","Jun","Jul","Ago","Sep","Oct","Nov","Dic") -> Ago | G45: 8 | H45: ='PPTO 2027'!$P$19 -> 612500000 | I45: ='PPTO 2027'!$AC$19 -> 684958750 | J45: =I45-H45 -> 72458750 | K45: =ABS(J45) -> 72458750 | L45: =IF(H45=0,"",J45/H45) -> 0.1183 | M45: =IFERROR(INDEX(tReal27[[Ene]:[Dic]],MATCH(C45,tReal27[Cuenta],0),8),0) -> 675199000
A46: ='PPTO 2027'!$E$19 -> Operaciones | B46: ='PPTO 2027'!$C$19 -> Costo de ventas | C46: ='PPTO 2027'!$B$19 -> Costo de mercancía vendida | D46: ='PPTO 2027'!$D$19 -> Costo | E46: ='PPTO 2027'!$F$19 -> Costo variable | F46: =CHOOSE(9,"Ene","Feb","Mar","Abr","May","Jun","Jul","Ago","Sep","Oct","Nov","Dic") -> Sep | G46: 9 | H46: ='PPTO 2027'!$Q$19 -> 583300000 | I46: ='PPTO 2027'!$AD$19 -> 652304390 | J46: =I46-H46 -> 69004390 | K46: =ABS(J46) -> 69004390 | L46: =IF(H46=0,"",J46/H46) -> 0.1183 | M46: =IFERROR(INDEX(tReal27[[Ene]:[Dic]],MATCH(C46,tReal27[Cuenta],0),9),0) -> 643661000
A47: ='PPTO 2027'!$E$19 -> Operaciones | B47: ='PPTO 2027'!$C$19 -> Costo de ventas | C47: ='PPTO 2027'!$B$19 -> Costo de mercancía vendida | D47: ='PPTO 2027'!$D$19 -> Costo | E47: ='PPTO 2027'!$F$19 -> Costo variable | F47: =CHOOSE(10,"Ene","Feb","Mar","Abr","May","Jun","Jul","Ago","Sep","Oct","Nov","Dic") -> Oct | G47: 10 | H47: ='PPTO 2027'!$R$19 -> 612500000 | I47: ='PPTO 2027'!$AE$19 -> 684958750 | J47: =I47-H47 -> 72458750 | K47: =ABS(J47) -> 72458750 | L47: =IF(H47=0,"",J47/H47) -> 0.1183 | M47: =IFERROR(INDEX(tReal27[[Ene]:[Dic]],MATCH(C47,tReal27[Cuenta],0),10),0) -> 657894000
A48: ='PPTO 2027'!$E$19 -> Operaciones | B48: ='PPTO 2027'!$C$19 -> Costo de ventas | C48: ='PPTO 2027'!$B$19 -> Costo de mercancía vendida | D48: ='PPTO 2027'!$D$19 -> Costo | E48: ='PPTO 2027'!$F$19 -> Costo variable | F48: =CHOOSE(11,"Ene","Feb","Mar","Abr","May","Jun","Jul","Ago","Sep","Oct","Nov","Dic") -> Nov | G48: 11 | H48: ='PPTO 2027'!$S$19 -> 670800000 | I48: ='PPTO 2027'!$AF$19 -> 750155640 | J48: =I48-H48 -> 79355640 | K48: =ABS(J48) -> 79355640 | L48: =IF(H48=0,"",J48/H48) -> 0.1183 | M48: =IFERROR(INDEX(tReal27[[Ene]:[Dic]],MATCH(C48,tReal27[Cuenta],0),11),0) -> 734942000
A49: ='PPTO 2027'!$E$19 -> Operaciones | B49: ='PPTO 2027'!$C$19 -> Costo de ventas | C49: ='PPTO 2027'!$B$19 -> Costo de mercancía vendida | D49: ='PPTO 2027'!$D$19 -> Costo | E49: ='PPTO 2027'!$F$19 -> Costo variable | F49: =CHOOSE(12,"Ene","Feb","Mar","Abr","May","Jun","Jul","Ago","Sep","Oct","Nov","Dic") -> Dic | G49: 12 | H49: ='PPTO 2027'!$T$19 -> 700100000 | I49: ='PPTO 2027'!$AG$19 -> 782921830 | J49: =I49-H49 -> 82821830 | K49: =ABS(J49) -> 82821830 | L49: =IF(H49=0,"",J49/H49) -> 0.1183 | M49: =IFERROR(INDEX(tReal27[[Ene]:[Dic]],MATCH(C49,tReal27[Cuenta],0),12),0) -> 753382000
A50: ='PPTO 2027'!$E$20 -> Operaciones | B50: ='PPTO 2027'!$C$20 -> Costo de ventas | C50: ='PPTO 2027'!$B$20 -> Fletes de compra | D50: ='PPTO 2027'!$D$20 -> Costo | E50: ='PPTO 2027'!$F$20 -> Costo variable | F50: =CHOOSE(1,"Ene","Feb","Mar","Abr","May","Jun","Jul","Ago","Sep","Oct","Nov","Dic") -> Ene | G50: 1 | H50: ='PPTO 2027'!$I$20 -> 32000000 | I50: ='PPTO 2027'!$V$20 -> 35785600 | J50: =I50-H50 -> 3785600 | K50: =ABS(J50) -> 3785600 | L50: =IF(H50=0,"",J50/H50) -> 0.1183 | M50: =IFERROR(INDEX(tReal27[[Ene]:[Dic]],MATCH(C50,tReal27[Cuenta],0),1),0) -> 38643000
A51: ='PPTO 2027'!$E$20 -> Operaciones | B51: ='PPTO 2027'!$C$20 -> Costo de ventas | C51: ='PPTO 2027'!$B$20 -> Fletes de compra | D51: ='PPTO 2027'!$D$20 -> Costo | E51: ='PPTO 2027'!$F$20 -> Costo variable | F51: =CHOOSE(2,"Ene","Feb","Mar","Abr","May","Jun","Jul","Ago","Sep","Oct","Nov","Dic") -> Feb | G51: 2 | H51: ='PPTO 2027'!$J$20 -> 34000000 | I51: ='PPTO 2027'!$W$20 -> 38022200 | J51: =I51-H51 -> 4022200 | K51: =ABS(J51) -> 4022200 | L51: =IF(H51=0,"",J51/H51) -> 0.1183 | M51: =IFERROR(INDEX(tReal27[[Ene]:[Dic]],MATCH(C51,tReal27[Cuenta],0),2),0) -> 40855000
A52: ='PPTO 2027'!$E$20 -> Operaciones | B52: ='PPTO 2027'!$C$20 -> Costo de ventas | C52: ='PPTO 2027'!$B$20 -> Fletes de compra | D52: ='PPTO 2027'!$D$20 -> Costo | E52: ='PPTO 2027'!$F$20 -> Costo variable | F52: =CHOOSE(3,"Ene","Feb","Mar","Abr","May","Jun","Jul","Ago","Sep","Oct","Nov","Dic") -> Mar | G52: 3 | H52: ='PPTO 2027'!$K$20 -> 38000000 | I52: ='PPTO 2027'!$X$20 -> 42495400 | J52: =I52-H52 -> 4495400 | K52: =ABS(J52) -> 4495400 | L52: =IF(H52=0,"",J52/H52) -> 0.1183 | M52: =IFERROR(INDEX(tReal27[[Ene]:[Dic]],MATCH(C52,tReal27[Cuenta],0),3),0) -> 45998000
A53: ='PPTO 2027'!$E$20 -> Operaciones | B53: ='PPTO 2027'!$C$20 -> Costo de ventas | C53: ='PPTO 2027'!$B$20 -> Fletes de compra | D53: ='PPTO 2027'!$D$20 -> Costo | E53: ='PPTO 2027'!$F$20 -> Costo variable | F53: =CHOOSE(4,"Ene","Feb","Mar","Abr","May","Jun","Jul","Ago","Sep","Oct","Nov","Dic") -> Abr | G53: 4 | H53: ='PPTO 2027'!$L$20 -> 38000000 | I53: ='PPTO 2027'!$Y$20 -> 42495400 | J53: =I53-H53 -> 4495400 | K53: =ABS(J53) -> 4495400 | L53: =IF(H53=0,"",J53/H53) -> 0.1183 | M53: =IFERROR(INDEX(tReal27[[Ene]:[Dic]],MATCH(C53,tReal27[Cuenta],0),4),0) -> 45589000
A54: ='PPTO 2027'!$E$20 -> Operaciones | B54: ='PPTO 2027'!$C$20 -> Costo de ventas | C54: ='PPTO 2027'!$B$20 -> Fletes de compra | D54: ='PPTO 2027'!$D$20 -> Costo | E54: ='PPTO 2027'!$F$20 -> Costo variable | F54: =CHOOSE(5,"Ene","Feb","Mar","Abr","May","Jun","Jul","Ago","Sep","Oct","Nov","Dic") -> May | G54: 5 | H54: ='PPTO 2027'!$M$20 -> 40000000 | I54: ='PPTO 2027'!$Z$20 -> 44732000 | J54: =I54-H54 -> 4732000 | K54: =ABS(J54) -> 4732000 | L54: =IF(H54=0,"",J54/H54) -> 0.1183 | M54: =IFERROR(INDEX(tReal27[[Ene]:[Dic]],MATCH(C54,tReal27[Cuenta],0),5),0) -> 47318000
A55: ='PPTO 2027'!$E$20 -> Operaciones | B55: ='PPTO 2027'!$C$20 -> Costo de ventas | C55: ='PPTO 2027'!$B$20 -> Fletes de compra | D55: ='PPTO 2027'!$D$20 -> Costo | E55: ='PPTO 2027'!$F$20 -> Costo variable | F55: =CHOOSE(6,"Ene","Feb","Mar","Abr","May","Jun","Jul","Ago","Sep","Oct","Nov","Dic") -> Jun | G55: 6 | H55: ='PPTO 2027'!$N$20 -> 40000000 | I55: ='PPTO 2027'!$AA$20 -> 44732000 | J55: =I55-H55 -> 4732000 | K55: =ABS(J55) -> 4732000 | L55: =IF(H55=0,"",J55/H55) -> 0.1183 | M55: =IFERROR(INDEX(tReal27[[Ene]:[Dic]],MATCH(C55,tReal27[Cuenta],0),6),0) -> 47281000
A56: ='PPTO 2027'!$E$20 -> Operaciones | B56: ='PPTO 2027'!$C$20 -> Costo de ventas | C56: ='PPTO 2027'!$B$20 -> Fletes de compra | D56: ='PPTO 2027'!$D$20 -> Costo | E56: ='PPTO 2027'!$F$20 -> Costo variable | F56: =CHOOSE(7,"Ene","Feb","Mar","Abr","May","Jun","Jul","Ago","Sep","Oct","Nov","Dic") -> Jul | G56: 7 | H56: ='PPTO 2027'!$O$20 -> 40000000 | I56: ='PPTO 2027'!$AB$20 -> 44732000 | J56: =I56-H56 -> 4732000 | K56: =ABS(J56) -> 4732000 | L56: =IF(H56=0,"",J56/H56) -> 0.1183 | M56: =IFERROR(INDEX(tReal27[[Ene]:[Dic]],MATCH(C56,tReal27[Cuenta],0),7),0) -> 47999000
A57: ='PPTO 2027'!$E$20 -> Operaciones | B57: ='PPTO 2027'!$C$20 -> Costo de ventas | C57: ='PPTO 2027'!$B$20 -> Fletes de compra | D57: ='PPTO 2027'!$D$20 -> Costo | E57: ='PPTO 2027'!$F$20 -> Costo variable | F57: =CHOOSE(8,"Ene","Feb","Mar","Abr","May","Jun","Jul","Ago","Sep","Oct","Nov","Dic") -> Ago | G57: 8 | H57: ='PPTO 2027'!$P$20 -> 42000000 | I57: ='PPTO 2027'!$AC$20 -> 46968600 | J57: =I57-H57 -> 4968600 | K57: =ABS(J57) -> 4968600 | L57: =IF(H57=0,"",J57/H57) -> 0.1183 | M57: =IFERROR(INDEX(tReal27[[Ene]:[Dic]],MATCH(C57,tReal27[Cuenta],0),8),0) -> 50347000
A58: ='PPTO 2027'!$E$20 -> Operaciones | B58: ='PPTO 2027'!$C$20 -> Costo de ventas | C58: ='PPTO 2027'!$B$20 -> Fletes de compra | D58: ='PPTO 2027'!$D$20 -> Costo | E58: ='PPTO 2027'!$F$20 -> Costo variable | F58: =CHOOSE(9,"Ene","Feb","Mar","Abr","May","Jun","Jul","Ago","Sep","Oct","Nov","Dic") -> Sep | G58: 9 | H58: ='PPTO 2027'!$Q$20 -> 40000000 | I58: ='PPTO 2027'!$AD$20 -> 44732000 | J58: =I58-H58 -> 4732000 | K58: =ABS(J58) -> 4732000 | L58: =IF(H58=0,"",J58/H58) -> 0.1183 | M58: =IFERROR(INDEX(tReal27[[Ene]:[Dic]],MATCH(C58,tReal27[Cuenta],0),9),0) -> 47220000
A59: ='PPTO 2027'!$E$20 -> Operaciones | B59: ='PPTO 2027'!$C$20 -> Costo de ventas | C59: ='PPTO 2027'!$B$20 -> Fletes de compra | D59: ='PPTO 2027'!$D$20 -> Costo | E59: ='PPTO 2027'!$F$20 -> Costo variable | F59: =CHOOSE(10,"Ene","Feb","Mar","Abr","May","Jun","Jul","Ago","Sep","Oct","Nov","Dic") -> Oct | G59: 10 | H59: ='PPTO 2027'!$R$20 -> 42000000 | I59: ='PPTO 2027'!$AE$20 -> 46968600 | J59: =I59-H59 -> 4968600 | K59: =ABS(J59) -> 4968600 | L59: =IF(H59=0,"",J59/H59) -> 0.1183 | M59: =IFERROR(INDEX(tReal27[[Ene]:[Dic]],MATCH(C59,tReal27[Cuenta],0),10),0) -> 49564000
A60: ='PPTO 2027'!$E$20 -> Operaciones | B60: ='PPTO 2027'!$C$20 -> Costo de ventas | C60: ='PPTO 2027'!$B$20 -> Fletes de compra | D60: ='PPTO 2027'!$D$20 -> Costo | E60: ='PPTO 2027'!$F$20 -> Costo variable | F60: =CHOOSE(11,"Ene","Feb","Mar","Abr","May","Jun","Jul","Ago","Sep","Oct","Nov","Dic") -> Nov | G60: 11 | H60: ='PPTO 2027'!$S$20 -> 46000000 | I60: ='PPTO 2027'!$AF$20 -> 51441800 | J60: =I60-H60 -> 5441800 | K60: =ABS(J60) -> 5441800 | L60: =IF(H60=0,"",J60/H60) -> 0.1183 | M60: =IFERROR(INDEX(tReal27[[Ene]:[Dic]],MATCH(C60,tReal27[Cuenta],0),11),0) -> 54976000
A61: ='PPTO 2027'!$E$20 -> Operaciones | B61: ='PPTO 2027'!$C$20 -> Costo de ventas | C61: ='PPTO 2027'!$B$20 -> Fletes de compra | D61: ='PPTO 2027'!$D$20 -> Costo | E61: ='PPTO 2027'!$F$20 -> Costo variable | F61: =CHOOSE(12,"Ene","Feb","Mar","Abr","May","Jun","Jul","Ago","Sep","Oct","Nov","Dic") -> Dic | G61: 12 | H61: ='PPTO 2027'!$T$20 -> 48000000 | I61: ='PPTO 2027'!$AG$20 -> 53678400 | J61: =I61-H61 -> 5678400 | K61: =ABS(J61) -> 5678400 | L61: =IF(H61=0,"",J61/H61) -> 0.1183 | M61: =IFERROR(INDEX(tReal27[[Ene]:[Dic]],MATCH(C61,tReal27[Cuenta],0),12),0) -> 57551000
A62: ='PPTO 2027'!$E$21 -> Operaciones | B62: ='PPTO 2027'!$C$21 -> Costo de ventas | C62: ='PPTO 2027'!$B$21 -> Mermas y averías | D62: ='PPTO 2027'!$D$21 -> Costo | E62: ='PPTO 2027'!$F$21 -> Costo variable | F62: =CHOOSE(1,"Ene","Feb","Mar","Abr","May","Jun","Jul","Ago","Sep","Oct","Nov","Dic") -> Ene | G62: 1 | H62: ='PPTO 2027'!$I$21 -> 10000000 | I62: ='PPTO 2027'!$V$21 -> 11183000 | J62: =I62-H62 -> 1183000 | K62: =ABS(J62) -> 1183000 | L62: =IF(H62=0,"",J62/H62) -> 0.1183 | M62: =IFERROR(INDEX(tReal27[[Ene]:[Dic]],MATCH(C62,tReal27[Cuenta],0),1),0) -> 11415000
A63: ='PPTO 2027'!$E$21 -> Operaciones | B63: ='PPTO 2027'!$C$21 -> Costo de ventas | C63: ='PPTO 2027'!$B$21 -> Mermas y averías | D63: ='PPTO 2027'!$D$21 -> Costo | E63: ='PPTO 2027'!$F$21 -> Costo variable | F63: =CHOOSE(2,"Ene","Feb","Mar","Abr","May","Jun","Jul","Ago","Sep","Oct","Nov","Dic") -> Feb | G63: 2 | H63: ='PPTO 2027'!$J$21 -> 10600000 | I63: ='PPTO 2027'!$W$21 -> 11853980 | J63: =I63-H63 -> 1253980 | K63: =ABS(J63) -> 1253980 | L63: =IF(H63=0,"",J63/H63) -> 0.1183 | M63: =IFERROR(INDEX(tReal27[[Ene]:[Dic]],MATCH(C63,tReal27[Cuenta],0),2),0) -> 11898000
A64: ='PPTO 2027'!$E$21 -> Operaciones | B64: ='PPTO 2027'!$C$21 -> Costo de ventas | C64: ='PPTO 2027'!$B$21 -> Mermas y averías | D64: ='PPTO 2027'!$D$21 -> Costo | E64: ='PPTO 2027'!$F$21 -> Costo variable | F64: =CHOOSE(3,"Ene","Feb","Mar","Abr","May","Jun","Jul","Ago","Sep","Oct","Nov","Dic") -> Mar | G64: 3 | H64: ='PPTO 2027'!$K$21 -> 11900000 | I64: ='PPTO 2027'!$X$21 -> 13307770 | J64: =I64-H64 -> 1407770 | K64: =ABS(J64) -> 1407770 | L64: =IF(H64=0,"",J64/H64) -> 0.1183 | M64: =IFERROR(INDEX(tReal27[[Ene]:[Dic]],MATCH(C64,tReal27[Cuenta],0),3),0) -> 13149000
A65: ='PPTO 2027'!$E$21 -> Operaciones | B65: ='PPTO 2027'!$C$21 -> Costo de ventas | C65: ='PPTO 2027'!$B$21 -> Mermas y averías | D65: ='PPTO 2027'!$D$21 -> Costo | E65: ='PPTO 2027'!$F$21 -> Costo variable | F65: =CHOOSE(4,"Ene","Feb","Mar","Abr","May","Jun","Jul","Ago","Sep","Oct","Nov","Dic") -> Abr | G65: 4 | H65: ='PPTO 2027'!$L$21 -> 11900000 | I65: ='PPTO 2027'!$Y$21 -> 13307770 | J65: =I65-H65 -> 1407770 | K65: =ABS(J65) -> 1407770 | L65: =IF(H65=0,"",J65/H65) -> 0.1183 | M65: =IFERROR(INDEX(tReal27[[Ene]:[Dic]],MATCH(C65,tReal27[Cuenta],0),4),0) -> 13128000
A66: ='PPTO 2027'!$E$21 -> Operaciones | B66: ='PPTO 2027'!$C$21 -> Costo de ventas | C66: ='PPTO 2027'!$B$21 -> Mermas y averías | D66: ='PPTO 2027'!$D$21 -> Costo | E66: ='PPTO 2027'!$F$21 -> Costo variable | F66: =CHOOSE(5,"Ene","Feb","Mar","Abr","May","Jun","Jul","Ago","Sep","Oct","Nov","Dic") -> May | G66: 5 | H66: ='PPTO 2027'!$M$21 -> 12500000 | I66: ='PPTO 2027'!$Z$21 -> 13978750 | J66: =I66-H66 -> 1478750 | K66: =ABS(J66) -> 1478750 | L66: =IF(H66=0,"",J66/H66) -> 0.1183 | M66: =IFERROR(INDEX(tReal27[[Ene]:[Dic]],MATCH(C66,tReal27[Cuenta],0),5),0) -> 13589000
A67: ='PPTO 2027'!$E$21 -> Operaciones | B67: ='PPTO 2027'!$C$21 -> Costo de ventas | C67: ='PPTO 2027'!$B$21 -> Mermas y averías | D67: ='PPTO 2027'!$D$21 -> Costo | E67: ='PPTO 2027'!$F$21 -> Costo variable | F67: =CHOOSE(6,"Ene","Feb","Mar","Abr","May","Jun","Jul","Ago","Sep","Oct","Nov","Dic") -> Jun | G67: 6 | H67: ='PPTO 2027'!$N$21 -> 12500000 | I67: ='PPTO 2027'!$AA$21 -> 13978750 | J67: =I67-H67 -> 1478750 | K67: =ABS(J67) -> 1478750 | L67: =IF(H67=0,"",J67/H67) -> 0.1183 | M67: =IFERROR(INDEX(tReal27[[Ene]:[Dic]],MATCH(C67,tReal27[Cuenta],0),6),0) -> 13975000
A68: ='PPTO 2027'!$E$21 -> Operaciones | B68: ='PPTO 2027'!$C$21 -> Costo de ventas | C68: ='PPTO 2027'!$B$21 -> Mermas y averías | D68: ='PPTO 2027'!$D$21 -> Costo | E68: ='PPTO 2027'!$F$21 -> Costo variable | F68: =CHOOSE(7,"Ene","Feb","Mar","Abr","May","Jun","Jul","Ago","Sep","Oct","Nov","Dic") -> Jul | G68: 7 | H68: ='PPTO 2027'!$O$21 -> 12500000 | I68: ='PPTO 2027'!$AB$21 -> 13978750 | J68: =I68-H68 -> 1478750 | K68: =ABS(J68) -> 1478750 | L68: =IF(H68=0,"",J68/H68) -> 0.1183 | M68: =IFERROR(INDEX(tReal27[[Ene]:[Dic]],MATCH(C68,tReal27[Cuenta],0),7),0) -> 13599000
A69: ='PPTO 2027'!$E$21 -> Operaciones | B69: ='PPTO 2027'!$C$21 -> Costo de ventas | C69: ='PPTO 2027'!$B$21 -> Mermas y averías | D69: ='PPTO 2027'!$D$21 -> Costo | E69: ='PPTO 2027'!$F$21 -> Costo variable | F69: =CHOOSE(8,"Ene","Feb","Mar","Abr","May","Jun","Jul","Ago","Sep","Oct","Nov","Dic") -> Ago | G69: 8 | H69: ='PPTO 2027'!$P$21 -> 13100000 | I69: ='PPTO 2027'!$AC$21 -> 14649730 | J69: =I69-H69 -> 1549730 | K69: =ABS(J69) -> 1549730 | L69: =IF(H69=0,"",J69/H69) -> 0.1183 | M69: =IFERROR(INDEX(tReal27[[Ene]:[Dic]],MATCH(C69,tReal27[Cuenta],0),8),0) -> 14745000
A70: ='PPTO 2027'!$E$21 -> Operaciones | B70: ='PPTO 2027'!$C$21 -> Costo de ventas | C70: ='PPTO 2027'!$B$21 -> Mermas y averías | D70: ='PPTO 2027'!$D$21 -> Costo | E70: ='PPTO 2027'!$F$21 -> Costo variable | F70: =CHOOSE(9,"Ene","Feb","Mar","Abr","May","Jun","Jul","Ago","Sep","Oct","Nov","Dic") -> Sep | G70: 9 | H70: ='PPTO 2027'!$Q$21 -> 12500000 | I70: ='PPTO 2027'!$AD$21 -> 13978750 | J70: =I70-H70 -> 1478750 | K70: =ABS(J70) -> 1478750 | L70: =IF(H70=0,"",J70/H70) -> 0.1183 | M70: =IFERROR(INDEX(tReal27[[Ene]:[Dic]],MATCH(C70,tReal27[Cuenta],0),9),0) -> 13881000
A71: ='PPTO 2027'!$E$21 -> Operaciones | B71: ='PPTO 2027'!$C$21 -> Costo de ventas | C71: ='PPTO 2027'!$B$21 -> Mermas y averías | D71: ='PPTO 2027'!$D$21 -> Costo | E71: ='PPTO 2027'!$F$21 -> Costo variable | F71: =CHOOSE(10,"Ene","Feb","Mar","Abr","May","Jun","Jul","Ago","Sep","Oct","Nov","Dic") -> Oct | G71: 10 | H71: ='PPTO 2027'!$R$21 -> 13100000 | I71: ='PPTO 2027'!$AE$21 -> 14649730 | J71: =I71-H71 -> 1549730 | K71: =ABS(J71) -> 1549730 | L71: =IF(H71=0,"",J71/H71) -> 0.1183 | M71: =IFERROR(INDEX(tReal27[[Ene]:[Dic]],MATCH(C71,tReal27[Cuenta],0),10),0) -> 14746000
A72: ='PPTO 2027'!$E$21 -> Operaciones | B72: ='PPTO 2027'!$C$21 -> Costo de ventas | C72: ='PPTO 2027'!$B$21 -> Mermas y averías | D72: ='PPTO 2027'!$D$21 -> Costo | E72: ='PPTO 2027'!$F$21 -> Costo variable | F72: =CHOOSE(11,"Ene","Feb","Mar","Abr","May","Jun","Jul","Ago","Sep","Oct","Nov","Dic") -> Nov | G72: 11 | H72: ='PPTO 2027'!$S$21 -> 14400000 | I72: ='PPTO 2027'!$AF$21 -> 16103520 | J72: =I72-H72 -> 1703520 | K72: =ABS(J72) -> 1703520 | L72: =IF(H72=0,"",J72/H72) -> 0.1183 | M72: =IFERROR(INDEX(tReal27[[Ene]:[Dic]],MATCH(C72,tReal27[Cuenta],0),11),0) -> 15926000
A73: ='PPTO 2027'!$E$21 -> Operaciones | B73: ='PPTO 2027'!$C$21 -> Costo de ventas | C73: ='PPTO 2027'!$B$21 -> Mermas y averías | D73: ='PPTO 2027'!$D$21 -> Costo | E73: ='PPTO 2027'!$F$21 -> Costo variable | F73: =CHOOSE(12,"Ene","Feb","Mar","Abr","May","Jun","Jul","Ago","Sep","Oct","Nov","Dic") -> Dic | G73: 12 | H73: ='PPTO 2027'!$T$21 -> 15000000 | I73: ='PPTO 2027'!$AG$21 -> 16774500 | J73: =I73-H73 -> 1774500 | K73: =ABS(J73) -> 1774500 | L73: =IF(H73=0,"",J73/H73) -> 0.1183 | M73: =IFERROR(INDEX(tReal27[[Ene]:[Dic]],MATCH(C73,tReal27[Cuenta],0),12),0) -> 16801000
A74: ='PPTO 2027'!$E$27 -> Administración | B74: ='PPTO 2027'!$C$27 -> Gastos de administración | C74: ='PPTO 2027'!$B$27 -> Nómina administrativa | D74: ='PPTO 2027'!$D$27 -> Gasto | E74: ='PPTO 2027'!$F$27 -> Nómina | F74: =CHOOSE(1,"Ene","Feb","Mar","Abr","May","Jun","Jul","Ago","Sep","Oct","Nov","Dic") -> Ene | G74: 1 | H74: ='PPTO 2027'!$I$27 -> 50000000 | I74: ='PPTO 2027'!$V$27 -> 53500000 | J74: =I74-H74 -> 3500000 | K74: =ABS(J74) -> 3500000 | L74: =IF(H74=0,"",J74/H74) -> 0.07 | M74: =IFERROR(INDEX(tReal27[[Ene]:[Dic]],MATCH(C74,tReal27[Cuenta],0),1),0) -> 54372000
A75: ='PPTO 2027'!$E$27 -> Administración | B75: ='PPTO 2027'!$C$27 -> Gastos de administración | C75: ='PPTO 2027'!$B$27 -> Nómina administrativa | D75: ='PPTO 2027'!$D$27 -> Gasto | E75: ='PPTO 2027'!$F$27 -> Nómina | F75: =CHOOSE(2,"Ene","Feb","Mar","Abr","May","Jun","Jul","Ago","Sep","Oct","Nov","Dic") -> Feb | G75: 2 | H75: ='PPTO 2027'!$J$27 -> 50000000 | I75: ='PPTO 2027'!$W$27 -> 53500000 | J75: =I75-H75 -> 3500000 | K75: =ABS(J75) -> 3500000 | L75: =IF(H75=0,"",J75/H75) -> 0.07 | M75: =IFERROR(INDEX(tReal27[[Ene]:[Dic]],MATCH(C75,tReal27[Cuenta],0),2),0) -> 53128000
A76: ='PPTO 2027'!$E$27 -> Administración | B76: ='PPTO 2027'!$C$27 -> Gastos de administración | C76: ='PPTO 2027'!$B$27 -> Nómina administrativa | D76: ='PPTO 2027'!$D$27 -> Gasto | E76: ='PPTO 2027'!$F$27 -> Nómina | F76: =CHOOSE(3,"Ene","Feb","Mar","Abr","May","Jun","Jul","Ago","Sep","Oct","Nov","Dic") -> Mar | G76: 3 | H76: ='PPTO 2027'!$K$27 -> 50000000 | I76: ='PPTO 2027'!$X$27 -> 53500000 | J76: =I76-H76 -> 3500000 | K76: =ABS(J76) -> 3500000 | L76: =IF(H76=0,"",J76/H76) -> 0.07 | M76: =IFERROR(INDEX(tReal27[[Ene]:[Dic]],MATCH(C76,tReal27[Cuenta],0),3),0) -> 53226000
A77: ='PPTO 2027'!$E$27 -> Administración | B77: ='PPTO 2027'!$C$27 -> Gastos de administración | C77: ='PPTO 2027'!$B$27 -> Nómina administrativa | D77: ='PPTO 2027'!$D$27 -> Gasto | E77: ='PPTO 2027'!$F$27 -> Nómina | F77: =CHOOSE(4,"Ene","Feb","Mar","Abr","May","Jun","Jul","Ago","Sep","Oct","Nov","Dic") -> Abr | G77: 4 | H77: ='PPTO 2027'!$L$27 -> 50000000 | I77: ='PPTO 2027'!$Y$27 -> 53500000 | J77: =I77-H77 -> 3500000 | K77: =ABS(J77) -> 3500000 | L77: =IF(H77=0,"",J77/H77) -> 0.07 | M77: =IFERROR(INDEX(tReal27[[Ene]:[Dic]],MATCH(C77,tReal27[Cuenta],0),4),0) -> 53441000
A78: ='PPTO 2027'!$E$27 -> Administración | B78: ='PPTO 2027'!$C$27 -> Gastos de administración | C78: ='PPTO 2027'!$B$27 -> Nómina administrativa | D78: ='PPTO 2027'!$D$27 -> Gasto | E78: ='PPTO 2027'!$F$27 -> Nómina | F78: =CHOOSE(5,"Ene","Feb","Mar","Abr","May","Jun","Jul","Ago","Sep","Oct","Nov","Dic") -> May | G78: 5 | H78: ='PPTO 2027'!$M$27 -> 50000000 | I78: ='PPTO 2027'!$Z$27 -> 53500000 | J78: =I78-H78 -> 3500000 | K78: =ABS(J78) -> 3500000 | L78: =IF(H78=0,"",J78/H78) -> 0.07 | M78: =IFERROR(INDEX(tReal27[[Ene]:[Dic]],MATCH(C78,tReal27[Cuenta],0),5),0) -> 54341000
A79: ='PPTO 2027'!$E$27 -> Administración | B79: ='PPTO 2027'!$C$27 -> Gastos de administración | C79: ='PPTO 2027'!$B$27 -> Nómina administrativa | D79: ='PPTO 2027'!$D$27 -> Gasto | E79: ='PPTO 2027'!$F$27 -> Nómina | F79: =CHOOSE(6,"Ene","Feb","Mar","Abr","May","Jun","Jul","Ago","Sep","Oct","Nov","Dic") -> Jun | G79: 6 | H79: ='PPTO 2027'!$N$27 -> 50000000 | I79: ='PPTO 2027'!$AA$27 -> 53500000 | J79: =I79-H79 -> 3500000 | K79: =ABS(J79) -> 3500000 | L79: =IF(H79=0,"",J79/H79) -> 0.07 | M79: =IFERROR(INDEX(tReal27[[Ene]:[Dic]],MATCH(C79,tReal27[Cuenta],0),6),0) -> 51809000
A80: ='PPTO 2027'!$E$27 -> Administración | B80: ='PPTO 2027'!$C$27 -> Gastos de administración | C80: ='PPTO 2027'!$B$27 -> Nómina administrativa | D80: ='PPTO 2027'!$D$27 -> Gasto | E80: ='PPTO 2027'!$F$27 -> Nómina | F80: =CHOOSE(7,"Ene","Feb","Mar","Abr","May","Jun","Jul","Ago","Sep","Oct","Nov","Dic") -> Jul | G80: 7 | H80: ='PPTO 2027'!$O$27 -> 50000000 | I80: ='PPTO 2027'!$AB$27 -> 53500000 | J80: =I80-H80 -> 3500000 | K80: =ABS(J80) -> 3500000 | L80: =IF(H80=0,"",J80/H80) -> 0.07 | M80: =IFERROR(INDEX(tReal27[[Ene]:[Dic]],MATCH(C80,tReal27[Cuenta],0),7),0) -> 53941000
A81: ='PPTO 2027'!$E$27 -> Administración | B81: ='PPTO 2027'!$C$27 -> Gastos de administración | C81: ='PPTO 2027'!$B$27 -> Nómina administrativa | D81: ='PPTO 2027'!$D$27 -> Gasto | E81: ='PPTO 2027'!$F$27 -> Nómina | F81: =CHOOSE(8,"Ene","Feb","Mar","Abr","May","Jun","Jul","Ago","Sep","Oct","Nov","Dic") -> Ago | G81: 8 | H81: ='PPTO 2027'!$P$27 -> 50000000 | I81: ='PPTO 2027'!$AC$27 -> 53500000 | J81: =I81-H81 -> 3500000 | K81: =ABS(J81) -> 3500000 | L81: =IF(H81=0,"",J81/H81) -> 0.07 | M81: =IFERROR(INDEX(tReal27[[Ene]:[Dic]],MATCH(C81,tReal27[Cuenta],0),8),0) -> 54309000
A82: ='PPTO 2027'!$E$27 -> Administración | B82: ='PPTO 2027'!$C$27 -> Gastos de administración | C82: ='PPTO 2027'!$B$27 -> Nómina administrativa | D82: ='PPTO 2027'!$D$27 -> Gasto | E82: ='PPTO 2027'!$F$27 -> Nómina | F82: =CHOOSE(9,"Ene","Feb","Mar","Abr","May","Jun","Jul","Ago","Sep","Oct","Nov","Dic") -> Sep | G82: 9 | H82: ='PPTO 2027'!$Q$27 -> 50000000 | I82: ='PPTO 2027'!$AD$27 -> 53500000 | J82: =I82-H82 -> 3500000 | K82: =ABS(J82) -> 3500000 | L82: =IF(H82=0,"",J82/H82) -> 0.07 | M82: =IFERROR(INDEX(tReal27[[Ene]:[Dic]],MATCH(C82,tReal27[Cuenta],0),9),0) -> 53288000
A83: ='PPTO 2027'!$E$27 -> Administración | B83: ='PPTO 2027'!$C$27 -> Gastos de administración | C83: ='PPTO 2027'!$B$27 -> Nómina administrativa | D83: ='PPTO 2027'!$D$27 -> Gasto | E83: ='PPTO 2027'!$F$27 -> Nómina | F83: =CHOOSE(10,"Ene","Feb","Mar","Abr","May","Jun","Jul","Ago","Sep","Oct","Nov","Dic") -> Oct | G83: 10 | H83: ='PPTO 2027'!$R$27 -> 50000000 | I83: ='PPTO 2027'!$AE$27 -> 53500000 | J83: =I83-H83 -> 3500000 | K83: =ABS(J83) -> 3500000 | L83: =IF(H83=0,"",J83/H83) -> 0.07 | M83: =IFERROR(INDEX(tReal27[[Ene]:[Dic]],MATCH(C83,tReal27[Cuenta],0),10),0) -> 53215000
A84: ='PPTO 2027'!$E$27 -> Administración | B84: ='PPTO 2027'!$C$27 -> Gastos de administración | C84: ='PPTO 2027'!$B$27 -> Nómina administrativa | D84: ='PPTO 2027'!$D$27 -> Gasto | E84: ='PPTO 2027'!$F$27 -> Nómina | F84: =CHOOSE(11,"Ene","Feb","Mar","Abr","May","Jun","Jul","Ago","Sep","Oct","Nov","Dic") -> Nov | G84: 11 | H84: ='PPTO 2027'!$S$27 -> 50000000 | I84: ='PPTO 2027'!$AF$27 -> 53500000 | J84: =I84-H84 -> 3500000 | K84: =ABS(J84) -> 3500000 | L84: =IF(H84=0,"",J84/H84) -> 0.07 | M84: =IFERROR(INDEX(tReal27[[Ene]:[Dic]],MATCH(C84,tReal27[Cuenta],0),11),0) -> 53230000
A85: ='PPTO 2027'!$E$27 -> Administración | B85: ='PPTO 2027'!$C$27 -> Gastos de administración | C85: ='PPTO 2027'!$B$27 -> Nómina administrativa | D85: ='PPTO 2027'!$D$27 -> Gasto | E85: ='PPTO 2027'!$F$27 -> Nómina | F85: =CHOOSE(12,"Ene","Feb","Mar","Abr","May","Jun","Jul","Ago","Sep","Oct","Nov","Dic") -> Dic | G85: 12 | H85: ='PPTO 2027'!$T$27 -> 50000000 | I85: ='PPTO 2027'!$AG$27 -> 53500000 | J85: =I85-H85 -> 3500000 | K85: =ABS(J85) -> 3500000 | L85: =IF(H85=0,"",J85/H85) -> 0.07 | M85: =IFERROR(INDEX(tReal27[[Ene]:[Dic]],MATCH(C85,tReal27[Cuenta],0),12),0) -> 52501000
A86: ='PPTO 2027'!$E$28 -> Administración | B86: ='PPTO 2027'!$C$28 -> Gastos de administración | C86: ='PPTO 2027'!$B$28 -> Arrendamiento de oficinas | D86: ='PPTO 2027'!$D$28 -> Gasto | E86: ='PPTO 2027'!$F$28 -> IPC | F86: =CHOOSE(1,"Ene","Feb","Mar","Abr","May","Jun","Jul","Ago","Sep","Oct","Nov","Dic") -> Ene | G86: 1 | H86: ='PPTO 2027'!$I$28 -> 15000000 | I86: ='PPTO 2027'!$V$28 -> 15600000 | J86: =I86-H86 -> 600000 | K86: =ABS(J86) -> 600000 | L86: =IF(H86=0,"",J86/H86) -> 0.04 | M86: =IFERROR(INDEX(tReal27[[Ene]:[Dic]],MATCH(C86,tReal27[Cuenta],0),1),0) -> 15520000
A87: ='PPTO 2027'!$E$28 -> Administración | B87: ='PPTO 2027'!$C$28 -> Gastos de administración | C87: ='PPTO 2027'!$B$28 -> Arrendamiento de oficinas | D87: ='PPTO 2027'!$D$28 -> Gasto | E87: ='PPTO 2027'!$F$28 -> IPC | F87: =CHOOSE(2,"Ene","Feb","Mar","Abr","May","Jun","Jul","Ago","Sep","Oct","Nov","Dic") -> Feb | G87: 2 | H87: ='PPTO 2027'!$J$28 -> 15000000 | I87: ='PPTO 2027'!$W$28 -> 15600000 | J87: =I87-H87 -> 600000 | K87: =ABS(J87) -> 600000 | L87: =IF(H87=0,"",J87/H87) -> 0.04 | M87: =IFERROR(INDEX(tReal27[[Ene]:[Dic]],MATCH(C87,tReal27[Cuenta],0),2),0) -> 15871000
A88: ='PPTO 2027'!$E$28 -> Administración | B88: ='PPTO 2027'!$C$28 -> Gastos de administración | C88: ='PPTO 2027'!$B$28 -> Arrendamiento de oficinas | D88: ='PPTO 2027'!$D$28 -> Gasto | E88: ='PPTO 2027'!$F$28 -> IPC | F88: =CHOOSE(3,"Ene","Feb","Mar","Abr","May","Jun","Jul","Ago","Sep","Oct","Nov","Dic") -> Mar | G88: 3 | H88: ='PPTO 2027'!$K$28 -> 15000000 | I88: ='PPTO 2027'!$X$28 -> 15600000 | J88: =I88-H88 -> 600000 | K88: =ABS(J88) -> 600000 | L88: =IF(H88=0,"",J88/H88) -> 0.04 | M88: =IFERROR(INDEX(tReal27[[Ene]:[Dic]],MATCH(C88,tReal27[Cuenta],0),3),0) -> 16161000
A89: ='PPTO 2027'!$E$28 -> Administración | B89: ='PPTO 2027'!$C$28 -> Gastos de administración | C89: ='PPTO 2027'!$B$28 -> Arrendamiento de oficinas | D89: ='PPTO 2027'!$D$28 -> Gasto | E89: ='PPTO 2027'!$F$28 -> IPC | F89: =CHOOSE(4,"Ene","Feb","Mar","Abr","May","Jun","Jul","Ago","Sep","Oct","Nov","Dic") -> Abr | G89: 4 | H89: ='PPTO 2027'!$L$28 -> 15000000 | I89: ='PPTO 2027'!$Y$28 -> 15600000 | J89: =I89-H89 -> 600000 | K89: =ABS(J89) -> 600000 | L89: =IF(H89=0,"",J89/H89) -> 0.04 | M89: =IFERROR(INDEX(tReal27[[Ene]:[Dic]],MATCH(C89,tReal27[Cuenta],0),4),0) -> 15854000
A90: ='PPTO 2027'!$E$28 -> Administración | B90: ='PPTO 2027'!$C$28 -> Gastos de administración | C90: ='PPTO 2027'!$B$28 -> Arrendamiento de oficinas | D90: ='PPTO 2027'!$D$28 -> Gasto | E90: ='PPTO 2027'!$F$28 -> IPC | F90: =CHOOSE(5,"Ene","Feb","Mar","Abr","May","Jun","Jul","Ago","Sep","Oct","Nov","Dic") -> May | G90: 5 | H90: ='PPTO 2027'!$M$28 -> 15000000 | I90: ='PPTO 2027'!$Z$28 -> 15600000 | J90: =I90-H90 -> 600000 | K90: =ABS(J90) -> 600000 | L90: =IF(H90=0,"",J90/H90) -> 0.04 | M90: =IFERROR(INDEX(tReal27[[Ene]:[Dic]],MATCH(C90,tReal27[Cuenta],0),5),0) -> 15363000
A91: ='PPTO 2027'!$E$28 -> Administración | B91: ='PPTO 2027'!$C$28 -> Gastos de administración | C91: ='PPTO 2027'!$B$28 -> Arrendamiento de oficinas | D91: ='PPTO 2027'!$D$28 -> Gasto | E91: ='PPTO 2027'!$F$28 -> IPC | F91: =CHOOSE(6,"Ene","Feb","Mar","Abr","May","Jun","Jul","Ago","Sep","Oct","Nov","Dic") -> Jun | G91: 6 | H91: ='PPTO 2027'!$N$28 -> 15000000 | I91: ='PPTO 2027'!$AA$28 -> 15600000 | J91: =I91-H91 -> 600000 | K91: =ABS(J91) -> 600000 | L91: =IF(H91=0,"",J91/H91) -> 0.04 | M91: =IFERROR(INDEX(tReal27[[Ene]:[Dic]],MATCH(C91,tReal27[Cuenta],0),6),0) -> 15493000
A92: ='PPTO 2027'!$E$28 -> Administración | B92: ='PPTO 2027'!$C$28 -> Gastos de administración | C92: ='PPTO 2027'!$B$28 -> Arrendamiento de oficinas | D92: ='PPTO 2027'!$D$28 -> Gasto | E92: ='PPTO 2027'!$F$28 -> IPC | F92: =CHOOSE(7,"Ene","Feb","Mar","Abr","May","Jun","Jul","Ago","Sep","Oct","Nov","Dic") -> Jul | G92: 7 | H92: ='PPTO 2027'!$O$28 -> 15000000 | I92: ='PPTO 2027'!$AB$28 -> 15600000 | J92: =I92-H92 -> 600000 | K92: =ABS(J92) -> 600000 | L92: =IF(H92=0,"",J92/H92) -> 0.04 | M92: =IFERROR(INDEX(tReal27[[Ene]:[Dic]],MATCH(C92,tReal27[Cuenta],0),7),0) -> 15741000
A93: ='PPTO 2027'!$E$28 -> Administración | B93: ='PPTO 2027'!$C$28 -> Gastos de administración | C93: ='PPTO 2027'!$B$28 -> Arrendamiento de oficinas | D93: ='PPTO 2027'!$D$28 -> Gasto | E93: ='PPTO 2027'!$F$28 -> IPC | F93: =CHOOSE(8,"Ene","Feb","Mar","Abr","May","Jun","Jul","Ago","Sep","Oct","Nov","Dic") -> Ago | G93: 8 | H93: ='PPTO 2027'!$P$28 -> 15000000 | I93: ='PPTO 2027'!$AC$28 -> 15600000 | J93: =I93-H93 -> 600000 | K93: =ABS(J93) -> 600000 | L93: =IF(H93=0,"",J93/H93) -> 0.04 | M93: =IFERROR(INDEX(tReal27[[Ene]:[Dic]],MATCH(C93,tReal27[Cuenta],0),8),0) -> 15615000
A94: ='PPTO 2027'!$E$28 -> Administración | B94: ='PPTO 2027'!$C$28 -> Gastos de administración | C94: ='PPTO 2027'!$B$28 -> Arrendamiento de oficinas | D94: ='PPTO 2027'!$D$28 -> Gasto | E94: ='PPTO 2027'!$F$28 -> IPC | F94: =CHOOSE(9,"Ene","Feb","Mar","Abr","May","Jun","Jul","Ago","Sep","Oct","Nov","Dic") -> Sep | G94: 9 | H94: ='PPTO 2027'!$Q$28 -> 15000000 | I94: ='PPTO 2027'!$AD$28 -> 15600000 | J94: =I94-H94 -> 600000 | K94: =ABS(J94) -> 600000 | L94: =IF(H94=0,"",J94/H94) -> 0.04 | M94: =IFERROR(INDEX(tReal27[[Ene]:[Dic]],MATCH(C94,tReal27[Cuenta],0),9),0) -> 15559000
A95: ='PPTO 2027'!$E$28 -> Administración | B95: ='PPTO 2027'!$C$28 -> Gastos de administración | C95: ='PPTO 2027'!$B$28 -> Arrendamiento de oficinas | D95: ='PPTO 2027'!$D$28 -> Gasto | E95: ='PPTO 2027'!$F$28 -> IPC | F95: =CHOOSE(10,"Ene","Feb","Mar","Abr","May","Jun","Jul","Ago","Sep","Oct","Nov","Dic") -> Oct | G95: 10 | H95: ='PPTO 2027'!$R$28 -> 15000000 | I95: ='PPTO 2027'!$AE$28 -> 15600000 | J95: =I95-H95 -> 600000 | K95: =ABS(J95) -> 600000 | L95: =IF(H95=0,"",J95/H95) -> 0.04 | M95: =IFERROR(INDEX(tReal27[[Ene]:[Dic]],MATCH(C95,tReal27[Cuenta],0),10),0) -> 15300000
A96: ='PPTO 2027'!$E$28 -> Administración | B96: ='PPTO 2027'!$C$28 -> Gastos de administración | C96: ='PPTO 2027'!$B$28 -> Arrendamiento de oficinas | D96: ='PPTO 2027'!$D$28 -> Gasto | E96: ='PPTO 2027'!$F$28 -> IPC | F96: =CHOOSE(11,"Ene","Feb","Mar","Abr","May","Jun","Jul","Ago","Sep","Oct","Nov","Dic") -> Nov | G96: 11 | H96: ='PPTO 2027'!$S$28 -> 15000000 | I96: ='PPTO 2027'!$AF$28 -> 15600000 | J96: =I96-H96 -> 600000 | K96: =ABS(J96) -> 600000 | L96: =IF(H96=0,"",J96/H96) -> 0.04 | M96: =IFERROR(INDEX(tReal27[[Ene]:[Dic]],MATCH(C96,tReal27[Cuenta],0),11),0) -> 15119000
A97: ='PPTO 2027'!$E$28 -> Administración | B97: ='PPTO 2027'!$C$28 -> Gastos de administración | C97: ='PPTO 2027'!$B$28 -> Arrendamiento de oficinas | D97: ='PPTO 2027'!$D$28 -> Gasto | E97: ='PPTO 2027'!$F$28 -> IPC | F97: =CHOOSE(12,"Ene","Feb","Mar","Abr","May","Jun","Jul","Ago","Sep","Oct","Nov","Dic") -> Dic | G97: 12 | H97: ='PPTO 2027'!$T$28 -> 15000000 | I97: ='PPTO 2027'!$AG$28 -> 15600000 | J97: =I97-H97 -> 600000 | K97: =ABS(J97) -> 600000 | L97: =IF(H97=0,"",J97/H97) -> 0.04 | M97: =IFERROR(INDEX(tReal27[[Ene]:[Dic]],MATCH(C97,tReal27[Cuenta],0),12),0) -> 15765000
A98: ='PPTO 2027'!$E$29 -> Administración | B98: ='PPTO 2027'!$C$29 -> Gastos de administración | C98: ='PPTO 2027'!$B$29 -> Servicios públicos | D98: ='PPTO 2027'!$D$29 -> Gasto | E98: ='PPTO 2027'!$F$29 -> IPC | F98: =CHOOSE(1,"Ene","Feb","Mar","Abr","May","Jun","Jul","Ago","Sep","Oct","Nov","Dic") -> Ene | G98: 1 | H98: ='PPTO 2027'!$I$29 -> 7000000 | I98: ='PPTO 2027'!$V$29 -> 7280000 | J98: =I98-H98 -> 280000 | K98: =ABS(J98) -> 280000 | L98: =IF(H98=0,"",J98/H98) -> 0.04 | M98: =IFERROR(INDEX(tReal27[[Ene]:[Dic]],MATCH(C98,tReal27[Cuenta],0),1),0) -> 7348000
